Workbook

Sheet README
A1: CPI Component Workbook
A3: Build timestamp | B3: 2026-10-24 18:32 UTC
A4: Data as of | B4: Sep 2026
A5: Latest 3 reference months | B5: Jul 2026, Aug 2026, Sep 2026
A6: Next CPI release | B6: 2027-05-12 08:30AM
A7: BLS_API_KEY detected | B7: yes
A8: Refresh command | B8: BLS_API_KEY=... python build_workbook.py
A9: Source of truth | B9: BLS Public Data API, LABSTAT cu.item/cu.series, and BLS relative-importance tables
A12: Notes
A13: Derived m/m, y/y, price-updated relative importance, and contribution cells are Excel formulas that reference Data_NSA and Data_SA.
A15: Primary BLS URLs
A16: bls_api | B16: https://api.bls.gov/publicAPI/v2/timeseries/data/
A17: api_registration | B17: https://data.bls.gov/registrationEngine/
A18: labstat_base | B18: https://download.bls.gov/pub/time.series/cu/
A19: cu_item | B19: https://download.bls.gov/pub/time.series/cu/cu.item
A20: cu_series | B20: https://download.bls.gov/pub/time.series/cu/cu.series
A21: cu_current | B21: https://download.bls.gov/pub/time.series/cu/cu.data.0.Current
A22: relative_importance | B22: https://www.bls.gov/cpi/tables/relative-importance/
A23: relative_importance_xlsx | B23: https://www.bls.gov/web/cpi/cpi-relative-importance.xlsx
A24: news_release | B24: https://www.bls.gov/news.release/cpi.nr0.htm
A25: news_table_1 | B25: https://www.bls.gov/news.release/cpi.t01.htm
A26: news_table_2 | B26: https://www.bls.gov/news.release/cpi.t02.htm
A27: supplemental | B27: https://www.bls.gov/web/cpi.supp.toc.htm
... A36: cost_weights | B36: https://www.bls.gov/cpi/tables/consumer-expenditure/cost-weights.htm

Sheet Dashboard
A1: CPI Dashboard
A3: Data as of | B3: Sep 2026
A5: Headline and core | F5: Summary groups
A6: Metric | B6: Jul 2026 | C6: Aug 2026 | D6: Sep 2026 | F6: Group | G6: Latest SA m/m | H6: Contribution pp
A7: All items SA m/m | B7: =IFERROR(INDEX(Latest_3M!$K:$K,MATCH("SA0",Latest_3M!$A:$A,0)),"") | C7: =IFERROR(INDEX(Latest_3M!$Q:$Q,MATCH("SA0",Latest_3M!$A:$A,0)),"") | D7: =IFERROR(INDEX(Latest_3M!$W:$W,MATCH("SA0",Latest_3M!$A:$A,0)),"") | F7: Food | G7: =IFERROR(INDEX(Latest_3M!$W:$W,MATCH("SAF1",Latest_3M!$A:$A,0)),"") | H7: =IFERROR(INDEX(Latest_3M!$Z:$Z,MATCH("SAF1",Latest_3M!$A:$A,0)),"")
A8: All items NSA y/y | B8: =IFERROR(INDEX(Latest_3M!$L:$L,MATCH("SA0",Latest_3M!$A:$A,0)),"") | C8: =IFERROR(INDEX(Latest_3M!$R:$R,MATCH("SA0",Latest_3M!$A:$A,0)),"") | D8: =IFERROR(INDEX(Latest_3M!$X:$X,MATCH("SA0",Latest_3M!$A:$A,0)),"") | F8: Energy | G8: =IFERROR(INDEX(Latest_3M!$W:$W,MATCH("SA0E",Latest_3M!$A:$A,0)),"") | H8: =IFERROR(INDEX(Latest_3M!$Z:$Z,MATCH("SA0E",Latest_3M!$A:$A,0)),"")
A9: Core SA m/m | B9: =IFERROR(INDEX(Latest_3M!$K:$K,MATCH("SA0L1E",Latest_3M!$A:$A,0)),"") | C9: =IFERROR(INDEX(Latest_3M!$Q:$Q,MATCH("SA0L1E",Latest_3M!$A:$A,0)),"") | D9: =IFERROR(INDEX(Latest_3M!$W:$W,MATCH("SA0L1E",Latest_3M!$A:$A,0)),"") | F9: Shelter | G9: =IFERROR(INDEX(Latest_3M!$W:$W,MATCH("SAH1",Latest_3M!$A:$A,0)),"") | H9: =IFERROR(INDEX(Latest_3M!$Z:$Z,MATCH("SAH1",Latest_3M!$A:$A,0)),"")
A10: Core NSA y/y | B10: =IFERROR(INDEX(Latest_3M!$L:$L,MATCH("SA0L1E",Latest_3M!$A:$A,0)),"") | C10: =IFERROR(INDEX(Latest_3M!$R:$R,MATCH("SA0L1E",Latest_3M!$A:$A,0)),"") | D10: =IFERROR(INDEX(Latest_3M!$X:$X,MATCH("SA0L1E",Latest_3M!$A:$A,0)),"") | F10: Core | G10: =IFERROR(INDEX(Latest_3M!$W:$W,MATCH("SA0L1E",Latest_3M!$A:$A,0)),"") | H10: =IFERROR(INDEX(Latest_3M!$Z:$Z,MATCH("SA0L1E",Latest_3M!$A:$A,0)),"")
A13: Top contributors, Sep 2026
A14: Rank | B14: item_code | C14: component | D14: SA contribution pp
A15: 1 | B15: SA0 | C15: All items | D15: =IFERROR(INDEX(Latest_3M!$Z:$Z,MATCH(B15,Latest_3M!$A:$A,0)),"")
A16: 2 | B16: SA0L1 | C16: All items less food | D16: =IFERROR(INDEX(Latest_3M!$Z:$Z,MATCH(B16,Latest_3M!$A:$A,0)),"")
A17: 3 | B17: SA0L5 | C17: All items less medical care | D17: =IFERROR(INDEX(Latest_3M!$Z:$Z,MATCH(B17,Latest_3M!$A:$A,0)),"")
A18: 4 | B18: SA0L2 | C18: All items less shelter | D18: =IFERROR(INDEX(Latest_3M!$Z:$Z,MATCH(B18,Latest_3M!$A:$A,0)),"")
A19: 5 | B19: SAC | C19: Commodities | D19: =IFERROR(INDEX(Latest_3M!$Z:$Z,MATCH(B19,Latest_3M!$A:$A,0)),"")
A20: 6 | B20: SACL11 | C20: Commodities less food and beverages | D20: =IFERROR(INDEX(Latest_3M!$Z:$Z,MATCH(B20,Latest_3M!$A:$A,0)),"")
A21: 7 | B21: SACL1 | C21: Commodities less food | D21: =IFERROR(INDEX(Latest_3M!$Z:$Z,MATCH(B21,Latest_3M!$A:$A,0)),"")
A22: 8 | B22: SACE | C22: Energy commodities | D22: =IFERROR(INDEX(Latest_3M!$Z:$Z,MATCH(B22,Latest_3M!$A:$A,0)),"")
A23: 9 | B23: SA0E | C23: Energy | D23: =IFERROR(INDEX(Latest_3M!$Z:$Z,MATCH(B23,Latest_3M!$A:$A,0)),"")
A24: 10 | B24: SANL13 | C24: Nondurables less food and apparel | D24: =IFERROR(INDEX(Latest_3M!$Z:$Z,MATCH(B24,Latest_3M!$A:$A,0)),"")

Sheet Component_Tree
A1: item_code | B1: name | C1: parent | D1: display_level | E1: is_item_stratum | F1: sort_sequence
A2: SA0 | B2: All items | D2: 0 | E2: TRUE | F2: 1
A3: AA0 | B3: All items - old base | C3: SA0 | D3: 0 | E3: TRUE | F3: 2
A4: SAF | B4: Food and beverages | C4: SA0 | D4: 0 | E4: FALSE | F4: 3
A5: SAF1 | B5: Food | C5: SAF | D5: 1 | E5: FALSE | F5: 4
A6: SAF11 | B6: Food at home | C6: SAF1 | D6: 2 | E6: FALSE | F6: 5
A7: SAF111 | B7: Cereals and bakery products | C7: SAF11 | D7: 3 | E7: FALSE | F7: 6
A8: SEFA | B8: Cereals and cereal products | C8: SAF111 | D8: 4 | E8: FALSE | F8: 7
A9: SEFA01 | B9: Flour and prepared flour mixes | C9: SEFA | D9: 5 | E9: TRUE | F9: 8
A10: SEFA02 | B10: Breakfast cereal | C10: SEFA | D10: 5 | E10: TRUE | F10: 9
A11: SEFA03 | B11: Rice, pasta, cornmeal | C11: SEFA | D11: 5 | E11: FALSE | F11: 10
A12: SS01031 | B12: Rice | C12: SEFA03 | D12: 6 | E12: TRUE | F12: 11
A13: SEFB | B13: Bakery products | C13: SAF111 | D13: 4 | E13: FALSE | F13: 12
A14: SEFB01 | B14: Bread | C14: SEFB | D14: 5 | E14: FALSE | F14: 13
... A399: SERAS | B399: Video and audio services | C399: SAG | D399: 1 | E399: TRUE | F399: 398
A400: SA0R | B400: Purchasing power of the consumer dollar | D400: 0 | E400: TRUE | F400: 399
A401: AA0R | B401: Purchasing power of the consumer dollar - old base | D401: 0 | E401: TRUE | F401: 400

Sheet Methodology
A1: item_code | B1: component | C1: formula | D1: collection | E1: qa_method | F1: alt_data | G1: factsheet_or_index | H1: handbook_calculation | I1: nsa_series | J1: sa_series
A2: SA0 | B2: All items | C2: aggregate | D2: aggregate | E2: aggregate | G2: factsheet/index | H2: calculation handbook | I2: CUUR0000SA0 | J2: CUSR0000SA0
A3: AA0 | B3: All items - old base | C3: GM | D3: monthly in New York/Los Angeles/Chicago; often bimonthly elsewhere | E3: cell-relative imputation for missing quotes; direct comparison/direct QA as applicable | G3: factsheet/index | H3: calculation handbook | I3: CUUR0000AA0
A4: SAF | B4: Food and beverages | C4: aggregate | D4: aggregate | E4: aggregate of component methods | G4: factsheet/index | H4: calculation handbook | I4: CUUR0000SAF | J4: CUSR0000SAF
A5: SAF1 | B5: Food | C5: aggregate | D5: aggregate | E5: aggregate | G5: factsheet/index | H5: calculation handbook | I5: CUUR0000SAF1 | J5: CUSR0000SAF1
A6: SAF11 | B6: Food at home | C6: GM | D6: direct collection; monthly in all areas | E6: cell-relative imputation common; seasonal-item pricing rules | G6: factsheet/index | H6: calculation handbook | I6: CUUR0000SAF11 | J6: CUSR0000SAF11
A7: SAF111 | B7: Cereals and bakery products | C7: GM | D7: monthly | E7: cell-relative | G7: factsheet/index | H7: calculation handbook | I7: CUUR0000SAF111 | J7: CUSR0000SAF111
A8: SEFA | B8: Cereals and cereal products | C8: aggregate | D8: aggregate | E8: aggregate of component methods | G8: factsheet/index | H8: calculation handbook | I8: CUUR0000SEFA | J8: CUSR0000SEFA
A9: SEFA01 | B9: Flour and prepared flour mixes | C9: GM | D9: monthly food collection where sampled | E9: cell-relative imputation for missing quotes; direct comparison/direct QA as applicable | G9: factsheet/index | H9: calculation handbook | I9: CUUR0000SEFA01 | J9: CUSR0000SEFA01
A10: SEFA02 | B10: Breakfast cereal | C10: GM | D10: monthly food collection where sampled | E10: cell-relative imputation for missing quotes; direct comparison/direct QA as applicable | G10: factsheet/index | H10: calculation handbook | I10: CUUR0000SEFA02 | J10: CUSR0000SEFA02
A11: SEFA03 | B11: Rice, pasta, cornmeal | C11: aggregate | D11: aggregate | E11: aggregate of component methods | G11: factsheet/index | H11: calculation handbook | I11: CUUR0000SEFA03 | J11: CUSR0000SEFA03
A12: SS01031 | B12: Rice | C12: GM | D12: monthly in New York/Los Angeles/Chicago; often bimonthly elsewhere | E12: cell-relative imputation for missing quotes; direct comparison/direct QA as applicable | G12: factsheet/index | H12: calculation handbook | I12: CUUR0000SS01031
A13: SEFB | B13: Bakery products | C13: aggregate | D13: aggregate | E13: aggregate of component methods | G13: factsheet/index | H13: calculation handbook | I13: CUUR0000SEFB | J13: CUSR0000SEFB
A14: SEFB01 | B14: Bread | C14: aggregate | D14: aggregate | E14: aggregate of component methods | G14: factsheet/index | H14: calculation handbook | I14: CUUR0000SEFB01 | J14: CUSR0000SEFB01
A15: SS02011 | B15: White bread | C15: GM | D15: monthly in New York/Los Angeles/Chicago; often bimonthly elsewhere | E15: cell-relative imputation for missing quotes; direct comparison/direct QA as applicable | G15: factsheet/index | H15: calculation handbook | I15: CUUR0000SS02011
A16: SS02021 | B16: Bread other than white | C16: GM | D16: monthly in New York/Los Angeles/Chicago; often bimonthly elsewhere | E16: cell-relative imputation for missing quotes; direct comparison/direct QA as applicable | G16: factsheet/index | H16: calculation handbook | I16: CUUR0000SS02021
A17: SEFB02 | B17: Fresh biscuits, rolls, muffins | C17: GM | D17: monthly food collection where sampled | E17: cell-relative imputation for missing quotes; direct comparison/direct QA as applicable | G17: factsheet/index | H17: calculation handbook | I17: CUUR0000SEFB02 | J17: CUSR0000SEFB02
A18: SEFB03 | B18: Cakes, cupcakes, and cookies | C18: aggregate | D18: aggregate | E18: aggregate of component methods | G18: factsheet/index | H18: calculation handbook | I18: CUUR0000SEFB03 | J18: CUSR0000SEFB03
A19: SS02041 | B19: Fresh cakes and cupcakes | C19: GM | D19: monthly in New York/Los Angeles/Chicago; often bimonthly elsewhere | E19: cell-relative imputation for missing quotes; direct comparison/direct QA as applicable | G19: factsheet/index | H19: calculation handbook | I19: CUUR0000SS02041
A20: SS02042 | B20: Cookies | C20: GM | D20: monthly in New York/Los Angeles/Chicago; often bimonthly elsewhere | E20: cell-relative imputation for missing quotes; direct comparison/direct QA as applicable | G20: factsheet/index | H20: calculation handbook | I20: CUUR0000SS02042 | J20: CUSR0000SS02042
A21: SEFB04 | B21: Other bakery products | C21: aggregate | D21: aggregate | E21: aggregate of component methods | G21: factsheet/index | H21: calculation handbook | I21: CUUR0000SEFB04 | J21: CUSR0000SEFB04
A22: SS02063 | B22: Fresh sweetrolls, coffeecakes, doughnuts | C22: GM | D22: monthly in New York/Los Angeles/Chicago; often bimonthly elsewhere | E22: cell-relative imputation for missing quotes; direct comparison/direct QA as applicable | G22: factsheet/index | H22: calculation handbook | I22: CUUR0000SS02063
A23: SS0206A | B23: Crackers, bread, and cracker products | C23: GM | D23: monthly in New York/Los Angeles/Chicago; often bimonthly elsewhere | E23: cell-relative imputation for missing quotes; direct comparison/direct QA as applicable | G23: factsheet/index | H23: calculation handbook | I23: CUUR0000SS0206A | J23: CUSR0000SS0206A
A24: SS0206B | B24: Frozen and refrigerated bakery products, pies, tarts, turnovers | C24: GM | D24: monthly in New York/Los Angeles/Chicago; often bimonthly elsewhere | E24: cell-relative imputation for missing quotes; direct comparison/direct QA as applicable | G24: factsheet/index | H24: calculation handbook | I24: CUUR0000SS0206B | J24: CUSR0000SS0206B
A25: SAF112 | B25: Meats, poultry, fish, and eggs | C25: GM | D25: monthly | E25: cell-relative | G25: factsheet/index | H25: calculation handbook | I25: CUUR0000SAF112 | J25: CUSR0000SAF112
A26: SAF1121 | B26: Meats, poultry, and fish | C26: aggregate | D26: aggregate | E26: aggregate of component methods | G26: factsheet/index | H26: calculation handbook | I26: CUUR0000SAF1121 | J26: CUSR0000SAF1121
A27: SAF11211 | B27: Meats | C27: aggregate | D27: aggregate | E27: aggregate of component methods | G27: factsheet/index | H27: calculation handbook | I27: CUUR0000SAF11211 | J27: CUSR0000SAF11211
A28: SEFC | B28: Beef and veal | C28: aggregate | D28: aggregate | E28: aggregate of component methods | G28: factsheet/index | H28: calculation handbook | I28: CUUR0000SEFC | J28: CUSR0000SEFC
A29: SEFC01 | B29: Uncooked ground beef | C29: GM | D29: monthly food collection where sampled | E29: cell-relative imputation for missing quotes; direct comparison/direct QA as applicable | G29: factsheet/index | H29: calculation handbook | I29: CUUR0000SEFC01 | J29: CUSR0000SEFC01
A30: SEFC02 | B30: Uncooked beef roasts | C30: GM | D30: monthly food collection where sampled | E30: cell-relative imputation for missing quotes; direct comparison/direct QA as applicable | G30: factsheet/index | H30: calculation handbook | I30: CUUR0000SEFC02 | J30: CUSR0000SEFC02
A31: SEFC03 | B31: Uncooked beef steaks | C31: GM | D31: monthly food collection where sampled | E31: cell-relative imputation for missing quotes; direct comparison/direct QA as applicable | G31: factsheet/index | H31: calculation handbook | I31: CUUR0000SEFC03 | J31: CUSR0000SEFC03
A32: SEFC04 | B32: Uncooked other beef and veal | C32: GM | D32: monthly food collection where sampled | E32: cell-relative imputation for missing quotes; direct comparison/direct QA as applicable | G32: factsheet/index | H32: calculation handbook | I32: CUUR0000SEFC04
A33: SEFD | B33: Pork | C33: aggregate | D33: aggregate | E33: aggregate of component methods | G33: factsheet/index | H33: calculation handbook | I33: CUUR0000SEFD | J33: CUSR0000SEFD
A34: SEFD01 | B34: Bacon, breakfast sausage, and related products | C34: aggregate | D34: aggregate | E34: aggregate of component methods | G34: factsheet/index | H34: calculation handbook | I34: CUUR0000SEFD01 | J34: CUSR0000SEFD01
A35: SS04011 | B35: Bacon and related products | C35: GM | D35: monthly in New York/Los Angeles/Chicago; often bimonthly elsewhere | E35: cell-relative imputation for missing quotes; direct comparison/direct QA as applicable | G35: factsheet/index | H35: calculation handbook | I35: CUUR0000SS04011 | J35: CUSR0000SS04011
A36: SS04012 | B36: Breakfast sausage and related products | C36: GM | D36: monthly in New York/Los Angeles/Chicago; often bimonthly elsewhere | E36: cell-relative imputation for missing quotes; direct comparison/direct QA as applicable | G36: factsheet/index | H36: calculation handbook | I36: CUUR0000SS04012 | J36: CUSR0000SS04012
A37: SEFD02 | B37: Ham | C37: aggregate | D37: aggregate | E37: aggregate of component methods | G37: factsheet/index | H37: calculation handbook | I37: CUUR0000SEFD02 | J37: CUSR0000SEFD02
A38: SS04031 | B38: Ham, excluding canned | C38: GM | D38: monthly in New York/Los Angeles/Chicago; often bimonthly elsewhere | E38: cell-relative imputation for missing quotes; direct comparison/direct QA as applicable | G38: factsheet/index | H38: calculation handbook | I38: CUUR0000SS04031 | J38: CUSR0000SS04031
A39: SEFD03 | B39: Pork chops | C39: GM | D39: monthly food collection where sampled | E39: cell-relative imputation for missing quotes; direct comparison/direct QA as applicable | G39: factsheet/index | H39: calculation handbook | I39: CUUR0000SEFD03 | J39: CUSR0000SEFD03
A40: SEFD04 | B40: Other pork including roasts, steaks, and ribs | C40: GM | D40: monthly food collection where sampled | E40: cell-relative imputation for missing quotes; direct comparison/direct QA as applicable | G40: factsheet/index | H40: calculation handbook | I40: CUUR0000SEFD04 | J40: CUSR0000SEFD04
A41: SEFE | B41: Other meats | C41: aggregate | D41: aggregate | E41: aggregate of component methods | G41: factsheet/index | H41: calculation handbook | I41: CUUR0000SEFE | J41: CUSR0000SEFE
A42: SS05011 | B42: Frankfurters | C42: GM | D42: monthly in New York/Los Angeles/Chicago; often bimonthly elsewhere | E42: cell-relative imputation for missing quotes; direct comparison/direct QA as applicable | G42: factsheet/index | H42: calculation handbook | I42: CUUR0000SS05011 | J42: CUSR0000SS05011
A43: SS0501A | B43: Lunchmeats | C43: GM | D43: monthly in New York/Los Angeles/Chicago; often bimonthly elsewhere | E43: cell-relative imputation for missing quotes; direct comparison/direct QA as applicable | G43: factsheet/index | H43: calculation handbook | I43: CUUR0000SS0501A | J43: CUSR0000SS0501A
A44: SS05014 | B44: Lamb and organ meats | C44: GM | D44: monthly in New York/Los Angeles/Chicago; often bimonthly elsewhere | E44: cell-relative imputation for missing quotes; direct comparison/direct QA as applicable | G44: factsheet/index | H44: calculation handbook | I44: CUUR0000SS05014
A45: SS05015 | B45: Lamb and mutton | C45: GM | D45: monthly in New York/Los Angeles/Chicago; often bimonthly elsewhere | E45: cell-relative imputation for missing quotes; direct comparison/direct QA as applicable | G45: factsheet/index | H45: calculation handbook | I45: CUUR0000SS05015
A46: SEFF | B46: Poultry | C46: aggregate | D46: aggregate | E46: aggregate of component methods | G46: factsheet/index | H46: calculation handbook | I46: CUUR0000SEFF | J46: CUSR0000SEFF
A47: SEFF01 | B47: Chicken | C47: GM | D47: monthly food collection where sampled | E47: cell-relative imputation for missing quotes; direct comparison/direct QA as applicable | G47: factsheet/index | H47: calculation handbook | I47: CUUR0000SEFF01 | J47: CUSR0000SEFF01
A48: SS06011 | B48: Fresh whole chicken | C48: GM | D48: monthly in New York/Los Angeles/Chicago; often bimonthly elsewhere | E48: cell-relative imputation for missing quotes; direct comparison/direct QA as applicable | G48: factsheet/index | H48: calculation handbook | I48: CUUR0000SS06011 | J48: CUSR0000SS06011
A49: SS06021 | B49: Fresh and frozen chicken parts | C49: GM | D49: monthly in New York/Los Angeles/Chicago; often bimonthly elsewhere | E49: cell-relative imputation for missing quotes; direct comparison/direct QA as applicable | G49: factsheet/index | H49: calculation handbook | I49: CUUR0000SS06021 | J49: CUSR0000SS06021
A50: SEFF02 | B50: Other uncooked poultry including turkey | C50: GM | D50: monthly food collection where sampled | E50: cell-relative imputation for missing quotes; direct comparison/direct QA as applicable | G50: factsheet/index | H50: calculation handbook | I50: CUUR0000SEFF02 | J50: CUSR0000SEFF02
A51: SEFG | B51: Fish and seafood | C51: aggregate | D51: aggregate | E51: aggregate of component methods | G51: factsheet/index | H51: calculation handbook | I51: CUUR0000SEFG | J51: CUSR0000SEFG
A52: SEFG01 | B52: Fresh fish and seafood | C52: GM | D52: monthly food collection where sampled | E52: cell-relative imputation for missing quotes; direct comparison/direct QA as applicable | G52: factsheet/index | H52: calculation handbook | I52: CUUR0000SEFG01 | J52: CUSR0000SEFG01
A53: SEFG02 | B53: Processed fish and seafood | C53: aggregate | D53: aggregate | E53: aggregate of component methods | G53: factsheet/index | H53: calculation handbook | I53: CUUR0000SEFG02 | J53: CUSR0000SEFG02
A54: SS07011 | B54: Shelf stable fish and seafood | C54: GM | D54: monthly food collection where sampled | E54: cell-relative imputation for missing quotes; direct comparison/direct QA as applicable | G54: factsheet/index | H54: calculation handbook | I54: CUUR0000SS07011 | J54: CUSR0000SS07011
A55: SS07021 | B55: Frozen fish and seafood | C55: GM | D55: monthly food collection where sampled | E55: cell-relative imputation for missing quotes; direct comparison/direct QA as applicable | G55: factsheet/index | H55: calculation handbook | I55: CUUR0000SS07021 | J55: CUSR0000SS07021
A56: SEFH | B56: Eggs | C56: GM | D56: monthly food collection where sampled | E56: cell-relative imputation for missing quotes; direct comparison/direct QA as applicable | G56: factsheet/index | H56: calculation handbook | I56: CUUR0000SEFH | J56: CUSR0000SEFH
A57: SEFJ | B57: Dairy and related products | C57: GM | D57: monthly | E57: cell-relative | G57: factsheet/index | H57: calculation handbook | I57: CUUR0000SEFJ | J57: CUSR0000SEFJ
... A83: SEFM03 | B83: Other processed fruits and vegetables including dried | C83: aggregate | D83: aggregate | E83: aggregate of component methods | G83: factsheet/index | H83: calculation handbook | I83: CUUR0000SEFM03 | J83: CUSR0000SEFM03
A84: SS14022 | B84: Dried beans, peas, and lentils | C84: GM | D84: monthly in New York/Los Angeles/Chicago; often bimonthly elsewhere | E84: cell-relative imputation for missing quotes; direct comparison/direct QA as applicable | G84: factsheet/index | H84: calculation handbook | I84: CUUR0000SS14022
A85: SAF114 | B85: Nonalcoholic beverages and beverage materials | C85: GM | D85: monthly | E85: cell-relative | G85: factsheet/index | H85: calculation handbook | I85: CUUR0000SAF114 | J85: CUSR0000SAF114
A86: SEFN | B86: Juices and nonalcoholic drinks | C86: aggregate | D86: aggregate | E86: aggregate of component methods | G86: factsheet/index | H86: calculation handbook | I86: CUUR0000SEFN | J86: CUSR0000SEFN
A87: SEFN01 | B87: Carbonated drinks | C87: GM | D87: monthly food collection where sampled | E87: cell-relative imputation for missing quotes; direct comparison/direct QA as applicable | G87: factsheet/index | H87: calculation handbook | I87: CUUR0000SEFN01 | J87: CUSR0000SEFN01
A88: SEFN02 | B88: Frozen noncarbonated juices and drinks | C88: GM | D88: monthly food collection where sampled | E88: cell-relative imputation for missing quotes; direct comparison/direct QA as applicable | G88: factsheet/index | H88: calculation handbook | I88: CUUR0000SEFN02
A89: SEFN03 | B89: Nonfrozen noncarbonated juices and drinks | C89: GM | D89: monthly food collection where sampled | E89: cell-relative imputation for missing quotes; direct comparison/direct QA as applicable | G89: factsheet/index | H89: calculation handbook | I89: CUUR0000SEFN03 | J89: CUSR0000SEFN03
A90: SEFP | B90: Beverage materials including coffee and tea | C90: aggregate | D90: aggregate | E90: aggregate of component methods | G90: factsheet/index | H90: calculation handbook | I90: CUUR0000SEFP | J90: CUSR0000SEFP
A91: SEFP01 | B91: Coffee | C91: aggregate | D91: aggregate | E91: aggregate of component methods | G91: factsheet/index | H91: calculation handbook | I91: CUUR0000SEFP01 | J91: CUSR0000SEFP01
A92: SS17031 | B92: Roasted coffee | C92: GM | D92: monthly in New York/Los Angeles/Chicago; often bimonthly elsewhere | E92: cell-relative imputation for missing quotes; direct comparison/direct QA as applicable | G92: factsheet/index | H92: calculation handbook | I92: CUUR0000SS17031 | J92: CUSR0000SS17031
A93: SS17032 | B93: Instant coffee | C93: GM | D93: monthly in New York/Los Angeles/Chicago; often bimonthly elsewhere | E93: cell-relative imputation for missing quotes; direct comparison/direct QA as applicable | G93: factsheet/index | H93: calculation handbook | I93: CUUR0000SS17032
A94: SEFP02 | B94: Other beverage materials including tea | C94: GM | D94: monthly food collection where sampled | E94: cell-relative imputation for missing quotes; direct comparison/direct QA as applicable | G94: factsheet/index | H94: calculation handbook | I94: CUUR0000SEFP02 | J94: CUSR0000SEFP02
A95: SAF115 | B95: Other food at home | C95: GM | D95: monthly | E95: cell-relative | G95: factsheet/index | H95: calculation handbook | I95: CUUR0000SAF115 | J95: CUSR0000SAF115
A96: SEFR | B96: Sugar and sweets | C96: aggregate | D96: aggregate | E96: aggregate of component methods | G96: factsheet/index | H96: calculation handbook | I96: CUUR0000SEFR | J96: CUSR0000SEFR
A97: SEFR01 | B97: Sugar and sugar substitutes | C97: GM | D97: monthly food collection where sampled | E97: cell-relative imputation for missing quotes; direct comparison/direct QA as applicable | G97: factsheet/index | H97: calculation handbook | I97: CUUR0000SEFR01 | J97: CUSR0000SEFR01
A98: SEFR02 | B98: Candy and chewing gum | C98: GM | D98: monthly food collection where sampled | E98: cell-relative imputation for missing quotes; direct comparison/direct QA as applicable | G98: factsheet/index | H98: calculation handbook | I98: CUUR0000SEFR02 | J98: CUSR0000SEFR02
A99: SEFR03 | B99: Other sweets | C99: GM | D99: monthly food collection where sampled | E99: cell-relative imputation for missing quotes; direct comparison/direct QA as applicable | G99: factsheet/index | H99: calculation handbook | I99: CUUR0000SEFR03 | J99: CUSR0000SEFR03
A100: SEFS | B100: Fats and oils | C100: aggregate | D100: aggregate | E100: aggregate of component methods | G100: factsheet/index | H100: calculation handbook | I100: CUUR0000SEFS | J100: CUSR0000SEFS
A101: SEFS01 | B101: Butter and margarine | C101: aggregate | D101: aggregate | E101: aggregate of component methods | G101: factsheet/index | H101: calculation handbook | I101: CUUR0000SEFS01 | J101: CUSR0000SEFS01
A102: SS10011 | B102: Butter | C102: GM | D102: monthly in New York/Los Angeles/Chicago; often bimonthly elsewhere | E102: cell-relative imputation for missing quotes; direct comparison/direct QA as applicable | G102: factsheet/index | H102: calculation handbook | I102: CUUR0000SS10011 | J102: CUSR0000SS10011
A103: SS16011 | B103: Margarine | C103: GM | D103: monthly in New York/Los Angeles/Chicago; often bimonthly elsewhere | E103: cell-relative imputation for missing quotes; direct comparison/direct QA as applicable | G103: factsheet/index | H103: calculation handbook | I103: CUUR0000SS16011 | J103: CUSR0000SS16011
A104: SEFS02 | B104: Salad dressing | C104: GM | D104: monthly food collection where sampled | E104: cell-relative imputation for missing quotes; direct comparison/direct QA as applicable | G104: factsheet/index | H104: calculation handbook | I104: CUUR0000SEFS02 | J104: CUSR0000SEFS02
A105: SEFS03 | B105: Other fats and oils including peanut butter | C105: aggregate | D105: aggregate | E105: aggregate of component methods | G105: factsheet/index | H105: calculation handbook | I105: CUUR0000SEFS03 | J105: CUSR0000SEFS03
A106: SS16014 | B106: Peanut butter | C106: GM | D106: monthly in New York/Los Angeles/Chicago; often bimonthly elsewhere | E106: cell-relative imputation for missing quotes; direct comparison/direct QA as applicable | G106: factsheet/index | H106: calculation handbook | I106: CUUR0000SS16014
A107: SEFT | B107: Other foods | C107: aggregate | D107: aggregate | E107: aggregate of component methods | G107: factsheet/index | H107: calculation handbook | I107: CUUR0000SEFT | J107: CUSR0000SEFT
A108: SEFT01 | B108: Soups | C108: GM | D108: monthly food collection where sampled | E108: cell-relative imputation for missing quotes; direct comparison/direct QA as applicable | G108: factsheet/index | H108: calculation handbook | I108: CUUR0000SEFT01 | J108: CUSR0000SEFT01
A109: SEFT02 | B109: Frozen and freeze dried prepared foods | C109: GM | D109: monthly food collection where sampled | E109: cell-relative imputation for missing quotes; direct comparison/direct QA as applicable | G109: factsheet/index | H109: calculation handbook | I109: CUUR0000SEFT02 | J109: CUSR0000SEFT02
A110: SEFT03 | B110: Snacks | C110: GM | D110: monthly food collection where sampled | E110: cell-relative imputation for missing quotes; direct comparison/direct QA as applicable | G110: factsheet/index | H110: calculation handbook | I110: CUUR0000SEFT03 | J110: CUSR0000SEFT03
A111: SEFT04 | B111: Spices, seasonings, condiments, sauces | C111: aggregate | D111: aggregate | E111: aggregate of component methods | G111: factsheet/index | H111: calculation handbook | I111: CUUR0000SEFT04 | J111: CUSR0000SEFT04
A112: SS18041 | B112: Salt and other seasonings and spices | C112: GM | D112: monthly in New York/Los Angeles/Chicago; often bimonthly elsewhere | E112: cell-relative imputation for missing quotes; direct comparison/direct QA as applicable | G112: factsheet/index | H112: calculation handbook | I112: CUUR0000SS18041 | J112: CUSR0000SS18041
A113: SS18042 | B113: Olives, pickles, relishes | C113: GM | D113: monthly in New York/Los Angeles/Chicago; often bimonthly elsewhere | E113: cell-relative imputation for missing quotes; direct comparison/direct QA as applicable | G113: factsheet/index | H113: calculation handbook | I113: CUUR0000SS18042 | J113: CUSR0000SS18042
A114: SS18043 | B114: Sauces and gravies | C114: GM | D114: monthly in New York/Los Angeles/Chicago; often bimonthly elsewhere | E114: cell-relative imputation for missing quotes; direct comparison/direct QA as applicable | G114: factsheet/index | H114: calculation handbook | I114: CUUR0000SS18043 | J114: CUSR0000SS18043
A115: SS1804B | B115: Other condiments | C115: GM | D115: monthly in New York/Los Angeles/Chicago; often bimonthly elsewhere | E115: cell-relative imputation for missing quotes; direct comparison/direct QA as applicable | G115: factsheet/index | H115: calculation handbook | I115: CUUR0000SS1804B | J115: CUSR0000SS1804B
A116: SEFT05 | B116: Baby food and formula | C116: GM | D116: monthly food collection where sampled | E116: cell-relative imputation for missing quotes; direct comparison/direct QA as applicable | G116: factsheet/index | H116: calculation handbook | I116: CUUR0000SEFT05
A117: SEFT06 | B117: Other miscellaneous foods | C117: aggregate | D117: aggregate | E117: aggregate of component methods | G117: factsheet/index | H117: calculation handbook | I117: CUUR0000SEFT06 | J117: CUSR0000SEFT06
A118: SS18064 | B118: Prepared salads | C118: GM | D118: monthly in New York/Los Angeles/Chicago; often bimonthly elsewhere | E118: cell-relative imputation for missing quotes; direct comparison/direct QA as applicable | G118: factsheet/index | H118: calculation handbook | I118: CUUR0000SS18064 | J118: CUSR0000SS18064
A119: SEFV | B119: Food away from home | C119: GM | D119: monthly | E119: slow wage/input pass-through | G119: factsheet/index | H119: calculation handbook | I119: CUUR0000SEFV | J119: CUSR0000SEFV
A120: SEFV01 | B120: Full service meals and snacks | C120: GM | D120: monthly food collection where sampled | E120: cell-relative imputation for missing quotes; direct comparison/direct QA as applicable | G120: factsheet/index | H120: calculation handbook | I120: CUUR0000SEFV01 | J120: CUSR0000SEFV01
A121: SEFV02 | B121: Limited service meals and snacks | C121: GM | D121: monthly food collection where sampled | E121: cell-relative imputation for missing quotes; direct comparison/direct QA as applicable | G121: factsheet/index | H121: calculation handbook | I121: CUUR0000SEFV02
A122: SEFV03 | B122: Food at employee sites and schools | C122: GM | D122: monthly food collection where sampled | E122: cell-relative imputation for missing quotes; direct comparison/direct QA as applicable | G122: factsheet/index | H122: calculation handbook | I122: CUUR0000SEFV03 | J122: CUSR0000SEFV03
A123: SSFV031A | B123: Food at elementary and secondary schools | C123: GM | D123: monthly food collection where sampled | E123: cell-relative imputation for missing quotes; direct comparison/direct QA as applicable | G123: factsheet/index | H123: calculation handbook | I123: CUUR0000SSFV031A | J123: CUSR0000SSFV031A
A124: SEFV04 | B124: Food from vending machines and mobile vendors | C124: GM | D124: monthly food collection where sampled | E124: cell-relative imputation for missing quotes; direct comparison/direct QA as applicable | G124: factsheet/index | H124: calculation handbook | I124: CUUR0000SEFV04
A125: SEFV05 | B125: Other food away from home | C125: GM | D125: monthly food collection where sampled | E125: cell-relative imputation for missing quotes; direct comparison/direct QA as applicable | G125: factsheet/index | H125: calculation handbook | I125: CUUR0000SEFV05 | J125: CUSR0000SEFV05
...

Sheet Weights
A1: item_code | B1: component | C1: series_nsa | D1: December RI % | E1: December RI month | F1: CE weight vintage | G1: 46204 | H1: 46235 | I1: 46266
A2: SA0 | B2: All items | C2: CUUR0000SA0 | D2: 100 | E2: 45992 | F2: 2024 | G2: =IFERROR(100*($D2*(INDEX('Data_NSA'!$A:$OK,MATCH(G$1,'Data_NSA'!$A:$A,0),MATCH($C2,'Data_NSA'!$1:$1,0))/INDEX('Data_NSA'!$A:$OK,MATCH($E2,'Data_NSA'!$A:$A,0),MATCH($C2,'Data_NSA'!$1:$1,0))))/(100*(INDEX('Data_NSA'!$A:$OK,MATCH(G$1,'Data_NSA'!$A:$A,0),MATCH("CUUR0000SA0",'Data_NSA'!$1:$1,0))/INDEX('Data_NSA'!$A:$OK,MATCH($E2,'Data_NSA'!$A:$A,0),MATCH("CUUR0000SA0",'Data_NSA'!$1:$1,0)))),"") | H2: =IFERROR(100*($D2*(INDEX('Data_NSA'!$A:$OK,MATCH(H$1,'Data_NSA'!$A:$A,0),MATCH($C2,'Data_NSA'!$1:$1,0))/INDEX('Data_NSA'!$A:$OK,MATCH($E2,'Data_NSA'!$A:$A,0),MATCH($C2,'Data_NSA'!$1:$1,0))))/(100*(INDEX('Data_NSA'!$A:$OK,MATCH(H$1,'Data_NSA'!$A:$A,0),MATCH("CUUR0000SA0",'Data_NSA'!$1:$1,0))/INDEX('Data_NSA'!$A:$OK,MATCH($E2,'Data_NSA'!$A:$A,0),MATCH("CUUR0000SA0",'Data_NSA'!$1:$1,0)))),"") | I2: =IFERROR(100*($D2*(INDEX('Data_NSA'!$A:$OK,MATCH(I$1,'Data_NSA'!$A:$A,0),MATCH($C2,'Data_NSA'!$1:$1,0))/INDEX('Data_NSA'!$A:$OK,MATCH($E2,'Data_NSA'!$A:$A,0),MATCH($C2,'Data_NSA'!$1:$1,0))))/(100*(INDEX('Data_NSA'!$A:$OK,MATCH(I$1,'Data_NSA'!$A:$A,0),MATCH("CUUR0000SA0",'Data_NSA'!$1:$1,0))/INDEX('Data_NSA'!$A:$OK,MATCH($E2,'Data_NSA'!$A:$A,0),MATCH("CUUR0000SA0",'Data_NSA'!$1:$1,0)))),"")
A3: AA0 | B3: All items - old base | C3: CUUR0000AA0 | E3: 45992 | F3: 2024 | G3: =IFERROR(100*($D3*(INDEX('Data_NSA'!$A:$OK,MATCH(G$1,'Data_NSA'!$A:$A,0),MATCH($C3,'Data_NSA'!$1:$1,0))/INDEX('Data_NSA'!$A:$OK,MATCH($E3,'Data_NSA'!$A:$A,0),MATCH($C3,'Data_NSA'!$1:$1,0))))/(100*(INDEX('Data_NSA'!$A:$OK,MATCH(G$1,'Data_NSA'!$A:$A,0),MATCH("CUUR0000SA0",'Data_NSA'!$1:$1,0))/INDEX('Data_NSA'!$A:$OK,MATCH($E3,'Data_NSA'!$A:$A,0),MATCH("CUUR0000SA0",'Data_NSA'!$1:$1,0)))),"") | H3: =IFERROR(100*($D3*(INDEX('Data_NSA'!$A:$OK,MATCH(H$1,'Data_NSA'!$A:$A,0),MATCH($C3,'Data_NSA'!$1:$1,0))/INDEX('Data_NSA'!$A:$OK,MATCH($E3,'Data_NSA'!$A:$A,0),MATCH($C3,'Data_NSA'!$1:$1,0))))/(100*(INDEX('Data_NSA'!$A:$OK,MATCH(H$1,'Data_NSA'!$A:$A,0),MATCH("CUUR0000SA0",'Data_NSA'!$1:$1,0))/INDEX('Data_NSA'!$A:$OK,MATCH($E3,'Data_NSA'!$A:$A,0),MATCH("CUUR0000SA0",'Data_NSA'!$1:$1,0)))),"") | I3: =IFERROR(100*($D3*(INDEX('Data_NSA'!$A:$OK,MATCH(I$1,'Data_NSA'!$A:$A,0),MATCH($C3,'Data_NSA'!$1:$1,0))/INDEX('Data_NSA'!$A:$OK,MATCH($E3,'Data_NSA'!$A:$A,0),MATCH($C3,'Data_NSA'!$1:$1,0))))/(100*(INDEX('Data_NSA'!$A:$OK,MATCH(I$1,'Data_NSA'!$A:$A,0),MATCH("CUUR0000SA0",'Data_NSA'!$1:$1,0))/INDEX('Data_NSA'!$A:$OK,MATCH($E3,'Data_NSA'!$A:$A,0),MATCH("CUUR0000SA0",'Data_NSA'!$1:$1,0)))),"")
A4: SAF | B4: Food and beverages | C4: CUUR0000SAF | D4: 14.539 | E4: 45992 | F4: 2024 | G4: =IFERROR(100*($D4*(INDEX('Data_NSA'!$A:$OK,MATCH(G$1,'Data_NSA'!$A:$A,0),MATCH($C4,'Data_NSA'!$1:$1,0))/INDEX('Data_NSA'!$A:$OK,MATCH($E4,'Data_NSA'!$A:$A,0),MATCH($C4,'Data_NSA'!$1:$1,0))))/(100*(INDEX('Data_NSA'!$A:$OK,MATCH(G$1,'Data_NSA'!$A:$A,0),MATCH("CUUR0000SA0",'Data_NSA'!$1:$1,0))/INDEX('Data_NSA'!$A:$OK,MATCH($E4,'Data_NSA'!$A:$A,0),MATCH("CUUR0000SA0",'Data_NSA'!$1:$1,0)))),"") | H4: =IFERROR(100*($D4*(INDEX('Data_NSA'!$A:$OK,MATCH(H$1,'Data_NSA'!$A:$A,0),MATCH($C4,'Data_NSA'!$1:$1,0))/INDEX('Data_NSA'!$A:$OK,MATCH($E4,'Data_NSA'!$A:$A,0),MATCH($C4,'Data_NSA'!$1:$1,0))))/(100*(INDEX('Data_NSA'!$A:$OK,MATCH(H$1,'Data_NSA'!$A:$A,0),MATCH("CUUR0000SA0",'Data_NSA'!$1:$1,0))/INDEX('Data_NSA'!$A:$OK,MATCH($E4,'Data_NSA'!$A:$A,0),MATCH("CUUR0000SA0",'Data_NSA'!$1:$1,0)))),"") | I4: =IFERROR(100*($D4*(INDEX('Data_NSA'!$A:$OK,MATCH(I$1,'Data_NSA'!$A:$A,0),MATCH($C4,'Data_NSA'!$1:$1,0))/INDEX('Data_NSA'!$A:$OK,MATCH($E4,'Data_NSA'!$A:$A,0),MATCH($C4,'Data_NSA'!$1:$1,0))))/(100*(INDEX('Data_NSA'!$A:$OK,MATCH(I$1,'Data_NSA'!$A:$A,0),MATCH("CUUR0000SA0",'Data_NSA'!$1:$1,0))/INDEX('Data_NSA'!$A:$OK,MATCH($E4,'Data_NSA'!$A:$A,0),MATCH("CUUR0000SA0",'Data_NSA'!$1:$1,0)))),"")
A5: SAF1 | B5: Food | C5: CUUR0000SAF1 | D5: 13.698 | E5: 45992 | F5: 2024 | G5: =IFERROR(100*($D5*(INDEX('Data_NSA'!$A:$OK,MATCH(G$1,'Data_NSA'!$A:$A,0),MATCH($C5,'Data_NSA'!$1:$1,0))/INDEX('Data_NSA'!$A:$OK,MATCH($E5,'Data_NSA'!$A:$A,0),MATCH($C5,'Data_NSA'!$1:$1,0))))/(100*(INDEX('Data_NSA'!$A:$OK,MATCH(G$1,'Data_NSA'!$A:$A,0),MATCH("CUUR0000SA0",'Data_NSA'!$1:$1,0))/INDEX('Data_NSA'!$A:$OK,MATCH($E5,'Data_NSA'!$A:$A,0),MATCH("CUUR0000SA0",'Data_NSA'!$1:$1,0)))),"") | H5: =IFERROR(100*($D5*(INDEX('Data_NSA'!$A:$OK,MATCH(H$1,'Data_NSA'!$A:$A,0),MATCH($C5,'Data_NSA'!$1:$1,0))/INDEX('Data_NSA'!$A:$OK,MATCH($E5,'Data_NSA'!$A:$A,0),MATCH($C5,'Data_NSA'!$1:$1,0))))/(100*(INDEX('Data_NSA'!$A:$OK,MATCH(H$1,'Data_NSA'!$A:$A,0),MATCH("CUUR0000SA0",'Data_NSA'!$1:$1,0))/INDEX('Data_NSA'!$A:$OK,MATCH($E5,'Data_NSA'!$A:$A,0),MATCH("CUUR0000SA0",'Data_NSA'!$1:$1,0)))),"") | I5: =IFERROR(100*($D5*(INDEX('Data_NSA'!$A:$OK,MATCH(I$1,'Data_NSA'!$A:$A,0),MATCH($C5,'Data_NSA'!$1:$1,0))/INDEX('Data_NSA'!$A:$OK,MATCH($E5,'Data_NSA'!$A:$A,0),MATCH($C5,'Data_NSA'!$1:$1,0))))/(100*(INDEX('Data_NSA'!$A:$OK,MATCH(I$1,'Data_NSA'!$A:$A,0),MATCH("CUUR0000SA0",'Data_NSA'!$1:$1,0))/INDEX('Data_NSA'!$A:$OK,MATCH($E5,'Data_NSA'!$A:$A,0),MATCH("CUUR0000SA0",'Data_NSA'!$1:$1,0)))),"")
A6: SAF11 | B6: Food at home | C6: CUUR0000SAF11 | D6: 8.325 | E6: 45992 | F6: 2024 | G6: =IFERROR(100*($D6*(INDEX('Data_NSA'!$A:$OK,MATCH(G$1,'Data_NSA'!$A:$A,0),MATCH($C6,'Data_NSA'!$1:$1,0))/INDEX('Data_NSA'!$A:$OK,MATCH($E6,'Data_NSA'!$A:$A,0),MATCH($C6,'Data_NSA'!$1:$1,0))))/(100*(INDEX('Data_NSA'!$A:$OK,MATCH(G$1,'Data_NSA'!$A:$A,0),MATCH("CUUR0000SA0",'Data_NSA'!$1:$1,0))/INDEX('Data_NSA'!$A:$OK,MATCH($E6,'Data_NSA'!$A:$A,0),MATCH("CUUR0000SA0",'Data_NSA'!$1:$1,0)))),"") | H6: =IFERROR(100*($D6*(INDEX('Data_NSA'!$A:$OK,MATCH(H$1,'Data_NSA'!$A:$A,0),MATCH($C6,'Data_NSA'!$1:$1,0))/INDEX('Data_NSA'!$A:$OK,MATCH($E6,'Data_NSA'!$A:$A,0),MATCH($C6,'Data_NSA'!$1:$1,0))))/(100*(INDEX('Data_NSA'!$A:$OK,MATCH(H$1,'Data_NSA'!$A:$A,0),MATCH("CUUR0000SA0",'Data_NSA'!$1:$1,0))/INDEX('Data_NSA'!$A:$OK,MATCH($E6,'Data_NSA'!$A:$A,0),MATCH("CUUR0000SA0",'Data_NSA'!$1:$1,0)))),"") | I6: =IFERROR(100*($D6*(INDEX('Data_NSA'!$A:$OK,MATCH(I$1,'Data_NSA'!$A:$A,0),MATCH($C6,'Data_NSA'!$1:$1,0))/INDEX('Data_NSA'!$A:$OK,MATCH($E6,'Data_NSA'!$A:$A,0),MATCH($C6,'Data_NSA'!$1:$1,0))))/(100*(INDEX('Data_NSA'!$A:$OK,MATCH(I$1,'Data_NSA'!$A:$A,0),MATCH("CUUR0000SA0",'Data_NSA'!$1:$1,0))/INDEX('Data_NSA'!$A:$OK,MATCH($E6,'Data_NSA'!$A:$A,0),MATCH("CUUR0000SA0",'Data_NSA'!$1:$1,0)))),"")
A7: SAF111 | B7: Cereals and bakery products | C7: CUUR0000SAF111 | D7: 1.035 | E7: 45992 | F7: 2024 | G7: =IFERROR(100*($D7*(INDEX('Data_NSA'!$A:$OK,MATCH(G$1,'Data_NSA'!$A:$A,0),MATCH($C7,'Data_NSA'!$1:$1,0))/INDEX('Data_NSA'!$A:$OK,MATCH($E7,'Data_NSA'!$A:$A,0),MATCH($C7,'Data_NSA'!$1:$1,0))))/(100*(INDEX('Data_NSA'!$A:$OK,MATCH(G$1,'Data_NSA'!$A:$A,0),MATCH("CUUR0000SA0",'Data_NSA'!$1:$1,0))/INDEX('Data_NSA'!$A:$OK,MATCH($E7,'Data_NSA'!$A:$A,0),MATCH("CUUR0000SA0",'Data_NSA'!$1:$1,0)))),"") | H7: =IFERROR(100*($D7*(INDEX('Data_NSA'!$A:$OK,MATCH(H$1,'Data_NSA'!$A:$A,0),MATCH($C7,'Data_NSA'!$1:$1,0))/INDEX('Data_NSA'!$A:$OK,MATCH($E7,'Data_NSA'!$A:$A,0),MATCH($C7,'Data_NSA'!$1:$1,0))))/(100*(INDEX('Data_NSA'!$A:$OK,MATCH(H$1,'Data_NSA'!$A:$A,0),MATCH("CUUR0000SA0",'Data_NSA'!$1:$1,0))/INDEX('Data_NSA'!$A:$OK,MATCH($E7,'Data_NSA'!$A:$A,0),MATCH("CUUR0000SA0",'Data_NSA'!$1:$1,0)))),"") | I7: =IFERROR(100*($D7*(INDEX('Data_NSA'!$A:$OK,MATCH(I$1,'Data_NSA'!$A:$A,0),MATCH($C7,'Data_NSA'!$1:$1,0))/INDEX('Data_NSA'!$A:$OK,MATCH($E7,'Data_NSA'!$A:$A,0),MATCH($C7,'Data_NSA'!$1:$1,0))))/(100*(INDEX('Data_NSA'!$A:$OK,MATCH(I$1,'Data_NSA'!$A:$A,0),MATCH("CUUR0000SA0",'Data_NSA'!$1:$1,0))/INDEX('Data_NSA'!$A:$OK,MATCH($E7,'Data_NSA'!$A:$A,0),MATCH("CUUR0000SA0",'Data_NSA'!$1:$1,0)))),"")
A8: SEFA | B8: Cereals and cereal products | C8: CUUR0000SEFA | D8: 0.315 | E8: 45992 | F8: 2024 | G8: =IFERROR(100*($D8*(INDEX('Data_NSA'!$A:$OK,MATCH(G$1,'Data_NSA'!$A:$A,0),MATCH($C8,'Data_NSA'!$1:$1,0))/INDEX('Data_NSA'!$A:$OK,MATCH($E8,'Data_NSA'!$A:$A,0),MATCH($C8,'Data_NSA'!$1:$1,0))))/(100*(INDEX('Data_NSA'!$A:$OK,MATCH(G$1,'Data_NSA'!$A:$A,0),MATCH("CUUR0000SA0",'Data_NSA'!$1:$1,0))/INDEX('Data_NSA'!$A:$OK,MATCH($E8,'Data_NSA'!$A:$A,0),MATCH("CUUR0000SA0",'Data_NSA'!$1:$1,0)))),"") | H8: =IFERROR(100*($D8*(INDEX('Data_NSA'!$A:$OK,MATCH(H$1,'Data_NSA'!$A:$A,0),MATCH($C8,'Data_NSA'!$1:$1,0))/INDEX('Data_NSA'!$A:$OK,MATCH($E8,'Data_NSA'!$A:$A,0),MATCH($C8,'Data_NSA'!$1:$1,0))))/(100*(INDEX('Data_NSA'!$A:$OK,MATCH(H$1,'Data_NSA'!$A:$A,0),MATCH("CUUR0000SA0",'Data_NSA'!$1:$1,0))/INDEX('Data_NSA'!$A:$OK,MATCH($E8,'Data_NSA'!$A:$A,0),MATCH("CUUR0000SA0",'Data_NSA'!$1:$1,0)))),"") | I8: =IFERROR(100*($D8*(INDEX('Data_NSA'!$A:$OK,MATCH(I$1,'Data_NSA'!$A:$A,0),MATCH($C8,'Data_NSA'!$1:$1,0))/INDEX('Data_NSA'!$A:$OK,MATCH($E8,'Data_NSA'!$A:$A,0),MATCH($C8,'Data_NSA'!$1:$1,0))))/(100*(INDEX('Data_NSA'!$A:$OK,MATCH(I$1,'Data_NSA'!$A:$A,0),MATCH("CUUR0000SA0",'Data_NSA'!$1:$1,0))/INDEX('Data_NSA'!$A:$OK,MATCH($E8,'Data_NSA'!$A:$A,0),MATCH("CUUR0000SA0",'Data_NSA'!$1:$1,0)))),"")
A9: SEFA01 | B9: Flour and prepared flour mixes | C9: CUUR0000SEFA01 | D9: 0.038 | E9: 45992 | F9: 2024 | G9: =IFERROR(100*($D9*(INDEX('Data_NSA'!$A:$OK,MATCH(G$1,'Data_NSA'!$A:$A,0),MATCH($C9,'Data_NSA'!$1:$1,0))/INDEX('Data_NSA'!$A:$OK,MATCH($E9,'Data_NSA'!$A:$A,0),MATCH($C9,'Data_NSA'!$1:$1,0))))/(100*(INDEX('Data_NSA'!$A:$OK,MATCH(G$1,'Data_NSA'!$A:$A,0),MATCH("CUUR0000SA0",'Data_NSA'!$1:$1,0))/INDEX('Data_NSA'!$A:$OK,MATCH($E9,'Data_NSA'!$A:$A,0),MATCH("CUUR0000SA0",'Data_NSA'!$1:$1,0)))),"") | H9: =IFERROR(100*($D9*(INDEX('Data_NSA'!$A:$OK,MATCH(H$1,'Data_NSA'!$A:$A,0),MATCH($C9,'Data_NSA'!$1:$1,0))/INDEX('Data_NSA'!$A:$OK,MATCH($E9,'Data_NSA'!$A:$A,0),MATCH($C9,'Data_NSA'!$1:$1,0))))/(100*(INDEX('Data_NSA'!$A:$OK,MATCH(H$1,'Data_NSA'!$A:$A,0),MATCH("CUUR0000SA0",'Data_NSA'!$1:$1,0))/INDEX('Data_NSA'!$A:$OK,MATCH($E9,'Data_NSA'!$A:$A,0),MATCH("CUUR0000SA0",'Data_NSA'!$1:$1,0)))),"") | I9: =IFERROR(100*($D9*(INDEX('Data_NSA'!$A:$OK,MATCH(I$1,'Data_NSA'!$A:$A,0),MATCH($C9,'Data_NSA'!$1:$1,0))/INDEX('Data_NSA'!$A:$OK,MATCH($E9,'Data_NSA'!$A:$A,0),MATCH($C9,'Data_NSA'!$1:$1,0))))/(100*(INDEX('Data_NSA'!$A:$OK,MATCH(I$1,'Data_NSA'!$A:$A,0),MATCH("CUUR0000SA0",'Data_NSA'!$1:$1,0))/INDEX('Data_NSA'!$A:$OK,MATCH($E9,'Data_NSA'!$A:$A,0),MATCH("CUUR0000SA0",'Data_NSA'!$1:$1,0)))),"")
A10: SEFA02 | B10: Breakfast cereal | C10: CUUR0000SEFA02 | D10: 0.136 | E10: 45992 | F10: 2024 | G10: =IFERROR(100*($D10*(INDEX('Data_NSA'!$A:$OK,MATCH(G$1,'Data_NSA'!$A:$A,0),MATCH($C10,'Data_NSA'!$1:$1,0))/INDEX('Data_NSA'!$A:$OK,MATCH($E10,'Data_NSA'!$A:$A,0),MATCH($C10,'Data_NSA'!$1:$1,0))))/(100*(INDEX('Data_NSA'!$A:$OK,MATCH(G$1,'Data_NSA'!$A:$A,0),MATCH("CUUR0000SA0",'Data_NSA'!$1:$1,0))/INDEX('Data_NSA'!$A:$OK,MATCH($E10,'Data_NSA'!$A:$A,0),MATCH("CUUR0000SA0",'Data_NSA'!$1:$1,0)))),"") | H10: =IFERROR(100*($D10*(INDEX('Data_NSA'!$A:$OK,MATCH(H$1,'Data_NSA'!$A:$A,0),MATCH($C10,'Data_NSA'!$1:$1,0))/INDEX('Data_NSA'!$A:$OK,MATCH($E10,'Data_NSA'!$A:$A,0),MATCH($C10,'Data_NSA'!$1:$1,0))))/(100*(INDEX('Data_NSA'!$A:$OK,MATCH(H$1,'Data_NSA'!$A:$A,0),MATCH("CUUR0000SA0",'Data_NSA'!$1:$1,0))/INDEX('Data_NSA'!$A:$OK,MATCH($E10,'Data_NSA'!$A:$A,0),MATCH("CUUR0000SA0",'Data_NSA'!$1:$1,0)))),"") | I10: =IFERROR(100*($D10*(INDEX('Data_NSA'!$A:$OK,MATCH(I$1,'Data_NSA'!$A:$A,0),MATCH($C10,'Data_NSA'!$1:$1,0))/INDEX('Data_NSA'!$A:$OK,MATCH($E10,'Data_NSA'!$A:$A,0),MATCH($C10,'Data_NSA'!$1:$1,0))))/(100*(INDEX('Data_NSA'!$A:$OK,MATCH(I$1,'Data_NSA'!$A:$A,0),MATCH("CUUR0000SA0",'Data_NSA'!$1:$1,0))/INDEX('Data_NSA'!$A:$OK,MATCH($E10,'Data_NSA'!$A:$A,0),MATCH("CUUR0000SA0",'Data_NSA'!$1:$1,0)))),"")
A11: SEFA03 | B11: Rice, pasta, cornmeal | C11: CUUR0000SEFA03 | D11: 0.141 | E11: 45992 | F11: 2024 | G11: =IFERROR(100*($D11*(INDEX('Data_NSA'!$A:$OK,MATCH(G$1,'Data_NSA'!$A:$A,0),MATCH($C11,'Data_NSA'!$1:$1,0))/INDEX('Data_NSA'!$A:$OK,MATCH($E11,'Data_NSA'!$A:$A,0),MATCH($C11,'Data_NSA'!$1:$1,0))))/(100*(INDEX('Data_NSA'!$A:$OK,MATCH(G$1,'Data_NSA'!$A:$A,0),MATCH("CUUR0000SA0",'Data_NSA'!$1:$1,0))/INDEX('Data_NSA'!$A:$OK,MATCH($E11,'Data_NSA'!$A:$A,0),MATCH("CUUR0000SA0",'Data_NSA'!$1:$1,0)))),"") | H11: =IFERROR(100*($D11*(INDEX('Data_NSA'!$A:$OK,MATCH(H$1,'Data_NSA'!$A:$A,0),MATCH($C11,'Data_NSA'!$1:$1,0))/INDEX('Data_NSA'!$A:$OK,MATCH($E11,'Data_NSA'!$A:$A,0),MATCH($C11,'Data_NSA'!$1:$1,0))))/(100*(INDEX('Data_NSA'!$A:$OK,MATCH(H$1,'Data_NSA'!$A:$A,0),MATCH("CUUR0000SA0",'Data_NSA'!$1:$1,0))/INDEX('Data_NSA'!$A:$OK,MATCH($E11,'Data_NSA'!$A:$A,0),MATCH("CUUR0000SA0",'Data_NSA'!$1:$1,0)))),"") | I11: =IFERROR(100*($D11*(INDEX('Data_NSA'!$A:$OK,MATCH(I$1,'Data_NSA'!$A:$A,0),MATCH($C11,'Data_NSA'!$1:$1,0))/INDEX('Data_NSA'!$A:$OK,MATCH($E11,'Data_NSA'!$A:$A,0),MATCH($C11,'Data_NSA'!$1:$1,0))))/(100*(INDEX('Data_NSA'!$A:$OK,MATCH(I$1,'Data_NSA'!$A:$A,0),MATCH("CUUR0000SA0",'Data_NSA'!$1:$1,0))/INDEX('Data_NSA'!$A:$OK,MATCH($E11,'Data_NSA'!$A:$A,0),MATCH("CUUR0000SA0",'Data_NSA'!$1:$1,0)))),"")
A12: SS01031 | B12: Rice | C12: CUUR0000SS01031 | E12: 45992 | F12: 2024 | G12: =IFERROR(100*($D12*(INDEX('Data_NSA'!$A:$OK,MATCH(G$1,'Data_NSA'!$A:$A,0),MATCH($C12,'Data_NSA'!$1:$1,0))/INDEX('Data_NSA'!$A:$OK,MATCH($E12,'Data_NSA'!$A:$A,0),MATCH($C12,'Data_NSA'!$1:$1,0))))/(100*(INDEX('Data_NSA'!$A:$OK,MATCH(G$1,'Data_NSA'!$A:$A,0),MATCH("CUUR0000SA0",'Data_NSA'!$1:$1,0))/INDEX('Data_NSA'!$A:$OK,MATCH($E12,'Data_NSA'!$A:$A,0),MATCH("CUUR0000SA0",'Data_NSA'!$1:$1,0)))),"") | H12: =IFERROR(100*($D12*(INDEX('Data_NSA'!$A:$OK,MATCH(H$1,'Data_NSA'!$A:$A,0),MATCH($C12,'Data_NSA'!$1:$1,0))/INDEX('Data_NSA'!$A:$OK,MATCH($E12,'Data_NSA'!$A:$A,0),MATCH($C12,'Data_NSA'!$1:$1,0))))/(100*(INDEX('Data_NSA'!$A:$OK,MATCH(H$1,'Data_NSA'!$A:$A,0),MATCH("CUUR0000SA0",'Data_NSA'!$1:$1,0))/INDEX('Data_NSA'!$A:$OK,MATCH($E12,'Data_NSA'!$A:$A,0),MATCH("CUUR0000SA0",'Data_NSA'!$1:$1,0)))),"") | I12: =IFERROR(100*($D12*(INDEX('Data_NSA'!$A:$OK,MATCH(I$1,'Data_NSA'!$A:$A,0),MATCH($C12,'Data_NSA'!$1:$1,0))/INDEX('Data_NSA'!$A:$OK,MATCH($E12,'Data_NSA'!$A:$A,0),MATCH($C12,'Data_NSA'!$1:$1,0))))/(100*(INDEX('Data_NSA'!$A:$OK,MATCH(I$1,'Data_NSA'!$A:$A,0),MATCH("CUUR0000SA0",'Data_NSA'!$1:$1,0))/INDEX('Data_NSA'!$A:$OK,MATCH($E12,'Data_NSA'!$A:$A,0),MATCH("CUUR0000SA0",'Data_NSA'!$1:$1,0)))),"")
A13: SEFB | B13: Bakery products | C13: CUUR0000SEFB | D13: 0.721 | E13: 45992 | F13: 2024 | G13: =IFERROR(100*($D13*(INDEX('Data_NSA'!$A:$OK,MATCH(G$1,'Data_NSA'!$A:$A,0),MATCH($C13,'Data_NSA'!$1:$1,0))/INDEX('Data_NSA'!$A:$OK,MATCH($E13,'Data_NSA'!$A:$A,0),MATCH($C13,'Data_NSA'!$1:$1,0))))/(100*(INDEX('Data_NSA'!$A:$OK,MATCH(G$1,'Data_NSA'!$A:$A,0),MATCH("CUUR0000SA0",'Data_NSA'!$1:$1,0))/INDEX('Data_NSA'!$A:$OK,MATCH($E13,'Data_NSA'!$A:$A,0),MATCH("CUUR0000SA0",'Data_NSA'!$1:$1,0)))),"") | H13: =IFERROR(100*($D13*(INDEX('Data_NSA'!$A:$OK,MATCH(H$1,'Data_NSA'!$A:$A,0),MATCH($C13,'Data_NSA'!$1:$1,0))/INDEX('Data_NSA'!$A:$OK,MATCH($E13,'Data_NSA'!$A:$A,0),MATCH($C13,'Data_NSA'!$1:$1,0))))/(100*(INDEX('Data_NSA'!$A:$OK,MATCH(H$1,'Data_NSA'!$A:$A,0),MATCH("CUUR0000SA0",'Data_NSA'!$1:$1,0))/INDEX('Data_NSA'!$A:$OK,MATCH($E13,'Data_NSA'!$A:$A,0),MATCH("CUUR0000SA0",'Data_NSA'!$1:$1,0)))),"") | I13: =IFERROR(100*($D13*(INDEX('Data_NSA'!$A:$OK,MATCH(I$1,'Data_NSA'!$A:$A,0),MATCH($C13,'Data_NSA'!$1:$1,0))/INDEX('Data_NSA'!$A:$OK,MATCH($E13,'Data_NSA'!$A:$A,0),MATCH($C13,'Data_NSA'!$1:$1,0))))/(100*(INDEX('Data_NSA'!$A:$OK,MATCH(I$1,'Data_NSA'!$A:$A,0),MATCH("CUUR0000SA0",'Data_NSA'!$1:$1,0))/INDEX('Data_NSA'!$A:$OK,MATCH($E13,'Data_NSA'!$A:$A,0),MATCH("CUUR0000SA0",'Data_NSA'!$1:$1,0)))),"")
A14: SEFB01 | B14: Bread | C14: CUUR0000SEFB01 | D14: 0.175 | E14: 45992 | F14: 2024 | G14: =IFERROR(100*($D14*(INDEX('Data_NSA'!$A:$OK,MATCH(G$1,'Data_NSA'!$A:$A,0),MATCH($C14,'Data_NSA'!$1:$1,0))/INDEX('Data_NSA'!$A:$OK,MATCH($E14,'Data_NSA'!$A:$A,0),MATCH($C14,'Data_NSA'!$1:$1,0))))/(100*(INDEX('Data_NSA'!$A:$OK,MATCH(G$1,'Data_NSA'!$A:$A,0),MATCH("CUUR0000SA0",'Data_NSA'!$1:$1,0))/INDEX('Data_NSA'!$A:$OK,MATCH($E14,'Data_NSA'!$A:$A,0),MATCH("CUUR0000SA0",'Data_NSA'!$1:$1,0)))),"") | H14: =IFERROR(100*($D14*(INDEX('Data_NSA'!$A:$OK,MATCH(H$1,'Data_NSA'!$A:$A,0),MATCH($C14,'Data_NSA'!$1:$1,0))/INDEX('Data_NSA'!$A:$OK,MATCH($E14,'Data_NSA'!$A:$A,0),MATCH($C14,'Data_NSA'!$1:$1,0))))/(100*(INDEX('Data_NSA'!$A:$OK,MATCH(H$1,'Data_NSA'!$A:$A,0),MATCH("CUUR0000SA0",'Data_NSA'!$1:$1,0))/INDEX('Data_NSA'!$A:$OK,MATCH($E14,'Data_NSA'!$A:$A,0),MATCH("CUUR0000SA0",'Data_NSA'!$1:$1,0)))),"") | I14: =IFERROR(100*($D14*(INDEX('Data_NSA'!$A:$OK,MATCH(I$1,'Data_NSA'!$A:$A,0),MATCH($C14,'Data_NSA'!$1:$1,0))/INDEX('Data_NSA'!$A:$OK,MATCH($E14,'Data_NSA'!$A:$A,0),MATCH($C14,'Data_NSA'!$1:$1,0))))/(100*(INDEX('Data_NSA'!$A:$OK,MATCH(I$1,'Data_NSA'!$A:$A,0),MATCH("CUUR0000SA0",'Data_NSA'!$1:$1,0))/INDEX('Data_NSA'!$A:$OK,MATCH($E14,'Data_NSA'!$A:$A,0),MATCH("CUUR0000SA0",'Data_NSA'!$1:$1,0)))),"")
A15: SS02011 | B15: White bread | C15: CUUR0000SS02011 | E15: 45992 | F15: 2024 | G15: =IFERROR(100*($D15*(INDEX('Data_NSA'!$A:$OK,MATCH(G$1,'Data_NSA'!$A:$A,0),MATCH($C15,'Data_NSA'!$1:$1,0))/INDEX('Data_NSA'!$A:$OK,MATCH($E15,'Data_NSA'!$A:$A,0),MATCH($C15,'Data_NSA'!$1:$1,0))))/(100*(INDEX('Data_NSA'!$A:$OK,MATCH(G$1,'Data_NSA'!$A:$A,0),MATCH("CUUR0000SA0",'Data_NSA'!$1:$1,0))/INDEX('Data_NSA'!$A:$OK,MATCH($E15,'Data_NSA'!$A:$A,0),MATCH("CUUR0000SA0",'Data_NSA'!$1:$1,0)))),"") | H15: =IFERROR(100*($D15*(INDEX('Data_NSA'!$A:$OK,MATCH(H$1,'Data_NSA'!$A:$A,0),MATCH($C15,'Data_NSA'!$1:$1,0))/INDEX('Data_NSA'!$A:$OK,MATCH($E15,'Data_NSA'!$A:$A,0),MATCH($C15,'Data_NSA'!$1:$1,0))))/(100*(INDEX('Data_NSA'!$A:$OK,MATCH(H$1,'Data_NSA'!$A:$A,0),MATCH("CUUR0000SA0",'Data_NSA'!$1:$1,0))/INDEX('Data_NSA'!$A:$OK,MATCH($E15,'Data_NSA'!$A:$A,0),MATCH("CUUR0000SA0",'Data_NSA'!$1:$1,0)))),"") | I15: =IFERROR(100*($D15*(INDEX('Data_NSA'!$A:$OK,MATCH(I$1,'Data_NSA'!$A:$A,0),MATCH($C15,'Data_NSA'!$1:$1,0))/INDEX('Data_NSA'!$A:$OK,MATCH($E15,'Data_NSA'!$A:$A,0),MATCH($C15,'Data_NSA'!$1:$1,0))))/(100*(INDEX('Data_NSA'!$A:$OK,MATCH(I$1,'Data_NSA'!$A:$A,0),MATCH("CUUR0000SA0",'Data_NSA'!$1:$1,0))/INDEX('Data_NSA'!$A:$OK,MATCH($E15,'Data_NSA'!$A:$A,0),MATCH("CUUR0000SA0",'Data_NSA'!$1:$1,0)))),"")
A16: SS02021 | B16: Bread other than white | C16: CUUR0000SS02021 | E16: 45992 | F16: 2024 | G16: =IFERROR(100*($D16*(INDEX('Data_NSA'!$A:$OK,MATCH(G$1,'Data_NSA'!$A:$A,0),MATCH($C16,'Data_NSA'!$1:$1,0))/INDEX('Data_NSA'!$A:$OK,MATCH($E16,'Data_NSA'!$A:$A,0),MATCH($C16,'Data_NSA'!$1:$1,0))))/(100*(INDEX('Data_NSA'!$A:$OK,MATCH(G$1,'Data_NSA'!$A:$A,0),MATCH("CUUR0000SA0",'Data_NSA'!$1:$1,0))/INDEX('Data_NSA'!$A:$OK,MATCH($E16,'Data_NSA'!$A:$A,0),MATCH("CUUR0000SA0",'Data_NSA'!$1:$1,0)))),"") | H16: =IFERROR(100*($D16*(INDEX('Data_NSA'!$A:$OK,MATCH(H$1,'Data_NSA'!$A:$A,0),MATCH($C16,'Data_NSA'!$1:$1,0))/INDEX('Data_NSA'!$A:$OK,MATCH($E16,'Data_NSA'!$A:$A,0),MATCH($C16,'Data_NSA'!$1:$1,0))))/(100*(INDEX('Data_NSA'!$A:$OK,MATCH(H$1,'Data_NSA'!$A:$A,0),MATCH("CUUR0000SA0",'Data_NSA'!$1:$1,0))/INDEX('Data_NSA'!$A:$OK,MATCH($E16,'Data_NSA'!$A:$A,0),MATCH("CUUR0000SA0",'Data_NSA'!$1:$1,0)))),"") | I16: =IFERROR(100*($D16*(INDEX('Data_NSA'!$A:$OK,MATCH(I$1,'Data_NSA'!$A:$A,0),MATCH($C16,'Data_NSA'!$1:$1,0))/INDEX('Data_NSA'!$A:$OK,MATCH($E16,'Data_NSA'!$A:$A,0),MATCH($C16,'Data_NSA'!$1:$1,0))))/(100*(INDEX('Data_NSA'!$A:$OK,MATCH(I$1,'Data_NSA'!$A:$A,0),MATCH("CUUR0000SA0",'Data_NSA'!$1:$1,0))/INDEX('Data_NSA'!$A:$OK,MATCH($E16,'Data_NSA'!$A:$A,0),MATCH("CUUR0000SA0",'Data_NSA'!$1:$1,0)))),"")
A17: SEFB02 | B17: Fresh biscuits, rolls, muffins | C17: CUUR0000SEFB02 | D17: 0.12 | E17: 45992 | F17: 2024 | G17: =IFERROR(100*($D17*(INDEX('Data_NSA'!$A:$OK,MATCH(G$1,'Data_NSA'!$A:$A,0),MATCH($C17,'Data_NSA'!$1:$1,0))/INDEX('Data_NSA'!$A:$OK,MATCH($E17,'Data_NSA'!$A:$A,0),MATCH($C17,'Data_NSA'!$1:$1,0))))/(100*(INDEX('Data_NSA'!$A:$OK,MATCH(G$1,'Data_NSA'!$A:$A,0),MATCH("CUUR0000SA0",'Data_NSA'!$1:$1,0))/INDEX('Data_NSA'!$A:$OK,MATCH($E17,'Data_NSA'!$A:$A,0),MATCH("CUUR0000SA0",'Data_NSA'!$1:$1,0)))),"") | H17: =IFERROR(100*($D17*(INDEX('Data_NSA'!$A:$OK,MATCH(H$1,'Data_NSA'!$A:$A,0),MATCH($C17,'Data_NSA'!$1:$1,0))/INDEX('Data_NSA'!$A:$OK,MATCH($E17,'Data_NSA'!$A:$A,0),MATCH($C17,'Data_NSA'!$1:$1,0))))/(100*(INDEX('Data_NSA'!$A:$OK,MATCH(H$1,'Data_NSA'!$A:$A,0),MATCH("CUUR0000SA0",'Data_NSA'!$1:$1,0))/INDEX('Data_NSA'!$A:$OK,MATCH($E17,'Data_NSA'!$A:$A,0),MATCH("CUUR0000SA0",'Data_NSA'!$1:$1,0)))),"") | I17: =IFERROR(100*($D17*(INDEX('Data_NSA'!$A:$OK,MATCH(I$1,'Data_NSA'!$A:$A,0),MATCH($C17,'Data_NSA'!$1:$1,0))/INDEX('Data_NSA'!$A:$OK,MATCH($E17,'Data_NSA'!$A:$A,0),MATCH($C17,'Data_NSA'!$1:$1,0))))/(100*(INDEX('Data_NSA'!$A:$OK,MATCH(I$1,'Data_NSA'!$A:$A,0),MATCH("CUUR0000SA0",'Data_NSA'!$1:$1,0))/INDEX('Data_NSA'!$A:$OK,MATCH($E17,'Data_NSA'!$A:$A,0),MATCH("CUUR0000SA0",'Data_NSA'!$1:$1,0)))),"")
A18: SEFB03 | B18: Cakes, cupcakes, and cookies | C18: CUUR0000SEFB03 | D18: 0.21 | E18: 45992 | F18: 2024 | G18: =IFERROR(100*($D18*(INDEX('Data_NSA'!$A:$OK,MATCH(G$1,'Data_NSA'!$A:$A,0),MATCH($C18,'Data_NSA'!$1:$1,0))/INDEX('Data_NSA'!$A:$OK,MATCH($E18,'Data_NSA'!$A:$A,0),MATCH($C18,'Data_NSA'!$1:$1,0))))/(100*(INDEX('Data_NSA'!$A:$OK,MATCH(G$1,'Data_NSA'!$A:$A,0),MATCH("CUUR0000SA0",'Data_NSA'!$1:$1,0))/INDEX('Data_NSA'!$A:$OK,MATCH($E18,'Data_NSA'!$A:$A,0),MATCH("CUUR0000SA0",'Data_NSA'!$1:$1,0)))),"") | H18: =IFERROR(100*($D18*(INDEX('Data_NSA'!$A:$OK,MATCH(H$1,'Data_NSA'!$A:$A,0),MATCH($C18,'Data_NSA'!$1:$1,0))/INDEX('Data_NSA'!$A:$OK,MATCH($E18,'Data_NSA'!$A:$A,0),MATCH($C18,'Data_NSA'!$1:$1,0))))/(100*(INDEX('Data_NSA'!$A:$OK,MATCH(H$1,'Data_NSA'!$A:$A,0),MATCH("CUUR0000SA0",'Data_NSA'!$1:$1,0))/INDEX('Data_NSA'!$A:$OK,MATCH($E18,'Data_NSA'!$A:$A,0),MATCH("CUUR0000SA0",'Data_NSA'!$1:$1,0)))),"") | I18: =IFERROR(100*($D18*(INDEX('Data_NSA'!$A:$OK,MATCH(I$1,'Data_NSA'!$A:$A,0),MATCH($C18,'Data_NSA'!$1:$1,0))/INDEX('Data_NSA'!$A:$OK,MATCH($E18,'Data_NSA'!$A:$A,0),MATCH($C18,'Data_NSA'!$1:$1,0))))/(100*(INDEX('Data_NSA'!$A:$OK,MATCH(I$1,'Data_NSA'!$A:$A,0),MATCH("CUUR0000SA0",'Data_NSA'!$1:$1,0))/INDEX('Data_NSA'!$A:$OK,MATCH($E18,'Data_NSA'!$A:$A,0),MATCH("CUUR0000SA0",'Data_NSA'!$1:$1,0)))),"")
A19: SS02041 | B19: Fresh cakes and cupcakes | C19: CUUR0000SS02041 | E19: 45992 | F19: 2024 | G19: =IFERROR(100*($D19*(INDEX('Data_NSA'!$A:$OK,MATCH(G$1,'Data_NSA'!$A:$A,0),MATCH($C19,'Data_NSA'!$1:$1,0))/INDEX('Data_NSA'!$A:$OK,MATCH($E19,'Data_NSA'!$A:$A,0),MATCH($C19,'Data_NSA'!$1:$1,0))))/(100*(INDEX('Data_NSA'!$A:$OK,MATCH(G$1,'Data_NSA'!$A:$A,0),MATCH("CUUR0000SA0",'Data_NSA'!$1:$1,0))/INDEX('Data_NSA'!$A:$OK,MATCH($E19,'Data_NSA'!$A:$A,0),MATCH("CUUR0000SA0",'Data_NSA'!$1:$1,0)))),"") | H19: =IFERROR(100*($D19*(INDEX('Data_NSA'!$A:$OK,MATCH(H$1,'Data_NSA'!$A:$A,0),MATCH($C19,'Data_NSA'!$1:$1,0))/INDEX('Data_NSA'!$A:$OK,MATCH($E19,'Data_NSA'!$A:$A,0),MATCH($C19,'Data_NSA'!$1:$1,0))))/(100*(INDEX('Data_NSA'!$A:$OK,MATCH(H$1,'Data_NSA'!$A:$A,0),MATCH("CUUR0000SA0",'Data_NSA'!$1:$1,0))/INDEX('Data_NSA'!$A:$OK,MATCH($E19,'Data_NSA'!$A:$A,0),MATCH("CUUR0000SA0",'Data_NSA'!$1:$1,0)))),"") | I19: =IFERROR(100*($D19*(INDEX('Data_NSA'!$A:$OK,MATCH(I$1,'Data_NSA'!$A:$A,0),MATCH($C19,'Data_NSA'!$1:$1,0))/INDEX('Data_NSA'!$A:$OK,MATCH($E19,'Data_NSA'!$A:$A,0),MATCH($C19,'Data_NSA'!$1:$1,0))))/(100*(INDEX('Data_NSA'!$A:$OK,MATCH(I$1,'Data_NSA'!$A:$A,0),MATCH("CUUR0000SA0",'Data_NSA'!$1:$1,0))/INDEX('Data_NSA'!$A:$OK,MATCH($E19,'Data_NSA'!$A:$A,0),MATCH("CUUR0000SA0",'Data_NSA'!$1:$1,0)))),"")
A20: SS02042 | B20: Cookies | C20: CUUR0000SS02042 | E20: 45992 | F20: 2024 | G20: =IFERROR(100*($D20*(INDEX('Data_NSA'!$A:$OK,MATCH(G$1,'Data_NSA'!$A:$A,0),MATCH($C20,'Data_NSA'!$1:$1,0))/INDEX('Data_NSA'!$A:$OK,MATCH($E20,'Data_NSA'!$A:$A,0),MATCH($C20,'Data_NSA'!$1:$1,0))))/(100*(INDEX('Data_NSA'!$A:$OK,MATCH(G$1,'Data_NSA'!$A:$A,0),MATCH("CUUR0000SA0",'Data_NSA'!$1:$1,0))/INDEX('Data_NSA'!$A:$OK,MATCH($E20,'Data_NSA'!$A:$A,0),MATCH("CUUR0000SA0",'Data_NSA'!$1:$1,0)))),"") | H20: =IFERROR(100*($D20*(INDEX('Data_NSA'!$A:$OK,MATCH(H$1,'Data_NSA'!$A:$A,0),MATCH($C20,'Data_NSA'!$1:$1,0))/INDEX('Data_NSA'!$A:$OK,MATCH($E20,'Data_NSA'!$A:$A,0),MATCH($C20,'Data_NSA'!$1:$1,0))))/(100*(INDEX('Data_NSA'!$A:$OK,MATCH(H$1,'Data_NSA'!$A:$A,0),MATCH("CUUR0000SA0",'Data_NSA'!$1:$1,0))/INDEX('Data_NSA'!$A:$OK,MATCH($E20,'Data_NSA'!$A:$A,0),MATCH("CUUR0000SA0",'Data_NSA'!$1:$1,0)))),"") | I20: =IFERROR(100*($D20*(INDEX('Data_NSA'!$A:$OK,MATCH(I$1,'Data_NSA'!$A:$A,0),MATCH($C20,'Data_NSA'!$1:$1,0))/INDEX('Data_NSA'!$A:$OK,MATCH($E20,'Data_NSA'!$A:$A,0),MATCH($C20,'Data_NSA'!$1:$1,0))))/(100*(INDEX('Data_NSA'!$A:$OK,MATCH(I$1,'Data_NSA'!$A:$A,0),MATCH("CUUR0000SA0",'Data_NSA'!$1:$1,0))/INDEX('Data_NSA'!$A:$OK,MATCH($E20,'Data_NSA'!$A:$A,0),MATCH("CUUR0000SA0",'Data_NSA'!$1:$1,0)))),"")
A21: SEFB04 | B21: Other bakery products | C21: CUUR0000SEFB04 | D21: 0.217 | E21: 45992 | F21: 2024 | G21: =IFERROR(100*($D21*(INDEX('Data_NSA'!$A:$OK,MATCH(G$1,'Data_NSA'!$A:$A,0),MATCH($C21,'Data_NSA'!$1:$1,0))/INDEX('Data_NSA'!$A:$OK,MATCH($E21,'Data_NSA'!$A:$A,0),MATCH($C21,'Data_NSA'!$1:$1,0))))/(100*(INDEX('Data_NSA'!$A:$OK,MATCH(G$1,'Data_NSA'!$A:$A,0),MATCH("CUUR0000SA0",'Data_NSA'!$1:$1,0))/INDEX('Data_NSA'!$A:$OK,MATCH($E21,'Data_NSA'!$A:$A,0),MATCH("CUUR0000SA0",'Data_NSA'!$1:$1,0)))),"") | H21: =IFERROR(100*($D21*(INDEX('Data_NSA'!$A:$OK,MATCH(H$1,'Data_NSA'!$A:$A,0),MATCH($C21,'Data_NSA'!$1:$1,0))/INDEX('Data_NSA'!$A:$OK,MATCH($E21,'Data_NSA'!$A:$A,0),MATCH($C21,'Data_NSA'!$1:$1,0))))/(100*(INDEX('Data_NSA'!$A:$OK,MATCH(H$1,'Data_NSA'!$A:$A,0),MATCH("CUUR0000SA0",'Data_NSA'!$1:$1,0))/INDEX('Data_NSA'!$A:$OK,MATCH($E21,'Data_NSA'!$A:$A,0),MATCH("CUUR0000SA0",'Data_NSA'!$1:$1,0)))),"") | I21: =IFERROR(100*($D21*(INDEX('Data_NSA'!$A:$OK,MATCH(I$1,'Data_NSA'!$A:$A,0),MATCH($C21,'Data_NSA'!$1:$1,0))/INDEX('Data_NSA'!$A:$OK,MATCH($E21,'Data_NSA'!$A:$A,0),MATCH($C21,'Data_NSA'!$1:$1,0))))/(100*(INDEX('Data_NSA'!$A:$OK,MATCH(I$1,'Data_NSA'!$A:$A,0),MATCH("CUUR0000SA0",'Data_NSA'!$1:$1,0))/INDEX('Data_NSA'!$A:$OK,MATCH($E21,'Data_NSA'!$A:$A,0),MATCH("CUUR0000SA0",'Data_NSA'!$1:$1,0)))),"")
A22: SS02063 | B22: Fresh sweetrolls, coffeecakes, doughnuts | C22: CUUR0000SS02063 | E22: 45992 | F22: 2024 | G22: =IFERROR(100*($D22*(INDEX('Data_NSA'!$A:$OK,MATCH(G$1,'Data_NSA'!$A:$A,0),MATCH($C22,'Data_NSA'!$1:$1,0))/INDEX('Data_NSA'!$A:$OK,MATCH($E22,'Data_NSA'!$A:$A,0),MATCH($C22,'Data_NSA'!$1:$1,0))))/(100*(INDEX('Data_NSA'!$A:$OK,MATCH(G$1,'Data_NSA'!$A:$A,0),MATCH("CUUR0000SA0",'Data_NSA'!$1:$1,0))/INDEX('Data_NSA'!$A:$OK,MATCH($E22,'Data_NSA'!$A:$A,0),MATCH("CUUR0000SA0",'Data_NSA'!$1:$1,0)))),"") | H22: =IFERROR(100*($D22*(INDEX('Data_NSA'!$A:$OK,MATCH(H$1,'Data_NSA'!$A:$A,0),MATCH($C22,'Data_NSA'!$1:$1,0))/INDEX('Data_NSA'!$A:$OK,MATCH($E22,'Data_NSA'!$A:$A,0),MATCH($C22,'Data_NSA'!$1:$1,0))))/(100*(INDEX('Data_NSA'!$A:$OK,MATCH(H$1,'Data_NSA'!$A:$A,0),MATCH("CUUR0000SA0",'Data_NSA'!$1:$1,0))/INDEX('Data_NSA'!$A:$OK,MATCH($E22,'Data_NSA'!$A:$A,0),MATCH("CUUR0000SA0",'Data_NSA'!$1:$1,0)))),"") | I22: =IFERROR(100*($D22*(INDEX('Data_NSA'!$A:$OK,MATCH(I$1,'Data_NSA'!$A:$A,0),MATCH($C22,'Data_NSA'!$1:$1,0))/INDEX('Data_NSA'!$A:$OK,MATCH($E22,'Data_NSA'!$A:$A,0),MATCH($C22,'Data_NSA'!$1:$1,0))))/(100*(INDEX('Data_NSA'!$A:$OK,MATCH(I$1,'Data_NSA'!$A:$A,0),MATCH("CUUR0000SA0",'Data_NSA'!$1:$1,0))/INDEX('Data_NSA'!$A:$OK,MATCH($E22,'Data_NSA'!$A:$A,0),MATCH("CUUR0000SA0",'Data_NSA'!$1:$1,0)))),"")
A23: SS0206A | B23: Crackers, bread, and cracker products | C23: CUUR0000SS0206A | E23: 45992 | F23: 2024 | G23: =IFERROR(100*($D23*(INDEX('Data_NSA'!$A:$OK,MATCH(G$1,'Data_NSA'!$A:$A,0),MATCH($C23,'Data_NSA'!$1:$1,0))/INDEX('Data_NSA'!$A:$OK,MATCH($E23,'Data_NSA'!$A:$A,0),MATCH($C23,'Data_NSA'!$1:$1,0))))/(100*(INDEX('Data_NSA'!$A:$OK,MATCH(G$1,'Data_NSA'!$A:$A,0),MATCH("CUUR0000SA0",'Data_NSA'!$1:$1,0))/INDEX('Data_NSA'!$A:$OK,MATCH($E23,'Data_NSA'!$A:$A,0),MATCH("CUUR0000SA0",'Data_NSA'!$1:$1,0)))),"") | H23: =IFERROR(100*($D23*(INDEX('Data_NSA'!$A:$OK,MATCH(H$1,'Data_NSA'!$A:$A,0),MATCH($C23,'Data_NSA'!$1:$1,0))/INDEX('Data_NSA'!$A:$OK,MATCH($E23,'Data_NSA'!$A:$A,0),MATCH($C23,'Data_NSA'!$1:$1,0))))/(100*(INDEX('Data_NSA'!$A:$OK,MATCH(H$1,'Data_NSA'!$A:$A,0),MATCH("CUUR0000SA0",'Data_NSA'!$1:$1,0))/INDEX('Data_NSA'!$A:$OK,MATCH($E23,'Data_NSA'!$A:$A,0),MATCH("CUUR0000SA0",'Data_NSA'!$1:$1,0)))),"") | I23: =IFERROR(100*($D23*(INDEX('Data_NSA'!$A:$OK,MATCH(I$1,'Data_NSA'!$A:$A,0),MATCH($C23,'Data_NSA'!$1:$1,0))/INDEX('Data_NSA'!$A:$OK,MATCH($E23,'Data_NSA'!$A:$A,0),MATCH($C23,'Data_NSA'!$1:$1,0))))/(100*(INDEX('Data_NSA'!$A:$OK,MATCH(I$1,'Data_NSA'!$A:$A,0),MATCH("CUUR0000SA0",'Data_NSA'!$1:$1,0))/INDEX('Data_NSA'!$A:$OK,MATCH($E23,'Data_NSA'!$A:$A,0),MATCH("CUUR0000SA0",'Data_NSA'!$1:$1,0)))),"")
A24: SS0206B | B24: Frozen and refrigerated bakery products, pies, tarts, turnovers | C24: CUUR0000SS0206B | E24: 45992 | F24: 2024 | G24: =IFERROR(100*($D24*(INDEX('Data_NSA'!$A:$OK,MATCH(G$1,'Data_NSA'!$A:$A,0),MATCH($C24,'Data_NSA'!$1:$1,0))/INDEX('Data_NSA'!$A:$OK,MATCH($E24,'Data_NSA'!$A:$A,0),MATCH($C24,'Data_NSA'!$1:$1,0))))/(100*(INDEX('Data_NSA'!$A:$OK,MATCH(G$1,'Data_NSA'!$A:$A,0),MATCH("CUUR0000SA0",'Data_NSA'!$1:$1,0))/INDEX('Data_NSA'!$A:$OK,MATCH($E24,'Data_NSA'!$A:$A,0),MATCH("CUUR0000SA0",'Data_NSA'!$1:$1,0)))),"") | H24: =IFERROR(100*($D24*(INDEX('Data_NSA'!$A:$OK,MATCH(H$1,'Data_NSA'!$A:$A,0),MATCH($C24,'Data_NSA'!$1:$1,0))/INDEX('Data_NSA'!$A:$OK,MATCH($E24,'Data_NSA'!$A:$A,0),MATCH($C24,'Data_NSA'!$1:$1,0))))/(100*(INDEX('Data_NSA'!$A:$OK,MATCH(H$1,'Data_NSA'!$A:$A,0),MATCH("CUUR0000SA0",'Data_NSA'!$1:$1,0))/INDEX('Data_NSA'!$A:$OK,MATCH($E24,'Data_NSA'!$A:$A,0),MATCH("CUUR0000SA0",'Data_NSA'!$1:$1,0)))),"") | I24: =IFERROR(100*($D24*(INDEX('Data_NSA'!$A:$OK,MATCH(I$1,'Data_NSA'!$A:$A,0),MATCH($C24,'Data_NSA'!$1:$1,0))/INDEX('Data_NSA'!$A:$OK,MATCH($E24,'Data_NSA'!$A:$A,0),MATCH($C24,'Data_NSA'!$1:$1,0))))/(100*(INDEX('Data_NSA'!$A:$OK,MATCH(I$1,'Data_NSA'!$A:$A,0),MATCH("CUUR0000SA0",'Data_NSA'!$1:$1,0))/INDEX('Data_NSA'!$A:$OK,MATCH($E24,'Data_NSA'!$A:$A,0),MATCH("CUUR0000SA0",'Data_NSA'!$1:$1,0)))),"")
A25: SAF112 | B25: Meats, poultry, fish, and eggs | C25: CUUR0000SAF112 | D25: 1.995 | E25: 45992 | F25: 2024 | G25: =IFERROR(100*($D25*(INDEX('Data_NSA'!$A:$OK,MATCH(G$1,'Data_NSA'!$A:$A,0),MATCH($C25,'Data_NSA'!$1:$1,0))/INDEX('Data_NSA'!$A:$OK,MATCH($E25,'Data_NSA'!$A:$A,0),MATCH($C25,'Data_NSA'!$1:$1,0))))/(100*(INDEX('Data_NSA'!$A:$OK,MATCH(G$1,'Data_NSA'!$A:$A,0),MATCH("CUUR0000SA0",'Data_NSA'!$1:$1,0))/INDEX('Data_NSA'!$A:$OK,MATCH($E25,'Data_NSA'!$A:$A,0),MATCH("CUUR0000SA0",'Data_NSA'!$1:$1,0)))),"") | H25: =IFERROR(100*($D25*(INDEX('Data_NSA'!$A:$OK,MATCH(H$1,'Data_NSA'!$A:$A,0),MATCH($C25,'Data_NSA'!$1:$1,0))/INDEX('Data_NSA'!$A:$OK,MATCH($E25,'Data_NSA'!$A:$A,0),MATCH($C25,'Data_NSA'!$1:$1,0))))/(100*(INDEX('Data_NSA'!$A:$OK,MATCH(H$1,'Data_NSA'!$A:$A,0),MATCH("CUUR0000SA0",'Data_NSA'!$1:$1,0))/INDEX('Data_NSA'!$A:$OK,MATCH($E25,'Data_NSA'!$A:$A,0),MATCH("CUUR0000SA0",'Data_NSA'!$1:$1,0)))),"") | I25: =IFERROR(100*($D25*(INDEX('Data_NSA'!$A:$OK,MATCH(I$1,'Data_NSA'!$A:$A,0),MATCH($C25,'Data_NSA'!$1:$1,0))/INDEX('Data_NSA'!$A:$OK,MATCH($E25,'Data_NSA'!$A:$A,0),MATCH($C25,'Data_NSA'!$1:$1,0))))/(100*(INDEX('Data_NSA'!$A:$OK,MATCH(I$1,'Data_NSA'!$A:$A,0),MATCH("CUUR0000SA0",'Data_NSA'!$1:$1,0))/INDEX('Data_NSA'!$A:$OK,MATCH($E25,'Data_NSA'!$A:$A,0),MATCH("CUUR0000SA0",'Data_NSA'!$1:$1,0)))),"")
A26: SAF1121 | B26: Meats, poultry, and fish | C26: CUUR0000SAF1121 | D26: 1.862 | E26: 45992 | F26: 2024 | G26: =IFERROR(100*($D26*(INDEX('Data_NSA'!$A:$OK,MATCH(G$1,'Data_NSA'!$A:$A,0),MATCH($C26,'Data_NSA'!$1:$1,0))/INDEX('Data_NSA'!$A:$OK,MATCH($E26,'Data_NSA'!$A:$A,0),MATCH($C26,'Data_NSA'!$1:$1,0))))/(100*(INDEX('Data_NSA'!$A:$OK,MATCH(G$1,'Data_NSA'!$A:$A,0),MATCH("CUUR0000SA0",'Data_NSA'!$1:$1,0))/INDEX('Data_NSA'!$A:$OK,MATCH($E26,'Data_NSA'!$A:$A,0),MATCH("CUUR0000SA0",'Data_NSA'!$1:$1,0)))),"") | H26: =IFERROR(100*($D26*(INDEX('Data_NSA'!$A:$OK,MATCH(H$1,'Data_NSA'!$A:$A,0),MATCH($C26,'Data_NSA'!$1:$1,0))/INDEX('Data_NSA'!$A:$OK,MATCH($E26,'Data_NSA'!$A:$A,0),MATCH($C26,'Data_NSA'!$1:$1,0))))/(100*(INDEX('Data_NSA'!$A:$OK,MATCH(H$1,'Data_NSA'!$A:$A,0),MATCH("CUUR0000SA0",'Data_NSA'!$1:$1,0))/INDEX('Data_NSA'!$A:$OK,MATCH($E26,'Data_NSA'!$A:$A,0),MATCH("CUUR0000SA0",'Data_NSA'!$1:$1,0)))),"") | I26: =IFERROR(100*($D26*(INDEX('Data_NSA'!$A:$OK,MATCH(I$1,'Data_NSA'!$A:$A,0),MATCH($C26,'Data_NSA'!$1:$1,0))/INDEX('Data_NSA'!$A:$OK,MATCH($E26,'Data_NSA'!$A:$A,0),MATCH($C26,'Data_NSA'!$1:$1,0))))/(100*(INDEX('Data_NSA'!$A:$OK,MATCH(I$1,'Data_NSA'!$A:$A,0),MATCH("CUUR0000SA0",'Data_NSA'!$1:$1,0))/INDEX('Data_NSA'!$A:$OK,MATCH($E26,'Data_NSA'!$A:$A,0),MATCH("CUUR0000SA0",'Data_NSA'!$1:$1,0)))),"")
A27: SAF11211 | B27: Meats | C27: CUUR0000SAF11211 | D27: 1.186 | E27: 45992 | F27: 2024 | G27: =IFERROR(100*($D27*(INDEX('Data_NSA'!$A:$OK,MATCH(G$1,'Data_NSA'!$A:$A,0),MATCH($C27,'Data_NSA'!$1:$1,0))/INDEX('Data_NSA'!$A:$OK,MATCH($E27,'Data_NSA'!$A:$A,0),MATCH($C27,'Data_NSA'!$1:$1,0))))/(100*(INDEX('Data_NSA'!$A:$OK,MATCH(G$1,'Data_NSA'!$A:$A,0),MATCH("CUUR0000SA0",'Data_NSA'!$1:$1,0))/INDEX('Data_NSA'!$A:$OK,MATCH($E27,'Data_NSA'!$A:$A,0),MATCH("CUUR0000SA0",'Data_NSA'!$1:$1,0)))),"") | H27: =IFERROR(100*($D27*(INDEX('Data_NSA'!$A:$OK,MATCH(H$1,'Data_NSA'!$A:$A,0),MATCH($C27,'Data_NSA'!$1:$1,0))/INDEX('Data_NSA'!$A:$OK,MATCH($E27,'Data_NSA'!$A:$A,0),MATCH($C27,'Data_NSA'!$1:$1,0))))/(100*(INDEX('Data_NSA'!$A:$OK,MATCH(H$1,'Data_NSA'!$A:$A,0),MATCH("CUUR0000SA0",'Data_NSA'!$1:$1,0))/INDEX('Data_NSA'!$A:$OK,MATCH($E27,'Data_NSA'!$A:$A,0),MATCH("CUUR0000SA0",'Data_NSA'!$1:$1,0)))),"") | I27: =IFERROR(100*($D27*(INDEX('Data_NSA'!$A:$OK,MATCH(I$1,'Data_NSA'!$A:$A,0),MATCH($C27,'Data_NSA'!$1:$1,0))/INDEX('Data_NSA'!$A:$OK,MATCH($E27,'Data_NSA'!$A:$A,0),MATCH($C27,'Data_NSA'!$1:$1,0))))/(100*(INDEX('Data_NSA'!$A:$OK,MATCH(I$1,'Data_NSA'!$A:$A,0),MATCH("CUUR0000SA0",'Data_NSA'!$1:$1,0))/INDEX('Data_NSA'!$A:$OK,MATCH($E27,'Data_NSA'!$A:$A,0),MATCH("CUUR0000SA0",'Data_NSA'!$1:$1,0)))),"")
A28: SEFC | B28: Beef and veal | C28: CUUR0000SEFC | D28: 0.638 | E28: 45992 | F28: 2024 | G28: =IFERROR(100*($D28*(INDEX('Data_NSA'!$A:$OK,MATCH(G$1,'Data_NSA'!$A:$A,0),MATCH($C28,'Data_NSA'!$1:$1,0))/INDEX('Data_NSA'!$A:$OK,MATCH($E28,'Data_NSA'!$A:$A,0),MATCH($C28,'Data_NSA'!$1:$1,0))))/(100*(INDEX('Data_NSA'!$A:$OK,MATCH(G$1,'Data_NSA'!$A:$A,0),MATCH("CUUR0000SA0",'Data_NSA'!$1:$1,0))/INDEX('Data_NSA'!$A:$OK,MATCH($E28,'Data_NSA'!$A:$A,0),MATCH("CUUR0000SA0",'Data_NSA'!$1:$1,0)))),"") | H28: =IFERROR(100*($D28*(INDEX('Data_NSA'!$A:$OK,MATCH(H$1,'Data_NSA'!$A:$A,0),MATCH($C28,'Data_NSA'!$1:$1,0))/INDEX('Data_NSA'!$A:$OK,MATCH($E28,'Data_NSA'!$A:$A,0),MATCH($C28,'Data_NSA'!$1:$1,0))))/(100*(INDEX('Data_NSA'!$A:$OK,MATCH(H$1,'Data_NSA'!$A:$A,0),MATCH("CUUR0000SA0",'Data_NSA'!$1:$1,0))/INDEX('Data_NSA'!$A:$OK,MATCH($E28,'Data_NSA'!$A:$A,0),MATCH("CUUR0000SA0",'Data_NSA'!$1:$1,0)))),"") | I28: =IFERROR(100*($D28*(INDEX('Data_NSA'!$A:$OK,MATCH(I$1,'Data_NSA'!$A:$A,0),MATCH($C28,'Data_NSA'!$1:$1,0))/INDEX('Data_NSA'!$A:$OK,MATCH($E28,'Data_NSA'!$A:$A,0),MATCH($C28,'Data_NSA'!$1:$1,0))))/(100*(INDEX('Data_NSA'!$A:$OK,MATCH(I$1,'Data_NSA'!$A:$A,0),MATCH("CUUR0000SA0",'Data_NSA'!$1:$1,0))/INDEX('Data_NSA'!$A:$OK,MATCH($E28,'Data_NSA'!$A:$A,0),MATCH("CUUR0000SA0",'Data_NSA'!$1:$1,0)))),"")
A29: SEFC01 | B29: Uncooked ground beef | C29: CUUR0000SEFC01 | D29: 0.236 | E29: 45992 | F29: 2024 | G29: =IFERROR(100*($D29*(INDEX('Data_NSA'!$A:$OK,MATCH(G$1,'Data_NSA'!$A:$A,0),MATCH($C29,'Data_NSA'!$1:$1,0))/INDEX('Data_NSA'!$A:$OK,MATCH($E29,'Data_NSA'!$A:$A,0),MATCH($C29,'Data_NSA'!$1:$1,0))))/(100*(INDEX('Data_NSA'!$A:$OK,MATCH(G$1,'Data_NSA'!$A:$A,0),MATCH("CUUR0000SA0",'Data_NSA'!$1:$1,0))/INDEX('Data_NSA'!$A:$OK,MATCH($E29,'Data_NSA'!$A:$A,0),MATCH("CUUR0000SA0",'Data_NSA'!$1:$1,0)))),"") | H29: =IFERROR(100*($D29*(INDEX('Data_NSA'!$A:$OK,MATCH(H$1,'Data_NSA'!$A:$A,0),MATCH($C29,'Data_NSA'!$1:$1,0))/INDEX('Data_NSA'!$A:$OK,MATCH($E29,'Data_NSA'!$A:$A,0),MATCH($C29,'Data_NSA'!$1:$1,0))))/(100*(INDEX('Data_NSA'!$A:$OK,MATCH(H$1,'Data_NSA'!$A:$A,0),MATCH("CUUR0000SA0",'Data_NSA'!$1:$1,0))/INDEX('Data_NSA'!$A:$OK,MATCH($E29,'Data_NSA'!$A:$A,0),MATCH("CUUR0000SA0",'Data_NSA'!$1:$1,0)))),"") | I29: =IFERROR(100*($D29*(INDEX('Data_NSA'!$A:$OK,MATCH(I$1,'Data_NSA'!$A:$A,0),MATCH($C29,'Data_NSA'!$1:$1,0))/INDEX('Data_NSA'!$A:$OK,MATCH($E29,'Data_NSA'!$A:$A,0),MATCH($C29,'Data_NSA'!$1:$1,0))))/(100*(INDEX('Data_NSA'!$A:$OK,MATCH(I$1,'Data_NSA'!$A:$A,0),MATCH("CUUR0000SA0",'Data_NSA'!$1:$1,0))/INDEX('Data_NSA'!$A:$OK,MATCH($E29,'Data_NSA'!$A:$A,0),MATCH("CUUR0000SA0",'Data_NSA'!$1:$1,0)))),"")
A30: SEFC02 | B30: Uncooked beef roasts | C30: CUUR0000SEFC02 | D30: 0.087 | E30: 45992 | F30: 2024 | G30: =IFERROR(100*($D30*(INDEX('Data_NSA'!$A:$OK,MATCH(G$1,'Data_NSA'!$A:$A,0),MATCH($C30,'Data_NSA'!$1:$1,0))/INDEX('Data_NSA'!$A:$OK,MATCH($E30,'Data_NSA'!$A:$A,0),MATCH($C30,'Data_NSA'!$1:$1,0))))/(100*(INDEX('Data_NSA'!$A:$OK,MATCH(G$1,'Data_NSA'!$A:$A,0),MATCH("CUUR0000SA0",'Data_NSA'!$1:$1,0))/INDEX('Data_NSA'!$A:$OK,MATCH($E30,'Data_NSA'!$A:$A,0),MATCH("CUUR0000SA0",'Data_NSA'!$1:$1,0)))),"") | H30: =IFERROR(100*($D30*(INDEX('Data_NSA'!$A:$OK,MATCH(H$1,'Data_NSA'!$A:$A,0),MATCH($C30,'Data_NSA'!$1:$1,0))/INDEX('Data_NSA'!$A:$OK,MATCH($E30,'Data_NSA'!$A:$A,0),MATCH($C30,'Data_NSA'!$1:$1,0))))/(100*(INDEX('Data_NSA'!$A:$OK,MATCH(H$1,'Data_NSA'!$A:$A,0),MATCH("CUUR0000SA0",'Data_NSA'!$1:$1,0))/INDEX('Data_NSA'!$A:$OK,MATCH($E30,'Data_NSA'!$A:$A,0),MATCH("CUUR0000SA0",'Data_NSA'!$1:$1,0)))),"") | I30: =IFERROR(100*($D30*(INDEX('Data_NSA'!$A:$OK,MATCH(I$1,'Data_NSA'!$A:$A,0),MATCH($C30,'Data_NSA'!$1:$1,0))/INDEX('Data_NSA'!$A:$OK,MATCH($E30,'Data_NSA'!$A:$A,0),MATCH($C30,'Data_NSA'!$1:$1,0))))/(100*(INDEX('Data_NSA'!$A:$OK,MATCH(I$1,'Data_NSA'!$A:$A,0),MATCH("CUUR0000SA0",'Data_NSA'!$1:$1,0))/INDEX('Data_NSA'!$A:$OK,MATCH($E30,'Data_NSA'!$A:$A,0),MATCH("CUUR0000SA0",'Data_NSA'!$1:$1,0)))),"")
A31: SEFC03 | B31: Uncooked beef steaks | C31: CUUR0000SEFC03 | D31: 0.24 | E31: 45992 | F31: 2024 | G31: =IFERROR(100*($D31*(INDEX('Data_NSA'!$A:$OK,MATCH(G$1,'Data_NSA'!$A:$A,0),MATCH($C31,'Data_NSA'!$1:$1,0))/INDEX('Data_NSA'!$A:$OK,MATCH($E31,'Data_NSA'!$A:$A,0),MATCH($C31,'Data_NSA'!$1:$1,0))))/(100*(INDEX('Data_NSA'!$A:$OK,MATCH(G$1,'Data_NSA'!$A:$A,0),MATCH("CUUR0000SA0",'Data_NSA'!$1:$1,0))/INDEX('Data_NSA'!$A:$OK,MATCH($E31,'Data_NSA'!$A:$A,0),MATCH("CUUR0000SA0",'Data_NSA'!$1:$1,0)))),"") | H31: =IFERROR(100*($D31*(INDEX('Data_NSA'!$A:$OK,MATCH(H$1,'Data_NSA'!$A:$A,0),MATCH($C31,'Data_NSA'!$1:$1,0))/INDEX('Data_NSA'!$A:$OK,MATCH($E31,'Data_NSA'!$A:$A,0),MATCH($C31,'Data_NSA'!$1:$1,0))))/(100*(INDEX('Data_NSA'!$A:$OK,MATCH(H$1,'Data_NSA'!$A:$A,0),MATCH("CUUR0000SA0",'Data_NSA'!$1:$1,0))/INDEX('Data_NSA'!$A:$OK,MATCH($E31,'Data_NSA'!$A:$A,0),MATCH("CUUR0000SA0",'Data_NSA'!$1:$1,0)))),"") | I31: =IFERROR(100*($D31*(INDEX('Data_NSA'!$A:$OK,MATCH(I$1,'Data_NSA'!$A:$A,0),MATCH($C31,'Data_NSA'!$1:$1,0))/INDEX('Data_NSA'!$A:$OK,MATCH($E31,'Data_NSA'!$A:$A,0),MATCH($C31,'Data_NSA'!$1:$1,0))))/(100*(INDEX('Data_NSA'!$A:$OK,MATCH(I$1,'Data_NSA'!$A:$A,0),MATCH("CUUR0000SA0",'Data_NSA'!$1:$1,0))/INDEX('Data_NSA'!$A:$OK,MATCH($E31,'Data_NSA'!$A:$A,0),MATCH("CUUR0000SA0",'Data_NSA'!$1:$1,0)))),"")
A32: SEFC04 | B32: Uncooked other beef and veal | C32: CUUR0000SEFC04 | D32: 0.076 | E32: 45992 | F32: 2024 | G32: =IFERROR(100*($D32*(INDEX('Data_NSA'!$A:$OK,MATCH(G$1,'Data_NSA'!$A:$A,0),MATCH($C32,'Data_NSA'!$1:$1,0))/INDEX('Data_NSA'!$A:$OK,MATCH($E32,'Data_NSA'!$A:$A,0),MATCH($C32,'Data_NSA'!$1:$1,0))))/(100*(INDEX('Data_NSA'!$A:$OK,MATCH(G$1,'Data_NSA'!$A:$A,0),MATCH("CUUR0000SA0",'Data_NSA'!$1:$1,0))/INDEX('Data_NSA'!$A:$OK,MATCH($E32,'Data_NSA'!$A:$A,0),MATCH("CUUR0000SA0",'Data_NSA'!$1:$1,0)))),"") | H32: =IFERROR(100*($D32*(INDEX('Data_NSA'!$A:$OK,MATCH(H$1,'Data_NSA'!$A:$A,0),MATCH($C32,'Data_NSA'!$1:$1,0))/INDEX('Data_NSA'!$A:$OK,MATCH($E32,'Data_NSA'!$A:$A,0),MATCH($C32,'Data_NSA'!$1:$1,0))))/(100*(INDEX('Data_NSA'!$A:$OK,MATCH(H$1,'Data_NSA'!$A:$A,0),MATCH("CUUR0000SA0",'Data_NSA'!$1:$1,0))/INDEX('Data_NSA'!$A:$OK,MATCH($E32,'Data_NSA'!$A:$A,0),MATCH("CUUR0000SA0",'Data_NSA'!$1:$1,0)))),"") | I32: =IFERROR(100*($D32*(INDEX('Data_NSA'!$A:$OK,MATCH(I$1,'Data_NSA'!$A:$A,0),MATCH($C32,'Data_NSA'!$1:$1,0))/INDEX('Data_NSA'!$A:$OK,MATCH($E32,'Data_NSA'!$A:$A,0),MATCH($C32,'Data_NSA'!$1:$1,0))))/(100*(INDEX('Data_NSA'!$A:$OK,MATCH(I$1,'Data_NSA'!$A:$A,0),MATCH("CUUR0000SA0",'Data_NSA'!$1:$1,0))/INDEX('Data_NSA'!$A:$OK,MATCH($E32,'Data_NSA'!$A:$A,0),MATCH("CUUR0000SA0",'Data_NSA'!$1:$1,0)))),"")
A33: SEFD | B33: Pork | C33: CUUR0000SEFD | D33: 0.34 | E33: 45992 | F33: 2024 | G33: =IFERROR(100*($D33*(INDEX('Data_NSA'!$A:$OK,MATCH(G$1,'Data_NSA'!$A:$A,0),MATCH($C33,'Data_NSA'!$1:$1,0))/INDEX('Data_NSA'!$A:$OK,MATCH($E33,'Data_NSA'!$A:$A,0),MATCH($C33,'Data_NSA'!$1:$1,0))))/(100*(INDEX('Data_NSA'!$A:$OK,MATCH(G$1,'Data_NSA'!$A:$A,0),MATCH("CUUR0000SA0",'Data_NSA'!$1:$1,0))/INDEX('Data_NSA'!$A:$OK,MATCH($E33,'Data_NSA'!$A:$A,0),MATCH("CUUR0000SA0",'Data_NSA'!$1:$1,0)))),"") | H33: =IFERROR(100*($D33*(INDEX('Data_NSA'!$A:$OK,MATCH(H$1,'Data_NSA'!$A:$A,0),MATCH($C33,'Data_NSA'!$1:$1,0))/INDEX('Data_NSA'!$A:$OK,MATCH($E33,'Data_NSA'!$A:$A,0),MATCH($C33,'Data_NSA'!$1:$1,0))))/(100*(INDEX('Data_NSA'!$A:$OK,MATCH(H$1,'Data_NSA'!$A:$A,0),MATCH("CUUR0000SA0",'Data_NSA'!$1:$1,0))/INDEX('Data_NSA'!$A:$OK,MATCH($E33,'Data_NSA'!$A:$A,0),MATCH("CUUR0000SA0",'Data_NSA'!$1:$1,0)))),"") | I33: =IFERROR(100*($D33*(INDEX('Data_NSA'!$A:$OK,MATCH(I$1,'Data_NSA'!$A:$A,0),MATCH($C33,'Data_NSA'!$1:$1,0))/INDEX('Data_NSA'!$A:$OK,MATCH($E33,'Data_NSA'!$A:$A,0),MATCH($C33,'Data_NSA'!$1:$1,0))))/(100*(INDEX('Data_NSA'!$A:$OK,MATCH(I$1,'Data_NSA'!$A:$A,0),MATCH("CUUR0000SA0",'Data_NSA'!$1:$1,0))/INDEX('Data_NSA'!$A:$OK,MATCH($E33,'Data_NSA'!$A:$A,0),MATCH("CUUR0000SA0",'Data_NSA'!$1:$1,0)))),"")
A34: SEFD01 | B34: Bacon, breakfast sausage, and related products | C34: CUUR0000SEFD01 | D34: 0.131 | E34: 45992 | F34: 2024 | G34: =IFERROR(100*($D34*(INDEX('Data_NSA'!$A:$OK,MATCH(G$1,'Data_NSA'!$A:$A,0),MATCH($C34,'Data_NSA'!$1:$1,0))/INDEX('Data_NSA'!$A:$OK,MATCH($E34,'Data_NSA'!$A:$A,0),MATCH($C34,'Data_NSA'!$1:$1,0))))/(100*(INDEX('Data_NSA'!$A:$OK,MATCH(G$1,'Data_NSA'!$A:$A,0),MATCH("CUUR0000SA0",'Data_NSA'!$1:$1,0))/INDEX('Data_NSA'!$A:$OK,MATCH($E34,'Data_NSA'!$A:$A,0),MATCH("CUUR0000SA0",'Data_NSA'!$1:$1,0)))),"") | H34: =IFERROR(100*($D34*(INDEX('Data_NSA'!$A:$OK,MATCH(H$1,'Data_NSA'!$A:$A,0),MATCH($C34,'Data_NSA'!$1:$1,0))/INDEX('Data_NSA'!$A:$OK,MATCH($E34,'Data_NSA'!$A:$A,0),MATCH($C34,'Data_NSA'!$1:$1,0))))/(100*(INDEX('Data_NSA'!$A:$OK,MATCH(H$1,'Data_NSA'!$A:$A,0),MATCH("CUUR0000SA0",'Data_NSA'!$1:$1,0))/INDEX('Data_NSA'!$A:$OK,MATCH($E34,'Data_NSA'!$A:$A,0),MATCH("CUUR0000SA0",'Data_NSA'!$1:$1,0)))),"") | I34: =IFERROR(100*($D34*(INDEX('Data_NSA'!$A:$OK,MATCH(I$1,'Data_NSA'!$A:$A,0),MATCH($C34,'Data_NSA'!$1:$1,0))/INDEX('Data_NSA'!$A:$OK,MATCH($E34,'Data_NSA'!$A:$A,0),MATCH($C34,'Data_NSA'!$1:$1,0))))/(100*(INDEX('Data_NSA'!$A:$OK,MATCH(I$1,'Data_NSA'!$A:$A,0),MATCH("CUUR0000SA0",'Data_NSA'!$1:$1,0))/INDEX('Data_NSA'!$A:$OK,MATCH($E34,'Data_NSA'!$A:$A,0),MATCH("CUUR0000SA0",'Data_NSA'!$1:$1,0)))),"")
A35: SS04011 | B35: Bacon and related products | C35: CUUR0000SS04011 | E35: 45992 | F35: 2024 | G35: =IFERROR(100*($D35*(INDEX('Data_NSA'!$A:$OK,MATCH(G$1,'Data_NSA'!$A:$A,0),MATCH($C35,'Data_NSA'!$1:$1,0))/INDEX('Data_NSA'!$A:$OK,MATCH($E35,'Data_NSA'!$A:$A,0),MATCH($C35,'Data_NSA'!$1:$1,0))))/(100*(INDEX('Data_NSA'!$A:$OK,MATCH(G$1,'Data_NSA'!$A:$A,0),MATCH("CUUR0000SA0",'Data_NSA'!$1:$1,0))/INDEX('Data_NSA'!$A:$OK,MATCH($E35,'Data_NSA'!$A:$A,0),MATCH("CUUR0000SA0",'Data_NSA'!$1:$1,0)))),"") | H35: =IFERROR(100*($D35*(INDEX('Data_NSA'!$A:$OK,MATCH(H$1,'Data_NSA'!$A:$A,0),MATCH($C35,'Data_NSA'!$1:$1,0))/INDEX('Data_NSA'!$A:$OK,MATCH($E35,'Data_NSA'!$A:$A,0),MATCH($C35,'Data_NSA'!$1:$1,0))))/(100*(INDEX('Data_NSA'!$A:$OK,MATCH(H$1,'Data_NSA'!$A:$A,0),MATCH("CUUR0000SA0",'Data_NSA'!$1:$1,0))/INDEX('Data_NSA'!$A:$OK,MATCH($E35,'Data_NSA'!$A:$A,0),MATCH("CUUR0000SA0",'Data_NSA'!$1:$1,0)))),"") | I35: =IFERROR(100*($D35*(INDEX('Data_NSA'!$A:$OK,MATCH(I$1,'Data_NSA'!$A:$A,0),MATCH($C35,'Data_NSA'!$1:$1,0))/INDEX('Data_NSA'!$A:$OK,MATCH($E35,'Data_NSA'!$A:$A,0),MATCH($C35,'Data_NSA'!$1:$1,0))))/(100*(INDEX('Data_NSA'!$A:$OK,MATCH(I$1,'Data_NSA'!$A:$A,0),MATCH("CUUR0000SA0",'Data_NSA'!$1:$1,0))/INDEX('Data_NSA'!$A:$OK,MATCH($E35,'Data_NSA'!$A:$A,0),MATCH("CUUR0000SA0",'Data_NSA'!$1:$1,0)))),"")
A36: SS04012 | B36: Breakfast sausage and related products | C36: CUUR0000SS04012 | E36: 45992 | F36: 2024 | G36: =IFERROR(100*($D36*(INDEX('Data_NSA'!$A:$OK,MATCH(G$1,'Data_NSA'!$A:$A,0),MATCH($C36,'Data_NSA'!$1:$1,0))/INDEX('Data_NSA'!$A:$OK,MATCH($E36,'Data_NSA'!$A:$A,0),MATCH($C36,'Data_NSA'!$1:$1,0))))/(100*(INDEX('Data_NSA'!$A:$OK,MATCH(G$1,'Data_NSA'!$A:$A,0),MATCH("CUUR0000SA0",'Data_NSA'!$1:$1,0))/INDEX('Data_NSA'!$A:$OK,MATCH($E36,'Data_NSA'!$A:$A,0),MATCH("CUUR0000SA0",'Data_NSA'!$1:$1,0)))),"") | H36: =IFERROR(100*($D36*(INDEX('Data_NSA'!$A:$OK,MATCH(H$1,'Data_NSA'!$A:$A,0),MATCH($C36,'Data_NSA'!$1:$1,0))/INDEX('Data_NSA'!$A:$OK,MATCH($E36,'Data_NSA'!$A:$A,0),MATCH($C36,'Data_NSA'!$1:$1,0))))/(100*(INDEX('Data_NSA'!$A:$OK,MATCH(H$1,'Data_NSA'!$A:$A,0),MATCH("CUUR0000SA0",'Data_NSA'!$1:$1,0))/INDEX('Data_NSA'!$A:$OK,MATCH($E36,'Data_NSA'!$A:$A,0),MATCH("CUUR0000SA0",'Data_NSA'!$1:$1,0)))),"") | I36: =IFERROR(100*($D36*(INDEX('Data_NSA'!$A:$OK,MATCH(I$1,'Data_NSA'!$A:$A,0),MATCH($C36,'Data_NSA'!$1:$1,0))/INDEX('Data_NSA'!$A:$OK,MATCH($E36,'Data_NSA'!$A:$A,0),MATCH($C36,'Data_NSA'!$1:$1,0))))/(100*(INDEX('Data_NSA'!$A:$OK,MATCH(I$1,'Data_NSA'!$A:$A,0),MATCH("CUUR0000SA0",'Data_NSA'!$1:$1,0))/INDEX('Data_NSA'!$A:$OK,MATCH($E36,'Data_NSA'!$A:$A,0),MATCH("CUUR0000SA0",'Data_NSA'!$1:$1,0)))),"")
A37: SEFD02 | B37: Ham | C37: CUUR0000SEFD02 | D37: 0.066 | E37: 45992 | F37: 2024 | G37: =IFERROR(100*($D37*(INDEX('Data_NSA'!$A:$OK,MATCH(G$1,'Data_NSA'!$A:$A,0),MATCH($C37,'Data_NSA'!$1:$1,0))/INDEX('Data_NSA'!$A:$OK,MATCH($E37,'Data_NSA'!$A:$A,0),MATCH($C37,'Data_NSA'!$1:$1,0))))/(100*(INDEX('Data_NSA'!$A:$OK,MATCH(G$1,'Data_NSA'!$A:$A,0),MATCH("CUUR0000SA0",'Data_NSA'!$1:$1,0))/INDEX('Data_NSA'!$A:$OK,MATCH($E37,'Data_NSA'!$A:$A,0),MATCH("CUUR0000SA0",'Data_NSA'!$1:$1,0)))),"") | H37: =IFERROR(100*($D37*(INDEX('Data_NSA'!$A:$OK,MATCH(H$1,'Data_NSA'!$A:$A,0),MATCH($C37,'Data_NSA'!$1:$1,0))/INDEX('Data_NSA'!$A:$OK,MATCH($E37,'Data_NSA'!$A:$A,0),MATCH($C37,'Data_NSA'!$1:$1,0))))/(100*(INDEX('Data_NSA'!$A:$OK,MATCH(H$1,'Data_NSA'!$A:$A,0),MATCH("CUUR0000SA0",'Data_NSA'!$1:$1,0))/INDEX('Data_NSA'!$A:$OK,MATCH($E37,'Data_NSA'!$A:$A,0),MATCH("CUUR0000SA0",'Data_NSA'!$1:$1,0)))),"") | I37: =IFERROR(100*($D37*(INDEX('Data_NSA'!$A:$OK,MATCH(I$1,'Data_NSA'!$A:$A,0),MATCH($C37,'Data_NSA'!$1:$1,0))/INDEX('Data_NSA'!$A:$OK,MATCH($E37,'Data_NSA'!$A:$A,0),MATCH($C37,'Data_NSA'!$1:$1,0))))/(100*(INDEX('Data_NSA'!$A:$OK,MATCH(I$1,'Data_NSA'!$A:$A,0),MATCH("CUUR0000SA0",'Data_NSA'!$1:$1,0))/INDEX('Data_NSA'!$A:$OK,MATCH($E37,'Data_NSA'!$A:$A,0),MATCH("CUUR0000SA0",'Data_NSA'!$1:$1,0)))),"")
A38: SS04031 | B38: Ham, excluding canned | C38: CUUR0000SS04031 | E38: 45992 | F38: 2024 | G38: =IFERROR(100*($D38*(INDEX('Data_NSA'!$A:$OK,MATCH(G$1,'Data_NSA'!$A:$A,0),MATCH($C38,'Data_NSA'!$1:$1,0))/INDEX('Data_NSA'!$A:$OK,MATCH($E38,'Data_NSA'!$A:$A,0),MATCH($C38,'Data_NSA'!$1:$1,0))))/(100*(INDEX('Data_NSA'!$A:$OK,MATCH(G$1,'Data_NSA'!$A:$A,0),MATCH("CUUR0000SA0",'Data_NSA'!$1:$1,0))/INDEX('Data_NSA'!$A:$OK,MATCH($E38,'Data_NSA'!$A:$A,0),MATCH("CUUR0000SA0",'Data_NSA'!$1:$1,0)))),"") | H38: =IFERROR(100*($D38*(INDEX('Data_NSA'!$A:$OK,MATCH(H$1,'Data_NSA'!$A:$A,0),MATCH($C38,'Data_NSA'!$1:$1,0))/INDEX('Data_NSA'!$A:$OK,MATCH($E38,'Data_NSA'!$A:$A,0),MATCH($C38,'Data_NSA'!$1:$1,0))))/(100*(INDEX('Data_NSA'!$A:$OK,MATCH(H$1,'Data_NSA'!$A:$A,0),MATCH("CUUR0000SA0",'Data_NSA'!$1:$1,0))/INDEX('Data_NSA'!$A:$OK,MATCH($E38,'Data_NSA'!$A:$A,0),MATCH("CUUR0000SA0",'Data_NSA'!$1:$1,0)))),"") | I38: =IFERROR(100*($D38*(INDEX('Data_NSA'!$A:$OK,MATCH(I$1,'Data_NSA'!$A:$A,0),MATCH($C38,'Data_NSA'!$1:$1,0))/INDEX('Data_NSA'!$A:$OK,MATCH($E38,'Data_NSA'!$A:$A,0),MATCH($C38,'Data_NSA'!$1:$1,0))))/(100*(INDEX('Data_NSA'!$A:$OK,MATCH(I$1,'Data_NSA'!$A:$A,0),MATCH("CUUR0000SA0",'Data_NSA'!$1:$1,0))/INDEX('Data_NSA'!$A:$OK,MATCH($E38,'Data_NSA'!$A:$A,0),MATCH("CUUR0000SA0",'Data_NSA'!$1:$1,0)))),"")
A39: SEFD03 | B39: Pork chops | C39: CUUR0000SEFD03 | D39: 0.046 | E39: 45992 | F39: 2024 | G39: =IFERROR(100*($D39*(INDEX('Data_NSA'!$A:$OK,MATCH(G$1,'Data_NSA'!$A:$A,0),MATCH($C39,'Data_NSA'!$1:$1,0))/INDEX('Data_NSA'!$A:$OK,MATCH($E39,'Data_NSA'!$A:$A,0),MATCH($C39,'Data_NSA'!$1:$1,0))))/(100*(INDEX('Data_NSA'!$A:$OK,MATCH(G$1,'Data_NSA'!$A:$A,0),MATCH("CUUR0000SA0",'Data_NSA'!$1:$1,0))/INDEX('Data_NSA'!$A:$OK,MATCH($E39,'Data_NSA'!$A:$A,0),MATCH("CUUR0000SA0",'Data_NSA'!$1:$1,0)))),"") | H39: =IFERROR(100*($D39*(INDEX('Data_NSA'!$A:$OK,MATCH(H$1,'Data_NSA'!$A:$A,0),MATCH($C39,'Data_NSA'!$1:$1,0))/INDEX('Data_NSA'!$A:$OK,MATCH($E39,'Data_NSA'!$A:$A,0),MATCH($C39,'Data_NSA'!$1:$1,0))))/(100*(INDEX('Data_NSA'!$A:$OK,MATCH(H$1,'Data_NSA'!$A:$A,0),MATCH("CUUR0000SA0",'Data_NSA'!$1:$1,0))/INDEX('Data_NSA'!$A:$OK,MATCH($E39,'Data_NSA'!$A:$A,0),MATCH("CUUR0000SA0",'Data_NSA'!$1:$1,0)))),"") | I39: =IFERROR(100*($D39*(INDEX('Data_NSA'!$A:$OK,MATCH(I$1,'Data_NSA'!$A:$A,0),MATCH($C39,'Data_NSA'!$1:$1,0))/INDEX('Data_NSA'!$A:$OK,MATCH($E39,'Data_NSA'!$A:$A,0),MATCH($C39,'Data_NSA'!$1:$1,0))))/(100*(INDEX('Data_NSA'!$A:$OK,MATCH(I$1,'Data_NSA'!$A:$A,0),MATCH("CUUR0000SA0",'Data_NSA'!$1:$1,0))/INDEX('Data_NSA'!$A:$OK,MATCH($E39,'Data_NSA'!$A:$A,0),MATCH("CUUR0000SA0",'Data_NSA'!$1:$1,0)))),"")
A40: SEFD04 | B40: Other pork including roasts, steaks, and ribs | C40: CUUR0000SEFD04 | D40: 0.097 | E40: 45992 | F40: 2024 | G40: =IFERROR(100*($D40*(INDEX('Data_NSA'!$A:$OK,MATCH(G$1,'Data_NSA'!$A:$A,0),MATCH($C40,'Data_NSA'!$1:$1,0))/INDEX('Data_NSA'!$A:$OK,MATCH($E40,'Data_NSA'!$A:$A,0),MATCH($C40,'Data_NSA'!$1:$1,0))))/(100*(INDEX('Data_NSA'!$A:$OK,MATCH(G$1,'Data_NSA'!$A:$A,0),MATCH("CUUR0000SA0",'Data_NSA'!$1:$1,0))/INDEX('Data_NSA'!$A:$OK,MATCH($E40,'Data_NSA'!$A:$A,0),MATCH("CUUR0000SA0",'Data_NSA'!$1:$1,0)))),"") | H40: =IFERROR(100*($D40*(INDEX('Data_NSA'!$A:$OK,MATCH(H$1,'Data_NSA'!$A:$A,0),MATCH($C40,'Data_NSA'!$1:$1,0))/INDEX('Data_NSA'!$A:$OK,MATCH($E40,'Data_NSA'!$A:$A,0),MATCH($C40,'Data_NSA'!$1:$1,0))))/(100*(INDEX('Data_NSA'!$A:$OK,MATCH(H$1,'Data_NSA'!$A:$A,0),MATCH("CUUR0000SA0",'Data_NSA'!$1:$1,0))/INDEX('Data_NSA'!$A:$OK,MATCH($E40,'Data_NSA'!$A:$A,0),MATCH("CUUR0000SA0",'Data_NSA'!$1:$1,0)))),"") | I40: =IFERROR(100*($D40*(INDEX('Data_NSA'!$A:$OK,MATCH(I$1,'Data_NSA'!$A:$A,0),MATCH($C40,'Data_NSA'!$1:$1,0))/INDEX('Data_NSA'!$A:$OK,MATCH($E40,'Data_NSA'!$A:$A,0),MATCH($C40,'Data_NSA'!$1:$1,0))))/(100*(INDEX('Data_NSA'!$A:$OK,MATCH(I$1,'Data_NSA'!$A:$A,0),MATCH("CUUR0000SA0",'Data_NSA'!$1:$1,0))/INDEX('Data_NSA'!$A:$OK,MATCH($E40,'Data_NSA'!$A:$A,0),MATCH("CUUR0000SA0",'Data_NSA'!$1:$1,0)))),"")
A41: SEFE | B41: Other meats | C41: CUUR0000SEFE | D41: 0.207 | E41: 45992 | F41: 2024 | G41: =IFERROR(100*($D41*(INDEX('Data_NSA'!$A:$OK,MATCH(G$1,'Data_NSA'!$A:$A,0),MATCH($C41,'Data_NSA'!$1:$1,0))/INDEX('Data_NSA'!$A:$OK,MATCH($E41,'Data_NSA'!$A:$A,0),MATCH($C41,'Data_NSA'!$1:$1,0))))/(100*(INDEX('Data_NSA'!$A:$OK,MATCH(G$1,'Data_NSA'!$A:$A,0),MATCH("CUUR0000SA0",'Data_NSA'!$1:$1,0))/INDEX('Data_NSA'!$A:$OK,MATCH($E41,'Data_NSA'!$A:$A,0),MATCH("CUUR0000SA0",'Data_NSA'!$1:$1,0)))),"") | H41: =IFERROR(100*($D41*(INDEX('Data_NSA'!$A:$OK,MATCH(H$1,'Data_NSA'!$A:$A,0),MATCH($C41,'Data_NSA'!$1:$1,0))/INDEX('Data_NSA'!$A:$OK,MATCH($E41,'Data_NSA'!$A:$A,0),MATCH($C41,'Data_NSA'!$1:$1,0))))/(100*(INDEX('Data_NSA'!$A:$OK,MATCH(H$1,'Data_NSA'!$A:$A,0),MATCH("CUUR0000SA0",'Data_NSA'!$1:$1,0))/INDEX('Data_NSA'!$A:$OK,MATCH($E41,'Data_NSA'!$A:$A,0),MATCH("CUUR0000SA0",'Data_NSA'!$1:$1,0)))),"") | I41: =IFERROR(100*($D41*(INDEX('Data_NSA'!$A:$OK,MATCH(I$1,'Data_NSA'!$A:$A,0),MATCH($C41,'Data_NSA'!$1:$1,0))/INDEX('Data_NSA'!$A:$OK,MATCH($E41,'Data_NSA'!$A:$A,0),MATCH($C41,'Data_NSA'!$1:$1,0))))/(100*(INDEX('Data_NSA'!$A:$OK,MATCH(I$1,'Data_NSA'!$A:$A,0),MATCH("CUUR0000SA0",'Data_NSA'!$1:$1,0))/INDEX('Data_NSA'!$A:$OK,MATCH($E41,'Data_NSA'!$A:$A,0),MATCH("CUUR0000SA0",'Data_NSA'!$1:$1,0)))),"")
A42: SS05011 | B42: Frankfurters | C42: CUUR0000SS05011 | E42: 45992 | F42: 2024 | G42: =IFERROR(100*($D42*(INDEX('Data_NSA'!$A:$OK,MATCH(G$1,'Data_NSA'!$A:$A,0),MATCH($C42,'Data_NSA'!$1:$1,0))/INDEX('Data_NSA'!$A:$OK,MATCH($E42,'Data_NSA'!$A:$A,0),MATCH($C42,'Data_NSA'!$1:$1,0))))/(100*(INDEX('Data_NSA'!$A:$OK,MATCH(G$1,'Data_NSA'!$A:$A,0),MATCH("CUUR0000SA0",'Data_NSA'!$1:$1,0))/INDEX('Data_NSA'!$A:$OK,MATCH($E42,'Data_NSA'!$A:$A,0),MATCH("CUUR0000SA0",'Data_NSA'!$1:$1,0)))),"") | H42: =IFERROR(100*($D42*(INDEX('Data_NSA'!$A:$OK,MATCH(H$1,'Data_NSA'!$A:$A,0),MATCH($C42,'Data_NSA'!$1:$1,0))/INDEX('Data_NSA'!$A:$OK,MATCH($E42,'Data_NSA'!$A:$A,0),MATCH($C42,'Data_NSA'!$1:$1,0))))/(100*(INDEX('Data_NSA'!$A:$OK,MATCH(H$1,'Data_NSA'!$A:$A,0),MATCH("CUUR0000SA0",'Data_NSA'!$1:$1,0))/INDEX('Data_NSA'!$A:$OK,MATCH($E42,'Data_NSA'!$A:$A,0),MATCH("CUUR0000SA0",'Data_NSA'!$1:$1,0)))),"") | I42: =IFERROR(100*($D42*(INDEX('Data_NSA'!$A:$OK,MATCH(I$1,'Data_NSA'!$A:$A,0),MATCH($C42,'Data_NSA'!$1:$1,0))/INDEX('Data_NSA'!$A:$OK,MATCH($E42,'Data_NSA'!$A:$A,0),MATCH($C42,'Data_NSA'!$1:$1,0))))/(100*(INDEX('Data_NSA'!$A:$OK,MATCH(I$1,'Data_NSA'!$A:$A,0),MATCH("CUUR0000SA0",'Data_NSA'!$1:$1,0))/INDEX('Data_NSA'!$A:$OK,MATCH($E42,'Data_NSA'!$A:$A,0),MATCH("CUUR0000SA0",'Data_NSA'!$1:$1,0)))),"")
A43: SS0501A | B43: Lunchmeats | C43: CUUR0000SS0501A | E43: 45992 | F43: 2024 | G43: =IFERROR(100*($D43*(INDEX('Data_NSA'!$A:$OK,MATCH(G$1,'Data_NSA'!$A:$A,0),MATCH($C43,'Data_NSA'!$1:$1,0))/INDEX('Data_NSA'!$A:$OK,MATCH($E43,'Data_NSA'!$A:$A,0),MATCH($C43,'Data_NSA'!$1:$1,0))))/(100*(INDEX('Data_NSA'!$A:$OK,MATCH(G$1,'Data_NSA'!$A:$A,0),MATCH("CUUR0000SA0",'Data_NSA'!$1:$1,0))/INDEX('Data_NSA'!$A:$OK,MATCH($E43,'Data_NSA'!$A:$A,0),MATCH("CUUR0000SA0",'Data_NSA'!$1:$1,0)))),"") | H43: =IFERROR(100*($D43*(INDEX('Data_NSA'!$A:$OK,MATCH(H$1,'Data_NSA'!$A:$A,0),MATCH($C43,'Data_NSA'!$1:$1,0))/INDEX('Data_NSA'!$A:$OK,MATCH($E43,'Data_NSA'!$A:$A,0),MATCH($C43,'Data_NSA'!$1:$1,0))))/(100*(INDEX('Data_NSA'!$A:$OK,MATCH(H$1,'Data_NSA'!$A:$A,0),MATCH("CUUR0000SA0",'Data_NSA'!$1:$1,0))/INDEX('Data_NSA'!$A:$OK,MATCH($E43,'Data_NSA'!$A:$A,0),MATCH("CUUR0000SA0",'Data_NSA'!$1:$1,0)))),"") | I43: =IFERROR(100*($D43*(INDEX('Data_NSA'!$A:$OK,MATCH(I$1,'Data_NSA'!$A:$A,0),MATCH($C43,'Data_NSA'!$1:$1,0))/INDEX('Data_NSA'!$A:$OK,MATCH($E43,'Data_NSA'!$A:$A,0),MATCH($C43,'Data_NSA'!$1:$1,0))))/(100*(INDEX('Data_NSA'!$A:$OK,MATCH(I$1,'Data_NSA'!$A:$A,0),MATCH("CUUR0000SA0",'Data_NSA'!$1:$1,0))/INDEX('Data_NSA'!$A:$OK,MATCH($E43,'Data_NSA'!$A:$A,0),MATCH("CUUR0000SA0",'Data_NSA'!$1:$1,0)))),"")
A44: SS05014 | B44: Lamb and organ meats | C44: CUUR0000SS05014 | E44: 45992 | F44: 2024 | G44: =IFERROR(100*($D44*(INDEX('Data_NSA'!$A:$OK,MATCH(G$1,'Data_NSA'!$A:$A,0),MATCH($C44,'Data_NSA'!$1:$1,0))/INDEX('Data_NSA'!$A:$OK,MATCH($E44,'Data_NSA'!$A:$A,0),MATCH($C44,'Data_NSA'!$1:$1,0))))/(100*(INDEX('Data_NSA'!$A:$OK,MATCH(G$1,'Data_NSA'!$A:$A,0),MATCH("CUUR0000SA0",'Data_NSA'!$1:$1,0))/INDEX('Data_NSA'!$A:$OK,MATCH($E44,'Data_NSA'!$A:$A,0),MATCH("CUUR0000SA0",'Data_NSA'!$1:$1,0)))),"") | H44: =IFERROR(100*($D44*(INDEX('Data_NSA'!$A:$OK,MATCH(H$1,'Data_NSA'!$A:$A,0),MATCH($C44,'Data_NSA'!$1:$1,0))/INDEX('Data_NSA'!$A:$OK,MATCH($E44,'Data_NSA'!$A:$A,0),MATCH($C44,'Data_NSA'!$1:$1,0))))/(100*(INDEX('Data_NSA'!$A:$OK,MATCH(H$1,'Data_NSA'!$A:$A,0),MATCH("CUUR0000SA0",'Data_NSA'!$1:$1,0))/INDEX('Data_NSA'!$A:$OK,MATCH($E44,'Data_NSA'!$A:$A,0),MATCH("CUUR0000SA0",'Data_NSA'!$1:$1,0)))),"") | I44: =IFERROR(100*($D44*(INDEX('Data_NSA'!$A:$OK,MATCH(I$1,'Data_NSA'!$A:$A,0),MATCH($C44,'Data_NSA'!$1:$1,0))/INDEX('Data_NSA'!$A:$OK,MATCH($E44,'Data_NSA'!$A:$A,0),MATCH($C44,'Data_NSA'!$1:$1,0))))/(100*(INDEX('Data_NSA'!$A:$OK,MATCH(I$1,'Data_NSA'!$A:$A,0),MATCH("CUUR0000SA0",'Data_NSA'!$1:$1,0))/INDEX('Data_NSA'!$A:$OK,MATCH($E44,'Data_NSA'!$A:$A,0),MATCH("CUUR0000SA0",'Data_NSA'!$1:$1,0)))),"")
A45: SS05015 | B45: Lamb and mutton | C45: CUUR0000SS05015 | E45: 45992 | F45: 2024 | G45: =IFERROR(100*($D45*(INDEX('Data_NSA'!$A:$OK,MATCH(G$1,'Data_NSA'!$A:$A,0),MATCH($C45,'Data_NSA'!$1:$1,0))/INDEX('Data_NSA'!$A:$OK,MATCH($E45,'Data_NSA'!$A:$A,0),MATCH($C45,'Data_NSA'!$1:$1,0))))/(100*(INDEX('Data_NSA'!$A:$OK,MATCH(G$1,'Data_NSA'!$A:$A,0),MATCH("CUUR0000SA0",'Data_NSA'!$1:$1,0))/INDEX('Data_NSA'!$A:$OK,MATCH($E45,'Data_NSA'!$A:$A,0),MATCH("CUUR0000SA0",'Data_NSA'!$1:$1,0)))),"") | H45: =IFERROR(100*($D45*(INDEX('Data_NSA'!$A:$OK,MATCH(H$1,'Data_NSA'!$A:$A,0),MATCH($C45,'Data_NSA'!$1:$1,0))/INDEX('Data_NSA'!$A:$OK,MATCH($E45,'Data_NSA'!$A:$A,0),MATCH($C45,'Data_NSA'!$1:$1,0))))/(100*(INDEX('Data_NSA'!$A:$OK,MATCH(H$1,'Data_NSA'!$A:$A,0),MATCH("CUUR0000SA0",'Data_NSA'!$1:$1,0))/INDEX('Data_NSA'!$A:$OK,MATCH($E45,'Data_NSA'!$A:$A,0),MATCH("CUUR0000SA0",'Data_NSA'!$1:$1,0)))),"") | I45: =IFERROR(100*($D45*(INDEX('Data_NSA'!$A:$OK,MATCH(I$1,'Data_NSA'!$A:$A,0),MATCH($C45,'Data_NSA'!$1:$1,0))/INDEX('Data_NSA'!$A:$OK,MATCH($E45,'Data_NSA'!$A:$A,0),MATCH($C45,'Data_NSA'!$1:$1,0))))/(100*(INDEX('Data_NSA'!$A:$OK,MATCH(I$1,'Data_NSA'!$A:$A,0),MATCH("CUUR0000SA0",'Data_NSA'!$1:$1,0))/INDEX('Data_NSA'!$A:$OK,MATCH($E45,'Data_NSA'!$A:$A,0),MATCH("CUUR0000SA0",'Data_NSA'!$1:$1,0)))),"")
A46: SEFF | B46: Poultry | C46: CUUR0000SEFF | D46: 0.363 | E46: 45992 | F46: 2024 | G46: =IFERROR(100*($D46*(INDEX('Data_NSA'!$A:$OK,MATCH(G$1,'Data_NSA'!$A:$A,0),MATCH($C46,'Data_NSA'!$1:$1,0))/INDEX('Data_NSA'!$A:$OK,MATCH($E46,'Data_NSA'!$A:$A,0),MATCH($C46,'Data_NSA'!$1:$1,0))))/(100*(INDEX('Data_NSA'!$A:$OK,MATCH(G$1,'Data_NSA'!$A:$A,0),MATCH("CUUR0000SA0",'Data_NSA'!$1:$1,0))/INDEX('Data_NSA'!$A:$OK,MATCH($E46,'Data_NSA'!$A:$A,0),MATCH("CUUR0000SA0",'Data_NSA'!$1:$1,0)))),"") | H46: =IFERROR(100*($D46*(INDEX('Data_NSA'!$A:$OK,MATCH(H$1,'Data_NSA'!$A:$A,0),MATCH($C46,'Data_NSA'!$1:$1,0))/INDEX('Data_NSA'!$A:$OK,MATCH($E46,'Data_NSA'!$A:$A,0),MATCH($C46,'Data_NSA'!$1:$1,0))))/(100*(INDEX('Data_NSA'!$A:$OK,MATCH(H$1,'Data_NSA'!$A:$A,0),MATCH("CUUR0000SA0",'Data_NSA'!$1:$1,0))/INDEX('Data_NSA'!$A:$OK,MATCH($E46,'Data_NSA'!$A:$A,0),MATCH("CUUR0000SA0",'Data_NSA'!$1:$1,0)))),"") | I46: =IFERROR(100*($D46*(INDEX('Data_NSA'!$A:$OK,MATCH(I$1,'Data_NSA'!$A:$A,0),MATCH($C46,'Data_NSA'!$1:$1,0))/INDEX('Data_NSA'!$A:$OK,MATCH($E46,'Data_NSA'!$A:$A,0),MATCH($C46,'Data_NSA'!$1:$1,0))))/(100*(INDEX('Data_NSA'!$A:$OK,MATCH(I$1,'Data_NSA'!$A:$A,0),MATCH("CUUR0000SA0",'Data_NSA'!$1:$1,0))/INDEX('Data_NSA'!$A:$OK,MATCH($E46,'Data_NSA'!$A:$A,0),MATCH("CUUR0000SA0",'Data_NSA'!$1:$1,0)))),"")
A47: SEFF01 | B47: Chicken | C47: CUUR0000SEFF01 | D47: 0.291 | E47: 45992 | F47: 2024 | G47: =IFERROR(100*($D47*(INDEX('Data_NSA'!$A:$OK,MATCH(G$1,'Data_NSA'!$A:$A,0),MATCH($C47,'Data_NSA'!$1:$1,0))/INDEX('Data_NSA'!$A:$OK,MATCH($E47,'Data_NSA'!$A:$A,0),MATCH($C47,'Data_NSA'!$1:$1,0))))/(100*(INDEX('Data_NSA'!$A:$OK,MATCH(G$1,'Data_NSA'!$A:$A,0),MATCH("CUUR0000SA0",'Data_NSA'!$1:$1,0))/INDEX('Data_NSA'!$A:$OK,MATCH($E47,'Data_NSA'!$A:$A,0),MATCH("CUUR0000SA0",'Data_NSA'!$1:$1,0)))),"") | H47: =IFERROR(100*($D47*(INDEX('Data_NSA'!$A:$OK,MATCH(H$1,'Data_NSA'!$A:$A,0),MATCH($C47,'Data_NSA'!$1:$1,0))/INDEX('Data_NSA'!$A:$OK,MATCH($E47,'Data_NSA'!$A:$A,0),MATCH($C47,'Data_NSA'!$1:$1,0))))/(100*(INDEX('Data_NSA'!$A:$OK,MATCH(H$1,'Data_NSA'!$A:$A,0),MATCH("CUUR0000SA0",'Data_NSA'!$1:$1,0))/INDEX('Data_NSA'!$A:$OK,MATCH($E47,'Data_NSA'!$A:$A,0),MATCH("CUUR0000SA0",'Data_NSA'!$1:$1,0)))),"") | I47: =IFERROR(100*($D47*(INDEX('Data_NSA'!$A:$OK,MATCH(I$1,'Data_NSA'!$A:$A,0),MATCH($C47,'Data_NSA'!$1:$1,0))/INDEX('Data_NSA'!$A:$OK,MATCH($E47,'Data_NSA'!$A:$A,0),MATCH($C47,'Data_NSA'!$1:$1,0))))/(100*(INDEX('Data_NSA'!$A:$OK,MATCH(I$1,'Data_NSA'!$A:$A,0),MATCH("CUUR0000SA0",'Data_NSA'!$1:$1,0))/INDEX('Data_NSA'!$A:$OK,MATCH($E47,'Data_NSA'!$A:$A,0),MATCH("CUUR0000SA0",'Data_NSA'!$1:$1,0)))),"")
A48: SS06011 | B48: Fresh whole chicken | C48: CUUR0000SS06011 | E48: 45992 | F48: 2024 | G48: =IFERROR(100*($D48*(INDEX('Data_NSA'!$A:$OK,MATCH(G$1,'Data_NSA'!$A:$A,0),MATCH($C48,'Data_NSA'!$1:$1,0))/INDEX('Data_NSA'!$A:$OK,MATCH($E48,'Data_NSA'!$A:$A,0),MATCH($C48,'Data_NSA'!$1:$1,0))))/(100*(INDEX('Data_NSA'!$A:$OK,MATCH(G$1,'Data_NSA'!$A:$A,0),MATCH("CUUR0000SA0",'Data_NSA'!$1:$1,0))/INDEX('Data_NSA'!$A:$OK,MATCH($E48,'Data_NSA'!$A:$A,0),MATCH("CUUR0000SA0",'Data_NSA'!$1:$1,0)))),"") | H48: =IFERROR(100*($D48*(INDEX('Data_NSA'!$A:$OK,MATCH(H$1,'Data_NSA'!$A:$A,0),MATCH($C48,'Data_NSA'!$1:$1,0))/INDEX('Data_NSA'!$A:$OK,MATCH($E48,'Data_NSA'!$A:$A,0),MATCH($C48,'Data_NSA'!$1:$1,0))))/(100*(INDEX('Data_NSA'!$A:$OK,MATCH(H$1,'Data_NSA'!$A:$A,0),MATCH("CUUR0000SA0",'Data_NSA'!$1:$1,0))/INDEX('Data_NSA'!$A:$OK,MATCH($E48,'Data_NSA'!$A:$A,0),MATCH("CUUR0000SA0",'Data_NSA'!$1:$1,0)))),"") | I48: =IFERROR(100*($D48*(INDEX('Data_NSA'!$A:$OK,MATCH(I$1,'Data_NSA'!$A:$A,0),MATCH($C48,'Data_NSA'!$1:$1,0))/INDEX('Data_NSA'!$A:$OK,MATCH($E48,'Data_NSA'!$A:$A,0),MATCH($C48,'Data_NSA'!$1:$1,0))))/(100*(INDEX('Data_NSA'!$A:$OK,MATCH(I$1,'Data_NSA'!$A:$A,0),MATCH("CUUR0000SA0",'Data_NSA'!$1:$1,0))/INDEX('Data_NSA'!$A:$OK,MATCH($E48,'Data_NSA'!$A:$A,0),MATCH("CUUR0000SA0",'Data_NSA'!$1:$1,0)))),"")
A49: SS06021 | B49: Fresh and frozen chicken parts | C49: CUUR0000SS06021 | E49: 45992 | F49: 2024 | G49: =IFERROR(100*($D49*(INDEX('Data_NSA'!$A:$OK,MATCH(G$1,'Data_NSA'!$A:$A,0),MATCH($C49,'Data_NSA'!$1:$1,0))/INDEX('Data_NSA'!$A:$OK,MATCH($E49,'Data_NSA'!$A:$A,0),MATCH($C49,'Data_NSA'!$1:$1,0))))/(100*(INDEX('Data_NSA'!$A:$OK,MATCH(G$1,'Data_NSA'!$A:$A,0),MATCH("CUUR0000SA0",'Data_NSA'!$1:$1,0))/INDEX('Data_NSA'!$A:$OK,MATCH($E49,'Data_NSA'!$A:$A,0),MATCH("CUUR0000SA0",'Data_NSA'!$1:$1,0)))),"") | H49: =IFERROR(100*($D49*(INDEX('Data_NSA'!$A:$OK,MATCH(H$1,'Data_NSA'!$A:$A,0),MATCH($C49,'Data_NSA'!$1:$1,0))/INDEX('Data_NSA'!$A:$OK,MATCH($E49,'Data_NSA'!$A:$A,0),MATCH($C49,'Data_NSA'!$1:$1,0))))/(100*(INDEX('Data_NSA'!$A:$OK,MATCH(H$1,'Data_NSA'!$A:$A,0),MATCH("CUUR0000SA0",'Data_NSA'!$1:$1,0))/INDEX('Data_NSA'!$A:$OK,MATCH($E49,'Data_NSA'!$A:$A,0),MATCH("CUUR0000SA0",'Data_NSA'!$1:$1,0)))),"") | I49: =IFERROR(100*($D49*(INDEX('Data_NSA'!$A:$OK,MATCH(I$1,'Data_NSA'!$A:$A,0),MATCH($C49,'Data_NSA'!$1:$1,0))/INDEX('Data_NSA'!$A:$OK,MATCH($E49,'Data_NSA'!$A:$A,0),MATCH($C49,'Data_NSA'!$1:$1,0))))/(100*(INDEX('Data_NSA'!$A:$OK,MATCH(I$1,'Data_NSA'!$A:$A,0),MATCH("CUUR0000SA0",'Data_NSA'!$1:$1,0))/INDEX('Data_NSA'!$A:$OK,MATCH($E49,'Data_NSA'!$A:$A,0),MATCH("CUUR0000SA0",'Data_NSA'!$1:$1,0)))),"")
A50: SEFF02 | B50: Other uncooked poultry including turkey | C50: CUUR0000SEFF02 | D50: 0.072 | E50: 45992 | F50: 2024 | G50: =IFERROR(100*($D50*(INDEX('Data_NSA'!$A:$OK,MATCH(G$1,'Data_NSA'!$A:$A,0),MATCH($C50,'Data_NSA'!$1:$1,0))/INDEX('Data_NSA'!$A:$OK,MATCH($E50,'Data_NSA'!$A:$A,0),MATCH($C50,'Data_NSA'!$1:$1,0))))/(100*(INDEX('Data_NSA'!$A:$OK,MATCH(G$1,'Data_NSA'!$A:$A,0),MATCH("CUUR0000SA0",'Data_NSA'!$1:$1,0))/INDEX('Data_NSA'!$A:$OK,MATCH($E50,'Data_NSA'!$A:$A,0),MATCH("CUUR0000SA0",'Data_NSA'!$1:$1,0)))),"") | H50: =IFERROR(100*($D50*(INDEX('Data_NSA'!$A:$OK,MATCH(H$1,'Data_NSA'!$A:$A,0),MATCH($C50,'Data_NSA'!$1:$1,0))/INDEX('Data_NSA'!$A:$OK,MATCH($E50,'Data_NSA'!$A:$A,0),MATCH($C50,'Data_NSA'!$1:$1,0))))/(100*(INDEX('Data_NSA'!$A:$OK,MATCH(H$1,'Data_NSA'!$A:$A,0),MATCH("CUUR0000SA0",'Data_NSA'!$1:$1,0))/INDEX('Data_NSA'!$A:$OK,MATCH($E50,'Data_NSA'!$A:$A,0),MATCH("CUUR0000SA0",'Data_NSA'!$1:$1,0)))),"") | I50: =IFERROR(100*($D50*(INDEX('Data_NSA'!$A:$OK,MATCH(I$1,'Data_NSA'!$A:$A,0),MATCH($C50,'Data_NSA'!$1:$1,0))/INDEX('Data_NSA'!$A:$OK,MATCH($E50,'Data_NSA'!$A:$A,0),MATCH($C50,'Data_NSA'!$1:$1,0))))/(100*(INDEX('Data_NSA'!$A:$OK,MATCH(I$1,'Data_NSA'!$A:$A,0),MATCH("CUUR0000SA0",'Data_NSA'!$1:$1,0))/INDEX('Data_NSA'!$A:$OK,MATCH($E50,'Data_NSA'!$A:$A,0),MATCH("CUUR0000SA0",'Data_NSA'!$1:$1,0)))),"")
A51: SEFG | B51: Fish and seafood | C51: CUUR0000SEFG | D51: 0.314 | E51: 45992 | F51: 2024 | G51: =IFERROR(100*($D51*(INDEX('Data_NSA'!$A:$OK,MATCH(G$1,'Data_NSA'!$A:$A,0),MATCH($C51,'Data_NSA'!$1:$1,0))/INDEX('Data_NSA'!$A:$OK,MATCH($E51,'Data_NSA'!$A:$A,0),MATCH($C51,'Data_NSA'!$1:$1,0))))/(100*(INDEX('Data_NSA'!$A:$OK,MATCH(G$1,'Data_NSA'!$A:$A,0),MATCH("CUUR0000SA0",'Data_NSA'!$1:$1,0))/INDEX('Data_NSA'!$A:$OK,MATCH($E51,'Data_NSA'!$A:$A,0),MATCH("CUUR0000SA0",'Data_NSA'!$1:$1,0)))),"") | H51: =IFERROR(100*($D51*(INDEX('Data_NSA'!$A:$OK,MATCH(H$1,'Data_NSA'!$A:$A,0),MATCH($C51,'Data_NSA'!$1:$1,0))/INDEX('Data_NSA'!$A:$OK,MATCH($E51,'Data_NSA'!$A:$A,0),MATCH($C51,'Data_NSA'!$1:$1,0))))/(100*(INDEX('Data_NSA'!$A:$OK,MATCH(H$1,'Data_NSA'!$A:$A,0),MATCH("CUUR0000SA0",'Data_NSA'!$1:$1,0))/INDEX('Data_NSA'!$A:$OK,MATCH($E51,'Data_NSA'!$A:$A,0),MATCH("CUUR0000SA0",'Data_NSA'!$1:$1,0)))),"") | I51: =IFERROR(100*($D51*(INDEX('Data_NSA'!$A:$OK,MATCH(I$1,'Data_NSA'!$A:$A,0),MATCH($C51,'Data_NSA'!$1:$1,0))/INDEX('Data_NSA'!$A:$OK,MATCH($E51,'Data_NSA'!$A:$A,0),MATCH($C51,'Data_NSA'!$1:$1,0))))/(100*(INDEX('Data_NSA'!$A:$OK,MATCH(I$1,'Data_NSA'!$A:$A,0),MATCH("CUUR0000SA0",'Data_NSA'!$1:$1,0))/INDEX('Data_NSA'!$A:$OK,MATCH($E51,'Data_NSA'!$A:$A,0),MATCH("CUUR0000SA0",'Data_NSA'!$1:$1,0)))),"")
A52: SEFG01 | B52: Fresh fish and seafood | C52: CUUR0000SEFG01 | D52: 0.165 | E52: 45992 | F52: 2024 | G52: =IFERROR(100*($D52*(INDEX('Data_NSA'!$A:$OK,MATCH(G$1,'Data_NSA'!$A:$A,0),MATCH($C52,'Data_NSA'!$1:$1,0))/INDEX('Data_NSA'!$A:$OK,MATCH($E52,'Data_NSA'!$A:$A,0),MATCH($C52,'Data_NSA'!$1:$1,0))))/(100*(INDEX('Data_NSA'!$A:$OK,MATCH(G$1,'Data_NSA'!$A:$A,0),MATCH("CUUR0000SA0",'Data_NSA'!$1:$1,0))/INDEX('Data_NSA'!$A:$OK,MATCH($E52,'Data_NSA'!$A:$A,0),MATCH("CUUR0000SA0",'Data_NSA'!$1:$1,0)))),"") | H52: =IFERROR(100*($D52*(INDEX('Data_NSA'!$A:$OK,MATCH(H$1,'Data_NSA'!$A:$A,0),MATCH($C52,'Data_NSA'!$1:$1,0))/INDEX('Data_NSA'!$A:$OK,MATCH($E52,'Data_NSA'!$A:$A,0),MATCH($C52,'Data_NSA'!$1:$1,0))))/(100*(INDEX('Data_NSA'!$A:$OK,MATCH(H$1,'Data_NSA'!$A:$A,0),MATCH("CUUR0000SA0",'Data_NSA'!$1:$1,0))/INDEX('Data_NSA'!$A:$OK,MATCH($E52,'Data_NSA'!$A:$A,0),MATCH("CUUR0000SA0",'Data_NSA'!$1:$1,0)))),"") | I52: =IFERROR(100*($D52*(INDEX('Data_NSA'!$A:$OK,MATCH(I$1,'Data_NSA'!$A:$A,0),MATCH($C52,'Data_NSA'!$1:$1,0))/INDEX('Data_NSA'!$A:$OK,MATCH($E52,'Data_NSA'!$A:$A,0),MATCH($C52,'Data_NSA'!$1:$1,0))))/(100*(INDEX('Data_NSA'!$A:$OK,MATCH(I$1,'Data_NSA'!$A:$A,0),MATCH("CUUR0000SA0",'Data_NSA'!$1:$1,0))/INDEX('Data_NSA'!$A:$OK,MATCH($E52,'Data_NSA'!$A:$A,0),MATCH("CUUR0000SA0",'Data_NSA'!$1:$1,0)))),"")
A53: SEFG02 | B53: Processed fish and seafood | C53: CUUR0000SEFG02 | D53: 0.149 | E53: 45992 | F53: 2024 | G53: =IFERROR(100*($D53*(INDEX('Data_NSA'!$A:$OK,MATCH(G$1,'Data_NSA'!$A:$A,0),MATCH($C53,'Data_NSA'!$1:$1,0))/INDEX('Data_NSA'!$A:$OK,MATCH($E53,'Data_NSA'!$A:$A,0),MATCH($C53,'Data_NSA'!$1:$1,0))))/(100*(INDEX('Data_NSA'!$A:$OK,MATCH(G$1,'Data_NSA'!$A:$A,0),MATCH("CUUR0000SA0",'Data_NSA'!$1:$1,0))/INDEX('Data_NSA'!$A:$OK,MATCH($E53,'Data_NSA'!$A:$A,0),MATCH("CUUR0000SA0",'Data_NSA'!$1:$1,0)))),"") | H53: =IFERROR(100*($D53*(INDEX('Data_NSA'!$A:$OK,MATCH(H$1,'Data_NSA'!$A:$A,0),MATCH($C53,'Data_NSA'!$1:$1,0))/INDEX('Data_NSA'!$A:$OK,MATCH($E53,'Data_NSA'!$A:$A,0),MATCH($C53,'Data_NSA'!$1:$1,0))))/(100*(INDEX('Data_NSA'!$A:$OK,MATCH(H$1,'Data_NSA'!$A:$A,0),MATCH("CUUR0000SA0",'Data_NSA'!$1:$1,0))/INDEX('Data_NSA'!$A:$OK,MATCH($E53,'Data_NSA'!$A:$A,0),MATCH("CUUR0000SA0",'Data_NSA'!$1:$1,0)))),"") | I53: =IFERROR(100*($D53*(INDEX('Data_NSA'!$A:$OK,MATCH(I$1,'Data_NSA'!$A:$A,0),MATCH($C53,'Data_NSA'!$1:$1,0))/INDEX('Data_NSA'!$A:$OK,MATCH($E53,'Data_NSA'!$A:$A,0),MATCH($C53,'Data_NSA'!$1:$1,0))))/(100*(INDEX('Data_NSA'!$A:$OK,MATCH(I$1,'Data_NSA'!$A:$A,0),MATCH("CUUR0000SA0",'Data_NSA'!$1:$1,0))/INDEX('Data_NSA'!$A:$OK,MATCH($E53,'Data_NSA'!$A:$A,0),MATCH("CUUR0000SA0",'Data_NSA'!$1:$1,0)))),"")
A54: SS07011 | B54: Shelf stable fish and seafood | C54: CUUR0000SS07011 | E54: 45992 | F54: 2024 | G54: =IFERROR(100*($D54*(INDEX('Data_NSA'!$A:$OK,MATCH(G$1,'Data_NSA'!$A:$A,0),MATCH($C54,'Data_NSA'!$1:$1,0))/INDEX('Data_NSA'!$A:$OK,MATCH($E54,'Data_NSA'!$A:$A,0),MATCH($C54,'Data_NSA'!$1:$1,0))))/(100*(INDEX('Data_NSA'!$A:$OK,MATCH(G$1,'Data_NSA'!$A:$A,0),MATCH("CUUR0000SA0",'Data_NSA'!$1:$1,0))/INDEX('Data_NSA'!$A:$OK,MATCH($E54,'Data_NSA'!$A:$A,0),MATCH("CUUR0000SA0",'Data_NSA'!$1:$1,0)))),"") | H54: =IFERROR(100*($D54*(INDEX('Data_NSA'!$A:$OK,MATCH(H$1,'Data_NSA'!$A:$A,0),MATCH($C54,'Data_NSA'!$1:$1,0))/INDEX('Data_NSA'!$A:$OK,MATCH($E54,'Data_NSA'!$A:$A,0),MATCH($C54,'Data_NSA'!$1:$1,0))))/(100*(INDEX('Data_NSA'!$A:$OK,MATCH(H$1,'Data_NSA'!$A:$A,0),MATCH("CUUR0000SA0",'Data_NSA'!$1:$1,0))/INDEX('Data_NSA'!$A:$OK,MATCH($E54,'Data_NSA'!$A:$A,0),MATCH("CUUR0000SA0",'Data_NSA'!$1:$1,0)))),"") | I54: =IFERROR(100*($D54*(INDEX('Data_NSA'!$A:$OK,MATCH(I$1,'Data_NSA'!$A:$A,0),MATCH($C54,'Data_NSA'!$1:$1,0))/INDEX('Data_NSA'!$A:$OK,MATCH($E54,'Data_NSA'!$A:$A,0),MATCH($C54,'Data_NSA'!$1:$1,0))))/(100*(INDEX('Data_NSA'!$A:$OK,MATCH(I$1,'Data_NSA'!$A:$A,0),MATCH("CUUR0000SA0",'Data_NSA'!$1:$1,0))/INDEX('Data_NSA'!$A:$OK,MATCH($E54,'Data_NSA'!$A:$A,0),MATCH("CUUR0000SA0",'Data_NSA'!$1:$1,0)))),"")
A55: SS07021 | B55: Frozen fish and seafood | C55: CUUR0000SS07021 | E55: 45992 | F55: 2024 | G55: =IFERROR(100*($D55*(INDEX('Data_NSA'!$A:$OK,MATCH(G$1,'Data_NSA'!$A:$A,0),MATCH($C55,'Data_NSA'!$1:$1,0))/INDEX('Data_NSA'!$A:$OK,MATCH($E55,'Data_NSA'!$A:$A,0),MATCH($C55,'Data_NSA'!$1:$1,0))))/(100*(INDEX('Data_NSA'!$A:$OK,MATCH(G$1,'Data_NSA'!$A:$A,0),MATCH("CUUR0000SA0",'Data_NSA'!$1:$1,0))/INDEX('Data_NSA'!$A:$OK,MATCH($E55,'Data_NSA'!$A:$A,0),MATCH("CUUR0000SA0",'Data_NSA'!$1:$1,0)))),"") | H55: =IFERROR(100*($D55*(INDEX('Data_NSA'!$A:$OK,MATCH(H$1,'Data_NSA'!$A:$A,0),MATCH($C55,'Data_NSA'!$1:$1,0))/INDEX('Data_NSA'!$A:$OK,MATCH($E55,'Data_NSA'!$A:$A,0),MATCH($C55,'Data_NSA'!$1:$1,0))))/(100*(INDEX('Data_NSA'!$A:$OK,MATCH(H$1,'Data_NSA'!$A:$A,0),MATCH("CUUR0000SA0",'Data_NSA'!$1:$1,0))/INDEX('Data_NSA'!$A:$OK,MATCH($E55,'Data_NSA'!$A:$A,0),MATCH("CUUR0000SA0",'Data_NSA'!$1:$1,0)))),"") | I55: =IFERROR(100*($D55*(INDEX('Data_NSA'!$A:$OK,MATCH(I$1,'Data_NSA'!$A:$A,0),MATCH($C55,'Data_NSA'!$1:$1,0))/INDEX('Data_NSA'!$A:$OK,MATCH($E55,'Data_NSA'!$A:$A,0),MATCH($C55,'Data_NSA'!$1:$1,0))))/(100*(INDEX('Data_NSA'!$A:$OK,MATCH(I$1,'Data_NSA'!$A:$A,0),MATCH("CUUR0000SA0",'Data_NSA'!$1:$1,0))/INDEX('Data_NSA'!$A:$OK,MATCH($E55,'Data_NSA'!$A:$A,0),MATCH("CUUR0000SA0",'Data_NSA'!$1:$1,0)))),"")
A56: SEFH | B56: Eggs | C56: CUUR0000SEFH | D56: 0.133 | E56: 45992 | F56: 2024 | G56: =IFERROR(100*($D56*(INDEX('Data_NSA'!$A:$OK,MATCH(G$1,'Data_NSA'!$A:$A,0),MATCH($C56,'Data_NSA'!$1:$1,0))/INDEX('Data_NSA'!$A:$OK,MATCH($E56,'Data_NSA'!$A:$A,0),MATCH($C56,'Data_NSA'!$1:$1,0))))/(100*(INDEX('Data_NSA'!$A:$OK,MATCH(G$1,'Data_NSA'!$A:$A,0),MATCH("CUUR0000SA0",'Data_NSA'!$1:$1,0))/INDEX('Data_NSA'!$A:$OK,MATCH($E56,'Data_NSA'!$A:$A,0),MATCH("CUUR0000SA0",'Data_NSA'!$1:$1,0)))),"") | H56: =IFERROR(100*($D56*(INDEX('Data_NSA'!$A:$OK,MATCH(H$1,'Data_NSA'!$A:$A,0),MATCH($C56,'Data_NSA'!$1:$1,0))/INDEX('Data_NSA'!$A:$OK,MATCH($E56,'Data_NSA'!$A:$A,0),MATCH($C56,'Data_NSA'!$1:$1,0))))/(100*(INDEX('Data_NSA'!$A:$OK,MATCH(H$1,'Data_NSA'!$A:$A,0),MATCH("CUUR0000SA0",'Data_NSA'!$1:$1,0))/INDEX('Data_NSA'!$A:$OK,MATCH($E56,'Data_NSA'!$A:$A,0),MATCH("CUUR0000SA0",'Data_NSA'!$1:$1,0)))),"") | I56: =IFERROR(100*($D56*(INDEX('Data_NSA'!$A:$OK,MATCH(I$1,'Data_NSA'!$A:$A,0),MATCH($C56,'Data_NSA'!$1:$1,0))/INDEX('Data_NSA'!$A:$OK,MATCH($E56,'Data_NSA'!$A:$A,0),MATCH($C56,'Data_NSA'!$1:$1,0))))/(100*(INDEX('Data_NSA'!$A:$OK,MATCH(I$1,'Data_NSA'!$A:$A,0),MATCH("CUUR0000SA0",'Data_NSA'!$1:$1,0))/INDEX('Data_NSA'!$A:$OK,MATCH($E56,'Data_NSA'!$A:$A,0),MATCH("CUUR0000SA0",'Data_NSA'!$1:$1,0)))),"")
A57: SEFJ | B57: Dairy and related products | C57: CUUR0000SEFJ | D57: 0.758 | E57: 45992 | F57: 2024 | G57: =IFERROR(100*($D57*(INDEX('Data_NSA'!$A:$OK,MATCH(G$1,'Data_NSA'!$A:$A,0),MATCH($C57,'Data_NSA'!$1:$1,0))/INDEX('Data_NSA'!$A:$OK,MATCH($E57,'Data_NSA'!$A:$A,0),MATCH($C57,'Data_NSA'!$1:$1,0))))/(100*(INDEX('Data_NSA'!$A:$OK,MATCH(G$1,'Data_NSA'!$A:$A,0),MATCH("CUUR0000SA0",'Data_NSA'!$1:$1,0))/INDEX('Data_NSA'!$A:$OK,MATCH($E57,'Data_NSA'!$A:$A,0),MATCH("CUUR0000SA0",'Data_NSA'!$1:$1,0)))),"") | H57: =IFERROR(100*($D57*(INDEX('Data_NSA'!$A:$OK,MATCH(H$1,'Data_NSA'!$A:$A,0),MATCH($C57,'Data_NSA'!$1:$1,0))/INDEX('Data_NSA'!$A:$OK,MATCH($E57,'Data_NSA'!$A:$A,0),MATCH($C57,'Data_NSA'!$1:$1,0))))/(100*(INDEX('Data_NSA'!$A:$OK,MATCH(H$1,'Data_NSA'!$A:$A,0),MATCH("CUUR0000SA0",'Data_NSA'!$1:$1,0))/INDEX('Data_NSA'!$A:$OK,MATCH($E57,'Data_NSA'!$A:$A,0),MATCH("CUUR0000SA0",'Data_NSA'!$1:$1,0)))),"") | I57: =IFERROR(100*($D57*(INDEX('Data_NSA'!$A:$OK,MATCH(I$1,'Data_NSA'!$A:$A,0),MATCH($C57,'Data_NSA'!$1:$1,0))/INDEX('Data_NSA'!$A:$OK,MATCH($E57,'Data_NSA'!$A:$A,0),MATCH($C57,'Data_NSA'!$1:$1,0))))/(100*(INDEX('Data_NSA'!$A:$OK,MATCH(I$1,'Data_NSA'!$A:$A,0),MATCH("CUUR0000SA0",'Data_NSA'!$1:$1,0))/INDEX('Data_NSA'!$A:$OK,MATCH($E57,'Data_NSA'!$A:$A,0),MATCH("CUUR0000SA0",'Data_NSA'!$1:$1,0)))),"")
A58: SEFJ01 | B58: Milk | C58: CUUR0000SEFJ01 | D58: 0.19 | E58: 45992 | F58: 2024 | G58: =IFERROR(100*($D58*(INDEX('Data_NSA'!$A:$OK,MATCH(G$1,'Data_NSA'!$A:$A,0),MATCH($C58,'Data_NSA'!$1:$1,0))/INDEX('Data_NSA'!$A:$OK,MATCH($E58,'Data_NSA'!$A:$A,0),MATCH($C58,'Data_NSA'!$1:$1,0))))/(100*(INDEX('Data_NSA'!$A:$OK,MATCH(G$1,'Data_NSA'!$A:$A,0),MATCH("CUUR0000SA0",'Data_NSA'!$1:$1,0))/INDEX('Data_NSA'!$A:$OK,MATCH($E58,'Data_NSA'!$A:$A,0),MATCH("CUUR0000SA0",'Data_NSA'!$1:$1,0)))),"") | H58: =IFERROR(100*($D58*(INDEX('Data_NSA'!$A:$OK,MATCH(H$1,'Data_NSA'!$A:$A,0),MATCH($C58,'Data_NSA'!$1:$1,0))/INDEX('Data_NSA'!$A:$OK,MATCH($E58,'Data_NSA'!$A:$A,0),MATCH($C58,'Data_NSA'!$1:$1,0))))/(100*(INDEX('Data_NSA'!$A:$OK,MATCH(H$1,'Data_NSA'!$A:$A,0),MATCH("CUUR0000SA0",'Data_NSA'!$1:$1,0))/INDEX('Data_NSA'!$A:$OK,MATCH($E58,'Data_NSA'!$A:$A,0),MATCH("CUUR0000SA0",'Data_NSA'!$1:$1,0)))),"") | I58: =IFERROR(100*($D58*(INDEX('Data_NSA'!$A:$OK,MATCH(I$1,'Data_NSA'!$A:$A,0),MATCH($C58,'Data_NSA'!$1:$1,0))/INDEX('Data_NSA'!$A:$OK,MATCH($E58,'Data_NSA'!$A:$A,0),MATCH($C58,'Data_NSA'!$1:$1,0))))/(100*(INDEX('Data_NSA'!$A:$OK,MATCH(I$1,'Data_NSA'!$A:$A,0),MATCH("CUUR0000SA0",'Data_NSA'!$1:$1,0))/INDEX('Data_NSA'!$A:$OK,MATCH($E58,'Data_NSA'!$A:$A,0),MATCH("CUUR0000SA0",'Data_NSA'!$1:$1,0)))),"")
A59: SS09011 | B59: Fresh whole milk | C59: CUUR0000SS09011 | E59: 45992 | F59: 2024 | G59: =IFERROR(100*($D59*(INDEX('Data_NSA'!$A:$OK,MATCH(G$1,'Data_NSA'!$A:$A,0),MATCH($C59,'Data_NSA'!$1:$1,0))/INDEX('Data_NSA'!$A:$OK,MATCH($E59,'Data_NSA'!$A:$A,0),MATCH($C59,'Data_NSA'!$1:$1,0))))/(100*(INDEX('Data_NSA'!$A:$OK,MATCH(G$1,'Data_NSA'!$A:$A,0),MATCH("CUUR0000SA0",'Data_NSA'!$1:$1,0))/INDEX('Data_NSA'!$A:$OK,MATCH($E59,'Data_NSA'!$A:$A,0),MATCH("CUUR0000SA0",'Data_NSA'!$1:$1,0)))),"") | H59: =IFERROR(100*($D59*(INDEX('Data_NSA'!$A:$OK,MATCH(H$1,'Data_NSA'!$A:$A,0),MATCH($C59,'Data_NSA'!$1:$1,0))/INDEX('Data_NSA'!$A:$OK,MATCH($E59,'Data_NSA'!$A:$A,0),MATCH($C59,'Data_NSA'!$1:$1,0))))/(100*(INDEX('Data_NSA'!$A:$OK,MATCH(H$1,'Data_NSA'!$A:$A,0),MATCH("CUUR0000SA0",'Data_NSA'!$1:$1,0))/INDEX('Data_NSA'!$A:$OK,MATCH($E59,'Data_NSA'!$A:$A,0),MATCH("CUUR0000SA0",'Data_NSA'!$1:$1,0)))),"") | I59: =IFERROR(100*($D59*(INDEX('Data_NSA'!$A:$OK,MATCH(I$1,'Data_NSA'!$A:$A,0),MATCH($C59,'Data_NSA'!$1:$1,0))/INDEX('Data_NSA'!$A:$OK,MATCH($E59,'Data_NSA'!$A:$A,0),MATCH($C59,'Data_NSA'!$1:$1,0))))/(100*(INDEX('Data_NSA'!$A:$OK,MATCH(I$1,'Data_NSA'!$A:$A,0),MATCH("CUUR0000SA0",'Data_NSA'!$1:$1,0))/INDEX('Data_NSA'!$A:$OK,MATCH($E59,'Data_NSA'!$A:$A,0),MATCH("CUUR0000SA0",'Data_NSA'!$1:$1,0)))),"")
A60: SS09021 | B60: Fresh milk other than whole | C60: CUUR0000SS09021 | E60: 45992 | F60: 2024 | G60: =IFERROR(100*($D60*(INDEX('Data_NSA'!$A:$OK,MATCH(G$1,'Data_NSA'!$A:$A,0),MATCH($C60,'Data_NSA'!$1:$1,0))/INDEX('Data_NSA'!$A:$OK,MATCH($E60,'Data_NSA'!$A:$A,0),MATCH($C60,'Data_NSA'!$1:$1,0))))/(100*(INDEX('Data_NSA'!$A:$OK,MATCH(G$1,'Data_NSA'!$A:$A,0),MATCH("CUUR0000SA0",'Data_NSA'!$1:$1,0))/INDEX('Data_NSA'!$A:$OK,MATCH($E60,'Data_NSA'!$A:$A,0),MATCH("CUUR0000SA0",'Data_NSA'!$1:$1,0)))),"") | H60: =IFERROR(100*($D60*(INDEX('Data_NSA'!$A:$OK,MATCH(H$1,'Data_NSA'!$A:$A,0),MATCH($C60,'Data_NSA'!$1:$1,0))/INDEX('Data_NSA'!$A:$OK,MATCH($E60,'Data_NSA'!$A:$A,0),MATCH($C60,'Data_NSA'!$1:$1,0))))/(100*(INDEX('Data_NSA'!$A:$OK,MATCH(H$1,'Data_NSA'!$A:$A,0),MATCH("CUUR0000SA0",'Data_NSA'!$1:$1,0))/INDEX('Data_NSA'!$A:$OK,MATCH($E60,'Data_NSA'!$A:$A,0),MATCH("CUUR0000SA0",'Data_NSA'!$1:$1,0)))),"") | I60: =IFERROR(100*($D60*(INDEX('Data_NSA'!$A:$OK,MATCH(I$1,'Data_NSA'!$A:$A,0),MATCH($C60,'Data_NSA'!$1:$1,0))/INDEX('Data_NSA'!$A:$OK,MATCH($E60,'Data_NSA'!$A:$A,0),MATCH($C60,'Data_NSA'!$1:$1,0))))/(100*(INDEX('Data_NSA'!$A:$OK,MATCH(I$1,'Data_NSA'!$A:$A,0),MATCH("CUUR0000SA0",'Data_NSA'!$1:$1,0))/INDEX('Data_NSA'!$A:$OK,MATCH($E60,'Data_NSA'!$A:$A,0),MATCH("CUUR0000SA0",'Data_NSA'!$1:$1,0)))),"")
A61: SEFJ02 | B61: Cheese and related products | C61: CUUR0000SEFJ02 | D61: 0.261 | E61: 45992 | F61: 2024 | G61: =IFERROR(100*($D61*(INDEX('Data_NSA'!$A:$OK,MATCH(G$1,'Data_NSA'!$A:$A,0),MATCH($C61,'Data_NSA'!$1:$1,0))/INDEX('Data_NSA'!$A:$OK,MATCH($E61,'Data_NSA'!$A:$A,0),MATCH($C61,'Data_NSA'!$1:$1,0))))/(100*(INDEX('Data_NSA'!$A:$OK,MATCH(G$1,'Data_NSA'!$A:$A,0),MATCH("CUUR0000SA0",'Data_NSA'!$1:$1,0))/INDEX('Data_NSA'!$A:$OK,MATCH($E61,'Data_NSA'!$A:$A,0),MATCH("CUUR0000SA0",'Data_NSA'!$1:$1,0)))),"") | H61: =IFERROR(100*($D61*(INDEX('Data_NSA'!$A:$OK,MATCH(H$1,'Data_NSA'!$A:$A,0),MATCH($C61,'Data_NSA'!$1:$1,0))/INDEX('Data_NSA'!$A:$OK,MATCH($E61,'Data_NSA'!$A:$A,0),MATCH($C61,'Data_NSA'!$1:$1,0))))/(100*(INDEX('Data_NSA'!$A:$OK,MATCH(H$1,'Data_NSA'!$A:$A,0),MATCH("CUUR0000SA0",'Data_NSA'!$1:$1,0))/INDEX('Data_NSA'!$A:$OK,MATCH($E61,'Data_NSA'!$A:$A,0),MATCH("CUUR0000SA0",'Data_NSA'!$1:$1,0)))),"") | I61: =IFERROR(100*($D61*(INDEX('Data_NSA'!$A:$OK,MATCH(I$1,'Data_NSA'!$A:$A,0),MATCH($C61,'Data_NSA'!$1:$1,0))/INDEX('Data_NSA'!$A:$OK,MATCH($E61,'Data_NSA'!$A:$A,0),MATCH($C61,'Data_NSA'!$1:$1,0))))/(100*(INDEX('Data_NSA'!$A:$OK,MATCH(I$1,'Data_NSA'!$A:$A,0),MATCH("CUUR0000SA0",'Data_NSA'!$1:$1,0))/INDEX('Data_NSA'!$A:$OK,MATCH($E61,'Data_NSA'!$A:$A,0),MATCH("CUUR0000SA0",'Data_NSA'!$1:$1,0)))),"")
A62: SEFJ03 | B62: Ice cream and related products | C62: CUUR0000SEFJ03 | D62: 0.115 | E62: 45992 | F62: 2024 | G62: =IFERROR(100*($D62*(INDEX('Data_NSA'!$A:$OK,MATCH(G$1,'Data_NSA'!$A:$A,0),MATCH($C62,'Data_NSA'!$1:$1,0))/INDEX('Data_NSA'!$A:$OK,MATCH($E62,'Data_NSA'!$A:$A,0),MATCH($C62,'Data_NSA'!$1:$1,0))))/(100*(INDEX('Data_NSA'!$A:$OK,MATCH(G$1,'Data_NSA'!$A:$A,0),MATCH("CUUR0000SA0",'Data_NSA'!$1:$1,0))/INDEX('Data_NSA'!$A:$OK,MATCH($E62,'Data_NSA'!$A:$A,0),MATCH("CUUR0000SA0",'Data_NSA'!$1:$1,0)))),"") | H62: =IFERROR(100*($D62*(INDEX('Data_NSA'!$A:$OK,MATCH(H$1,'Data_NSA'!$A:$A,0),MATCH($C62,'Data_NSA'!$1:$1,0))/INDEX('Data_NSA'!$A:$OK,MATCH($E62,'Data_NSA'!$A:$A,0),MATCH($C62,'Data_NSA'!$1:$1,0))))/(100*(INDEX('Data_NSA'!$A:$OK,MATCH(H$1,'Data_NSA'!$A:$A,0),MATCH("CUUR0000SA0",'Data_NSA'!$1:$1,0))/INDEX('Data_NSA'!$A:$OK,MATCH($E62,'Data_NSA'!$A:$A,0),MATCH("CUUR0000SA0",'Data_NSA'!$1:$1,0)))),"") | I62: =IFERROR(100*($D62*(INDEX('Data_NSA'!$A:$OK,MATCH(I$1,'Data_NSA'!$A:$A,0),MATCH($C62,'Data_NSA'!$1:$1,0))/INDEX('Data_NSA'!$A:$OK,MATCH($E62,'Data_NSA'!$A:$A,0),MATCH($C62,'Data_NSA'!$1:$1,0))))/(100*(INDEX('Data_NSA'!$A:$OK,MATCH(I$1,'Data_NSA'!$A:$A,0),MATCH("CUUR0000SA0",'Data_NSA'!$1:$1,0))/INDEX('Data_NSA'!$A:$OK,MATCH($E62,'Data_NSA'!$A:$A,0),MATCH("CUUR0000SA0",'Data_NSA'!$1:$1,0)))),"")
A63: SEFJ04 | B63: Other dairy and related products | C63: CUUR0000SEFJ04 | D63: 0.192 | E63: 45992 | F63: 2024 | G63: =IFERROR(100*($D63*(INDEX('Data_NSA'!$A:$OK,MATCH(G$1,'Data_NSA'!$A:$A,0),MATCH($C63,'Data_NSA'!$1:$1,0))/INDEX('Data_NSA'!$A:$OK,MATCH($E63,'Data_NSA'!$A:$A,0),MATCH($C63,'Data_NSA'!$1:$1,0))))/(100*(INDEX('Data_NSA'!$A:$OK,MATCH(G$1,'Data_NSA'!$A:$A,0),MATCH("CUUR0000SA0",'Data_NSA'!$1:$1,0))/INDEX('Data_NSA'!$A:$OK,MATCH($E63,'Data_NSA'!$A:$A,0),MATCH("CUUR0000SA0",'Data_NSA'!$1:$1,0)))),"") | H63: =IFERROR(100*($D63*(INDEX('Data_NSA'!$A:$OK,MATCH(H$1,'Data_NSA'!$A:$A,0),MATCH($C63,'Data_NSA'!$1:$1,0))/INDEX('Data_NSA'!$A:$OK,MATCH($E63,'Data_NSA'!$A:$A,0),MATCH($C63,'Data_NSA'!$1:$1,0))))/(100*(INDEX('Data_NSA'!$A:$OK,MATCH(H$1,'Data_NSA'!$A:$A,0),MATCH("CUUR0000SA0",'Data_NSA'!$1:$1,0))/INDEX('Data_NSA'!$A:$OK,MATCH($E63,'Data_NSA'!$A:$A,0),MATCH("CUUR0000SA0",'Data_NSA'!$1:$1,0)))),"") | I63: =IFERROR(100*($D63*(INDEX('Data_NSA'!$A:$OK,MATCH(I$1,'Data_NSA'!$A:$A,0),MATCH($C63,'Data_NSA'!$1:$1,0))/INDEX('Data_NSA'!$A:$OK,MATCH($E63,'Data_NSA'!$A:$A,0),MATCH($C63,'Data_NSA'!$1:$1,0))))/(100*(INDEX('Data_NSA'!$A:$OK,MATCH(I$1,'Data_NSA'!$A:$A,0),MATCH("CUUR0000SA0",'Data_NSA'!$1:$1,0))/INDEX('Data_NSA'!$A:$OK,MATCH($E63,'Data_NSA'!$A:$A,0),MATCH("CUUR0000SA0",'Data_NSA'!$1:$1,0)))),"")
A64: SAF113 | B64: Fruits and vegetables | C64: CUUR0000SAF113 | D64: 1.269 | E64: 45992 | F64: 2024 | G64: =IFERROR(100*($D64*(INDEX('Data_NSA'!$A:$OK,MATCH(G$1,'Data_NSA'!$A:$A,0),MATCH($C64,'Data_NSA'!$1:$1,0))/INDEX('Data_NSA'!$A:$OK,MATCH($E64,'Data_NSA'!$A:$A,0),MATCH($C64,'Data_NSA'!$1:$1,0))))/(100*(INDEX('Data_NSA'!$A:$OK,MATCH(G$1,'Data_NSA'!$A:$A,0),MATCH("CUUR0000SA0",'Data_NSA'!$1:$1,0))/INDEX('Data_NSA'!$A:$OK,MATCH($E64,'Data_NSA'!$A:$A,0),MATCH("CUUR0000SA0",'Data_NSA'!$1:$1,0)))),"") | H64: =IFERROR(100*($D64*(INDEX('Data_NSA'!$A:$OK,MATCH(H$1,'Data_NSA'!$A:$A,0),MATCH($C64,'Data_NSA'!$1:$1,0))/INDEX('Data_NSA'!$A:$OK,MATCH($E64,'Data_NSA'!$A:$A,0),MATCH($C64,'Data_NSA'!$1:$1,0))))/(100*(INDEX('Data_NSA'!$A:$OK,MATCH(H$1,'Data_NSA'!$A:$A,0),MATCH("CUUR0000SA0",'Data_NSA'!$1:$1,0))/INDEX('Data_NSA'!$A:$OK,MATCH($E64,'Data_NSA'!$A:$A,0),MATCH("CUUR0000SA0",'Data_NSA'!$1:$1,0)))),"") | I64: =IFERROR(100*($D64*(INDEX('Data_NSA'!$A:$OK,MATCH(I$1,'Data_NSA'!$A:$A,0),MATCH($C64,'Data_NSA'!$1:$1,0))/INDEX('Data_NSA'!$A:$OK,MATCH($E64,'Data_NSA'!$A:$A,0),MATCH($C64,'Data_NSA'!$1:$1,0))))/(100*(INDEX('Data_NSA'!$A:$OK,MATCH(I$1,'Data_NSA'!$A:$A,0),MATCH("CUUR0000SA0",'Data_NSA'!$1:$1,0))/INDEX('Data_NSA'!$A:$OK,MATCH($E64,'Data_NSA'!$A:$A,0),MATCH("CUUR0000SA0",'Data_NSA'!$1:$1,0)))),"")
A65: SAF1131 | B65: Fresh fruits and vegetables | C65: CUUR0000SAF1131 | D65: 1.008 | E65: 45992 | F65: 2024 | G65: =IFERROR(100*($D65*(INDEX('Data_NSA'!$A:$OK,MATCH(G$1,'Data_NSA'!$A:$A,0),MATCH($C65,'Data_NSA'!$1:$1,0))/INDEX('Data_NSA'!$A:$OK,MATCH($E65,'Data_NSA'!$A:$A,0),MATCH($C65,'Data_NSA'!$1:$1,0))))/(100*(INDEX('Data_NSA'!$A:$OK,MATCH(G$1,'Data_NSA'!$A:$A,0),MATCH("CUUR0000SA0",'Data_NSA'!$1:$1,0))/INDEX('Data_NSA'!$A:$OK,MATCH($E65,'Data_NSA'!$A:$A,0),MATCH("CUUR0000SA0",'Data_NSA'!$1:$1,0)))),"") | H65: =IFERROR(100*($D65*(INDEX('Data_NSA'!$A:$OK,MATCH(H$1,'Data_NSA'!$A:$A,0),MATCH($C65,'Data_NSA'!$1:$1,0))/INDEX('Data_NSA'!$A:$OK,MATCH($E65,'Data_NSA'!$A:$A,0),MATCH($C65,'Data_NSA'!$1:$1,0))))/(100*(INDEX('Data_NSA'!$A:$OK,MATCH(H$1,'Data_NSA'!$A:$A,0),MATCH("CUUR0000SA0",'Data_NSA'!$1:$1,0))/INDEX('Data_NSA'!$A:$OK,MATCH($E65,'Data_NSA'!$A:$A,0),MATCH("CUUR0000SA0",'Data_NSA'!$1:$1,0)))),"") | I65: =IFERROR(100*($D65*(INDEX('Data_NSA'!$A:$OK,MATCH(I$1,'Data_NSA'!$A:$A,0),MATCH($C65,'Data_NSA'!$1:$1,0))/INDEX('Data_NSA'!$A:$OK,MATCH($E65,'Data_NSA'!$A:$A,0),MATCH($C65,'Data_NSA'!$1:$1,0))))/(100*(INDEX('Data_NSA'!$A:$OK,MATCH(I$1,'Data_NSA'!$A:$A,0),MATCH("CUUR0000SA0",'Data_NSA'!$1:$1,0))/INDEX('Data_NSA'!$A:$OK,MATCH($E65,'Data_NSA'!$A:$A,0),MATCH("CUUR0000SA0",'Data_NSA'!$1:$1,0)))),"")
A66: SEFK | B66: Fresh fruits | C66: CUUR0000SEFK | D66: 0.532 | E66: 45992 | F66: 2024 | G66: =IFERROR(100*($D66*(INDEX('Data_NSA'!$A:$OK,MATCH(G$1,'Data_NSA'!$A:$A,0),MATCH($C66,'Data_NSA'!$1:$1,0))/INDEX('Data_NSA'!$A:$OK,MATCH($E66,'Data_NSA'!$A:$A,0),MATCH($C66,'Data_NSA'!$1:$1,0))))/(100*(INDEX('Data_NSA'!$A:$OK,MATCH(G$1,'Data_NSA'!$A:$A,0),MATCH("CUUR0000SA0",'Data_NSA'!$1:$1,0))/INDEX('Data_NSA'!$A:$OK,MATCH($E66,'Data_NSA'!$A:$A,0),MATCH("CUUR0000SA0",'Data_NSA'!$1:$1,0)))),"") | H66: =IFERROR(100*($D66*(INDEX('Data_NSA'!$A:$OK,MATCH(H$1,'Data_NSA'!$A:$A,0),MATCH($C66,'Data_NSA'!$1:$1,0))/INDEX('Data_NSA'!$A:$OK,MATCH($E66,'Data_NSA'!$A:$A,0),MATCH($C66,'Data_NSA'!$1:$1,0))))/(100*(INDEX('Data_NSA'!$A:$OK,MATCH(H$1,'Data_NSA'!$A:$A,0),MATCH("CUUR0000SA0",'Data_NSA'!$1:$1,0))/INDEX('Data_NSA'!$A:$OK,MATCH($E66,'Data_NSA'!$A:$A,0),MATCH("CUUR0000SA0",'Data_NSA'!$1:$1,0)))),"") | I66: =IFERROR(100*($D66*(INDEX('Data_NSA'!$A:$OK,MATCH(I$1,'Data_NSA'!$A:$A,0),MATCH($C66,'Data_NSA'!$1:$1,0))/INDEX('Data_NSA'!$A:$OK,MATCH($E66,'Data_NSA'!$A:$A,0),MATCH($C66,'Data_NSA'!$1:$1,0))))/(100*(INDEX('Data_NSA'!$A:$OK,MATCH(I$1,'Data_NSA'!$A:$A,0),MATCH("CUUR0000SA0",'Data_NSA'!$1:$1,0))/INDEX('Data_NSA'!$A:$OK,MATCH($E66,'Data_NSA'!$A:$A,0),MATCH("CUUR0000SA0",'Data_NSA'!$1:$1,0)))),"")
A67: SEFK01 | B67: Apples | C67: CUUR0000SEFK01 | D67: 0.073 | E67: 45992 | F67: 2024 | G67: =IFERROR(100*($D67*(INDEX('Data_NSA'!$A:$OK,MATCH(G$1,'Data_NSA'!$A:$A,0),MATCH($C67,'Data_NSA'!$1:$1,0))/INDEX('Data_NSA'!$A:$OK,MATCH($E67,'Data_NSA'!$A:$A,0),MATCH($C67,'Data_NSA'!$1:$1,0))))/(100*(INDEX('Data_NSA'!$A:$OK,MATCH(G$1,'Data_NSA'!$A:$A,0),MATCH("CUUR0000SA0",'Data_NSA'!$1:$1,0))/INDEX('Data_NSA'!$A:$OK,MATCH($E67,'Data_NSA'!$A:$A,0),MATCH("CUUR0000SA0",'Data_NSA'!$1:$1,0)))),"") | H67: =IFERROR(100*($D67*(INDEX('Data_NSA'!$A:$OK,MATCH(H$1,'Data_NSA'!$A:$A,0),MATCH($C67,'Data_NSA'!$1:$1,0))/INDEX('Data_NSA'!$A:$OK,MATCH($E67,'Data_NSA'!$A:$A,0),MATCH($C67,'Data_NSA'!$1:$1,0))))/(100*(INDEX('Data_NSA'!$A:$OK,MATCH(H$1,'Data_NSA'!$A:$A,0),MATCH("CUUR0000SA0",'Data_NSA'!$1:$1,0))/INDEX('Data_NSA'!$A:$OK,MATCH($E67,'Data_NSA'!$A:$A,0),MATCH("CUUR0000SA0",'Data_NSA'!$1:$1,0)))),"") | I67: =IFERROR(100*($D67*(INDEX('Data_NSA'!$A:$OK,MATCH(I$1,'Data_NSA'!$A:$A,0),MATCH($C67,'Data_NSA'!$1:$1,0))/INDEX('Data_NSA'!$A:$OK,MATCH($E67,'Data_NSA'!$A:$A,0),MATCH($C67,'Data_NSA'!$1:$1,0))))/(100*(INDEX('Data_NSA'!$A:$OK,MATCH(I$1,'Data_NSA'!$A:$A,0),MATCH("CUUR0000SA0",'Data_NSA'!$1:$1,0))/INDEX('Data_NSA'!$A:$OK,MATCH($E67,'Data_NSA'!$A:$A,0),MATCH("CUUR0000SA0",'Data_NSA'!$1:$1,0)))),"")
A68: SEFK02 | B68: Bananas | C68: CUUR0000SEFK02 | D68: 0.06 | E68: 45992 | F68: 2024 | G68: =IFERROR(100*($D68*(INDEX('Data_NSA'!$A:$OK,MATCH(G$1,'Data_NSA'!$A:$A,0),MATCH($C68,'Data_NSA'!$1:$1,0))/INDEX('Data_NSA'!$A:$OK,MATCH($E68,'Data_NSA'!$A:$A,0),MATCH($C68,'Data_NSA'!$1:$1,0))))/(100*(INDEX('Data_NSA'!$A:$OK,MATCH(G$1,'Data_NSA'!$A:$A,0),MATCH("CUUR0000SA0",'Data_NSA'!$1:$1,0))/INDEX('Data_NSA'!$A:$OK,MATCH($E68,'Data_NSA'!$A:$A,0),MATCH("CUUR0000SA0",'Data_NSA'!$1:$1,0)))),"") | H68: =IFERROR(100*($D68*(INDEX('Data_NSA'!$A:$OK,MATCH(H$1,'Data_NSA'!$A:$A,0),MATCH($C68,'Data_NSA'!$1:$1,0))/INDEX('Data_NSA'!$A:$OK,MATCH($E68,'Data_NSA'!$A:$A,0),MATCH($C68,'Data_NSA'!$1:$1,0))))/(100*(INDEX('Data_NSA'!$A:$OK,MATCH(H$1,'Data_NSA'!$A:$A,0),MATCH("CUUR0000SA0",'Data_NSA'!$1:$1,0))/INDEX('Data_NSA'!$A:$OK,MATCH($E68,'Data_NSA'!$A:$A,0),MATCH("CUUR0000SA0",'Data_NSA'!$1:$1,0)))),"") | I68: =IFERROR(100*($D68*(INDEX('Data_NSA'!$A:$OK,MATCH(I$1,'Data_NSA'!$A:$A,0),MATCH($C68,'Data_NSA'!$1:$1,0))/INDEX('Data_NSA'!$A:$OK,MATCH($E68,'Data_NSA'!$A:$A,0),MATCH($C68,'Data_NSA'!$1:$1,0))))/(100*(INDEX('Data_NSA'!$A:$OK,MATCH(I$1,'Data_NSA'!$A:$A,0),MATCH("CUUR0000SA0",'Data_NSA'!$1:$1,0))/INDEX('Data_NSA'!$A:$OK,MATCH($E68,'Data_NSA'!$A:$A,0),MATCH("CUUR0000SA0",'Data_NSA'!$1:$1,0)))),"")
A69: SEFK03 | B69: Citrus fruits | C69: CUUR0000SEFK03 | D69: 0.077 | E69: 45992 | F69: 2024 | G69: =IFERROR(100*($D69*(INDEX('Data_NSA'!$A:$OK,MATCH(G$1,'Data_NSA'!$A:$A,0),MATCH($C69,'Data_NSA'!$1:$1,0))/INDEX('Data_NSA'!$A:$OK,MATCH($E69,'Data_NSA'!$A:$A,0),MATCH($C69,'Data_NSA'!$1:$1,0))))/(100*(INDEX('Data_NSA'!$A:$OK,MATCH(G$1,'Data_NSA'!$A:$A,0),MATCH("CUUR0000SA0",'Data_NSA'!$1:$1,0))/INDEX('Data_NSA'!$A:$OK,MATCH($E69,'Data_NSA'!$A:$A,0),MATCH("CUUR0000SA0",'Data_NSA'!$1:$1,0)))),"") | H69: =IFERROR(100*($D69*(INDEX('Data_NSA'!$A:$OK,MATCH(H$1,'Data_NSA'!$A:$A,0),MATCH($C69,'Data_NSA'!$1:$1,0))/INDEX('Data_NSA'!$A:$OK,MATCH($E69,'Data_NSA'!$A:$A,0),MATCH($C69,'Data_NSA'!$1:$1,0))))/(100*(INDEX('Data_NSA'!$A:$OK,MATCH(H$1,'Data_NSA'!$A:$A,0),MATCH("CUUR0000SA0",'Data_NSA'!$1:$1,0))/INDEX('Data_NSA'!$A:$OK,MATCH($E69,'Data_NSA'!$A:$A,0),MATCH("CUUR0000SA0",'Data_NSA'!$1:$1,0)))),"") | I69: =IFERROR(100*($D69*(INDEX('Data_NSA'!$A:$OK,MATCH(I$1,'Data_NSA'!$A:$A,0),MATCH($C69,'Data_NSA'!$1:$1,0))/INDEX('Data_NSA'!$A:$OK,MATCH($E69,'Data_NSA'!$A:$A,0),MATCH($C69,'Data_NSA'!$1:$1,0))))/(100*(INDEX('Data_NSA'!$A:$OK,MATCH(I$1,'Data_NSA'!$A:$A,0),MATCH("CUUR0000SA0",'Data_NSA'!$1:$1,0))/INDEX('Data_NSA'!$A:$OK,MATCH($E69,'Data_NSA'!$A:$A,0),MATCH("CUUR0000SA0",'Data_NSA'!$1:$1,0)))),"")
A70: SS11031 | B70: Oranges, including tangerines | C70: CUUR0000SS11031 | E70: 45992 | F70: 2024 | G70: =IFERROR(100*($D70*(INDEX('Data_NSA'!$A:$OK,MATCH(G$1,'Data_NSA'!$A:$A,0),MATCH($C70,'Data_NSA'!$1:$1,0))/INDEX('Data_NSA'!$A:$OK,MATCH($E70,'Data_NSA'!$A:$A,0),MATCH($C70,'Data_NSA'!$1:$1,0))))/(100*(INDEX('Data_NSA'!$A:$OK,MATCH(G$1,'Data_NSA'!$A:$A,0),MATCH("CUUR0000SA0",'Data_NSA'!$1:$1,0))/INDEX('Data_NSA'!$A:$OK,MATCH($E70,'Data_NSA'!$A:$A,0),MATCH("CUUR0000SA0",'Data_NSA'!$1:$1,0)))),"") | H70: =IFERROR(100*($D70*(INDEX('Data_NSA'!$A:$OK,MATCH(H$1,'Data_NSA'!$A:$A,0),MATCH($C70,'Data_NSA'!$1:$1,0))/INDEX('Data_NSA'!$A:$OK,MATCH($E70,'Data_NSA'!$A:$A,0),MATCH($C70,'Data_NSA'!$1:$1,0))))/(100*(INDEX('Data_NSA'!$A:$OK,MATCH(H$1,'Data_NSA'!$A:$A,0),MATCH("CUUR0000SA0",'Data_NSA'!$1:$1,0))/INDEX('Data_NSA'!$A:$OK,MATCH($E70,'Data_NSA'!$A:$A,0),MATCH("CUUR0000SA0",'Data_NSA'!$1:$1,0)))),"") | I70: =IFERROR(100*($D70*(INDEX('Data_NSA'!$A:$OK,MATCH(I$1,'Data_NSA'!$A:$A,0),MATCH($C70,'Data_NSA'!$1:$1,0))/INDEX('Data_NSA'!$A:$OK,MATCH($E70,'Data_NSA'!$A:$A,0),MATCH($C70,'Data_NSA'!$1:$1,0))))/(100*(INDEX('Data_NSA'!$A:$OK,MATCH(I$1,'Data_NSA'!$A:$A,0),MATCH("CUUR0000SA0",'Data_NSA'!$1:$1,0))/INDEX('Data_NSA'!$A:$OK,MATCH($E70,'Data_NSA'!$A:$A,0),MATCH("CUUR0000SA0",'Data_NSA'!$1:$1,0)))),"")
A71: SEFK04 | B71: Other fresh fruits | C71: CUUR0000SEFK04 | D71: 0.322 | E71: 45992 | F71: 2024 | G71: =IFERROR(100*($D71*(INDEX('Data_NSA'!$A:$OK,MATCH(G$1,'Data_NSA'!$A:$A,0),MATCH($C71,'Data_NSA'!$1:$1,0))/INDEX('Data_NSA'!$A:$OK,MATCH($E71,'Data_NSA'!$A:$A,0),MATCH($C71,'Data_NSA'!$1:$1,0))))/(100*(INDEX('Data_NSA'!$A:$OK,MATCH(G$1,'Data_NSA'!$A:$A,0),MATCH("CUUR0000SA0",'Data_NSA'!$1:$1,0))/INDEX('Data_NSA'!$A:$OK,MATCH($E71,'Data_NSA'!$A:$A,0),MATCH("CUUR0000SA0",'Data_NSA'!$1:$1,0)))),"") | H71: =IFERROR(100*($D71*(INDEX('Data_NSA'!$A:$OK,MATCH(H$1,'Data_NSA'!$A:$A,0),MATCH($C71,'Data_NSA'!$1:$1,0))/INDEX('Data_NSA'!$A:$OK,MATCH($E71,'Data_NSA'!$A:$A,0),MATCH($C71,'Data_NSA'!$1:$1,0))))/(100*(INDEX('Data_NSA'!$A:$OK,MATCH(H$1,'Data_NSA'!$A:$A,0),MATCH("CUUR0000SA0",'Data_NSA'!$1:$1,0))/INDEX('Data_NSA'!$A:$OK,MATCH($E71,'Data_NSA'!$A:$A,0),MATCH("CUUR0000SA0",'Data_NSA'!$1:$1,0)))),"") | I71: =IFERROR(100*($D71*(INDEX('Data_NSA'!$A:$OK,MATCH(I$1,'Data_NSA'!$A:$A,0),MATCH($C71,'Data_NSA'!$1:$1,0))/INDEX('Data_NSA'!$A:$OK,MATCH($E71,'Data_NSA'!$A:$A,0),MATCH($C71,'Data_NSA'!$1:$1,0))))/(100*(INDEX('Data_NSA'!$A:$OK,MATCH(I$1,'Data_NSA'!$A:$A,0),MATCH("CUUR0000SA0",'Data_NSA'!$1:$1,0))/INDEX('Data_NSA'!$A:$OK,MATCH($E71,'Data_NSA'!$A:$A,0),MATCH("CUUR0000SA0",'Data_NSA'!$1:$1,0)))),"")
A72: SEFL | B72: Fresh vegetables | C72: CUUR0000SEFL | D72: 0.476 | E72: 45992 | F72: 2024 | G72: =IFERROR(100*($D72*(INDEX('Data_NSA'!$A:$OK,MATCH(G$1,'Data_NSA'!$A:$A,0),MATCH($C72,'Data_NSA'!$1:$1,0))/INDEX('Data_NSA'!$A:$OK,MATCH($E72,'Data_NSA'!$A:$A,0),MATCH($C72,'Data_NSA'!$1:$1,0))))/(100*(INDEX('Data_NSA'!$A:$OK,MATCH(G$1,'Data_NSA'!$A:$A,0),MATCH("CUUR0000SA0",'Data_NSA'!$1:$1,0))/INDEX('Data_NSA'!$A:$OK,MATCH($E72,'Data_NSA'!$A:$A,0),MATCH("CUUR0000SA0",'Data_NSA'!$1:$1,0)))),"") | H72: =IFERROR(100*($D72*(INDEX('Data_NSA'!$A:$OK,MATCH(H$1,'Data_NSA'!$A:$A,0),MATCH($C72,'Data_NSA'!$1:$1,0))/INDEX('Data_NSA'!$A:$OK,MATCH($E72,'Data_NSA'!$A:$A,0),MATCH($C72,'Data_NSA'!$1:$1,0))))/(100*(INDEX('Data_NSA'!$A:$OK,MATCH(H$1,'Data_NSA'!$A:$A,0),MATCH("CUUR0000SA0",'Data_NSA'!$1:$1,0))/INDEX('Data_NSA'!$A:$OK,MATCH($E72,'Data_NSA'!$A:$A,0),MATCH("CUUR0000SA0",'Data_NSA'!$1:$1,0)))),"") | I72: =IFERROR(100*($D72*(INDEX('Data_NSA'!$A:$OK,MATCH(I$1,'Data_NSA'!$A:$A,0),MATCH($C72,'Data_NSA'!$1:$1,0))/INDEX('Data_NSA'!$A:$OK,MATCH($E72,'Data_NSA'!$A:$A,0),MATCH($C72,'Data_NSA'!$1:$1,0))))/(100*(INDEX('Data_NSA'!$A:$OK,MATCH(I$1,'Data_NSA'!$A:$A,0),MATCH("CUUR0000SA0",'Data_NSA'!$1:$1,0))/INDEX('Data_NSA'!$A:$OK,MATCH($E72,'Data_NSA'!$A:$A,0),MATCH("CUUR0000SA0",'Data_NSA'!$1:$1,0)))),"")
A73: SEFL01 | B73: Potatoes | C73: CUUR0000SEFL01 | D73: 0.063 | E73: 45992 | F73: 2024 | G73: =IFERROR(100*($D73*(INDEX('Data_NSA'!$A:$OK,MATCH(G$1,'Data_NSA'!$A:$A,0),MATCH($C73,'Data_NSA'!$1:$1,0))/INDEX('Data_NSA'!$A:$OK,MATCH($E73,'Data_NSA'!$A:$A,0),MATCH($C73,'Data_NSA'!$1:$1,0))))/(100*(INDEX('Data_NSA'!$A:$OK,MATCH(G$1,'Data_NSA'!$A:$A,0),MATCH("CUUR0000SA0",'Data_NSA'!$1:$1,0))/INDEX('Data_NSA'!$A:$OK,MATCH($E73,'Data_NSA'!$A:$A,0),MATCH("CUUR0000SA0",'Data_NSA'!$1:$1,0)))),"") | H73: =IFERROR(100*($D73*(INDEX('Data_NSA'!$A:$OK,MATCH(H$1,'Data_NSA'!$A:$A,0),MATCH($C73,'Data_NSA'!$1:$1,0))/INDEX('Data_NSA'!$A:$OK,MATCH($E73,'Data_NSA'!$A:$A,0),MATCH($C73,'Data_NSA'!$1:$1,0))))/(100*(INDEX('Data_NSA'!$A:$OK,MATCH(H$1,'Data_NSA'!$A:$A,0),MATCH("CUUR0000SA0",'Data_NSA'!$1:$1,0))/INDEX('Data_NSA'!$A:$OK,MATCH($E73,'Data_NSA'!$A:$A,0),MATCH("CUUR0000SA0",'Data_NSA'!$1:$1,0)))),"") | I73: =IFERROR(100*($D73*(INDEX('Data_NSA'!$A:$OK,MATCH(I$1,'Data_NSA'!$A:$A,0),MATCH($C73,'Data_NSA'!$1:$1,0))/INDEX('Data_NSA'!$A:$OK,MATCH($E73,'Data_NSA'!$A:$A,0),MATCH($C73,'Data_NSA'!$1:$1,0))))/(100*(INDEX('Data_NSA'!$A:$OK,MATCH(I$1,'Data_NSA'!$A:$A,0),MATCH("CUUR0000SA0",'Data_NSA'!$1:$1,0))/INDEX('Data_NSA'!$A:$OK,MATCH($E73,'Data_NSA'!$A:$A,0),MATCH("CUUR0000SA0",'Data_NSA'!$1:$1,0)))),"")
A74: SEFL02 | B74: Lettuce | C74: CUUR0000SEFL02 | D74: 0.044 | E74: 45992 | F74: 2024 | G74: =IFERROR(100*($D74*(INDEX('Data_NSA'!$A:$OK,MATCH(G$1,'Data_NSA'!$A:$A,0),MATCH($C74,'Data_NSA'!$1:$1,0))/INDEX('Data_NSA'!$A:$OK,MATCH($E74,'Data_NSA'!$A:$A,0),MATCH($C74,'Data_NSA'!$1:$1,0))))/(100*(INDEX('Data_NSA'!$A:$OK,MATCH(G$1,'Data_NSA'!$A:$A,0),MATCH("CUUR0000SA0",'Data_NSA'!$1:$1,0))/INDEX('Data_NSA'!$A:$OK,MATCH($E74,'Data_NSA'!$A:$A,0),MATCH("CUUR0000SA0",'Data_NSA'!$1:$1,0)))),"") | H74: =IFERROR(100*($D74*(INDEX('Data_NSA'!$A:$OK,MATCH(H$1,'Data_NSA'!$A:$A,0),MATCH($C74,'Data_NSA'!$1:$1,0))/INDEX('Data_NSA'!$A:$OK,MATCH($E74,'Data_NSA'!$A:$A,0),MATCH($C74,'Data_NSA'!$1:$1,0))))/(100*(INDEX('Data_NSA'!$A:$OK,MATCH(H$1,'Data_NSA'!$A:$A,0),MATCH("CUUR0000SA0",'Data_NSA'!$1:$1,0))/INDEX('Data_NSA'!$A:$OK,MATCH($E74,'Data_NSA'!$A:$A,0),MATCH("CUUR0000SA0",'Data_NSA'!$1:$1,0)))),"") | I74: =IFERROR(100*($D74*(INDEX('Data_NSA'!$A:$OK,MATCH(I$1,'Data_NSA'!$A:$A,0),MATCH($C74,'Data_NSA'!$1:$1,0))/INDEX('Data_NSA'!$A:$OK,MATCH($E74,'Data_NSA'!$A:$A,0),MATCH($C74,'Data_NSA'!$1:$1,0))))/(100*(INDEX('Data_NSA'!$A:$OK,MATCH(I$1,'Data_NSA'!$A:$A,0),MATCH("CUUR0000SA0",'Data_NSA'!$1:$1,0))/INDEX('Data_NSA'!$A:$OK,MATCH($E74,'Data_NSA'!$A:$A,0),MATCH("CUUR0000SA0",'Data_NSA'!$1:$1,0)))),"")
A75: SEFL03 | B75: Tomatoes | C75: CUUR0000SEFL03 | D75: 0.063 | E75: 45992 | F75: 2024 | G75: =IFERROR(100*($D75*(INDEX('Data_NSA'!$A:$OK,MATCH(G$1,'Data_NSA'!$A:$A,0),MATCH($C75,'Data_NSA'!$1:$1,0))/INDEX('Data_NSA'!$A:$OK,MATCH($E75,'Data_NSA'!$A:$A,0),MATCH($C75,'Data_NSA'!$1:$1,0))))/(100*(INDEX('Data_NSA'!$A:$OK,MATCH(G$1,'Data_NSA'!$A:$A,0),MATCH("CUUR0000SA0",'Data_NSA'!$1:$1,0))/INDEX('Data_NSA'!$A:$OK,MATCH($E75,'Data_NSA'!$A:$A,0),MATCH("CUUR0000SA0",'Data_NSA'!$1:$1,0)))),"") | H75: =IFERROR(100*($D75*(INDEX('Data_NSA'!$A:$OK,MATCH(H$1,'Data_NSA'!$A:$A,0),MATCH($C75,'Data_NSA'!$1:$1,0))/INDEX('Data_NSA'!$A:$OK,MATCH($E75,'Data_NSA'!$A:$A,0),MATCH($C75,'Data_NSA'!$1:$1,0))))/(100*(INDEX('Data_NSA'!$A:$OK,MATCH(H$1,'Data_NSA'!$A:$A,0),MATCH("CUUR0000SA0",'Data_NSA'!$1:$1,0))/INDEX('Data_NSA'!$A:$OK,MATCH($E75,'Data_NSA'!$A:$A,0),MATCH("CUUR0000SA0",'Data_NSA'!$1:$1,0)))),"") | I75: =IFERROR(100*($D75*(INDEX('Data_NSA'!$A:$OK,MATCH(I$1,'Data_NSA'!$A:$A,0),MATCH($C75,'Data_NSA'!$1:$1,0))/INDEX('Data_NSA'!$A:$OK,MATCH($E75,'Data_NSA'!$A:$A,0),MATCH($C75,'Data_NSA'!$1:$1,0))))/(100*(INDEX('Data_NSA'!$A:$OK,MATCH(I$1,'Data_NSA'!$A:$A,0),MATCH("CUUR0000SA0",'Data_NSA'!$1:$1,0))/INDEX('Data_NSA'!$A:$OK,MATCH($E75,'Data_NSA'!$A:$A,0),MATCH("CUUR0000SA0",'Data_NSA'!$1:$1,0)))),"")
A76: SEFL04 | B76: Other fresh vegetables | C76: CUUR0000SEFL04 | D76: 0.305 | E76: 45992 | F76: 2024 | G76: =IFERROR(100*($D76*(INDEX('Data_NSA'!$A:$OK,MATCH(G$1,'Data_NSA'!$A:$A,0),MATCH($C76,'Data_NSA'!$1:$1,0))/INDEX('Data_NSA'!$A:$OK,MATCH($E76,'Data_NSA'!$A:$A,0),MATCH($C76,'Data_NSA'!$1:$1,0))))/(100*(INDEX('Data_NSA'!$A:$OK,MATCH(G$1,'Data_NSA'!$A:$A,0),MATCH("CUUR0000SA0",'Data_NSA'!$1:$1,0))/INDEX('Data_NSA'!$A:$OK,MATCH($E76,'Data_NSA'!$A:$A,0),MATCH("CUUR0000SA0",'Data_NSA'!$1:$1,0)))),"") | H76: =IFERROR(100*($D76*(INDEX('Data_NSA'!$A:$OK,MATCH(H$1,'Data_NSA'!$A:$A,0),MATCH($C76,'Data_NSA'!$1:$1,0))/INDEX('Data_NSA'!$A:$OK,MATCH($E76,'Data_NSA'!$A:$A,0),MATCH($C76,'Data_NSA'!$1:$1,0))))/(100*(INDEX('Data_NSA'!$A:$OK,MATCH(H$1,'Data_NSA'!$A:$A,0),MATCH("CUUR0000SA0",'Data_NSA'!$1:$1,0))/INDEX('Data_NSA'!$A:$OK,MATCH($E76,'Data_NSA'!$A:$A,0),MATCH("CUUR0000SA0",'Data_NSA'!$1:$1,0)))),"") | I76: =IFERROR(100*($D76*(INDEX('Data_NSA'!$A:$OK,MATCH(I$1,'Data_NSA'!$A:$A,0),MATCH($C76,'Data_NSA'!$1:$1,0))/INDEX('Data_NSA'!$A:$OK,MATCH($E76,'Data_NSA'!$A:$A,0),MATCH($C76,'Data_NSA'!$1:$1,0))))/(100*(INDEX('Data_NSA'!$A:$OK,MATCH(I$1,'Data_NSA'!$A:$A,0),MATCH("CUUR0000SA0",'Data_NSA'!$1:$1,0))/INDEX('Data_NSA'!$A:$OK,MATCH($E76,'Data_NSA'!$A:$A,0),MATCH("CUUR0000SA0",'Data_NSA'!$1:$1,0)))),"")
A77: SEFM | B77: Processed fruits and vegetables | C77: CUUR0000SEFM | D77: 0.262 | E77: 45992 | F77: 2024 | G77: =IFERROR(100*($D77*(INDEX('Data_NSA'!$A:$OK,MATCH(G$1,'Data_NSA'!$A:$A,0),MATCH($C77,'Data_NSA'!$1:$1,0))/INDEX('Data_NSA'!$A:$OK,MATCH($E77,'Data_NSA'!$A:$A,0),MATCH($C77,'Data_NSA'!$1:$1,0))))/(100*(INDEX('Data_NSA'!$A:$OK,MATCH(G$1,'Data_NSA'!$A:$A,0),MATCH("CUUR0000SA0",'Data_NSA'!$1:$1,0))/INDEX('Data_NSA'!$A:$OK,MATCH($E77,'Data_NSA'!$A:$A,0),MATCH("CUUR0000SA0",'Data_NSA'!$1:$1,0)))),"") | H77: =IFERROR(100*($D77*(INDEX('Data_NSA'!$A:$OK,MATCH(H$1,'Data_NSA'!$A:$A,0),MATCH($C77,'Data_NSA'!$1:$1,0))/INDEX('Data_NSA'!$A:$OK,MATCH($E77,'Data_NSA'!$A:$A,0),MATCH($C77,'Data_NSA'!$1:$1,0))))/(100*(INDEX('Data_NSA'!$A:$OK,MATCH(H$1,'Data_NSA'!$A:$A,0),MATCH("CUUR0000SA0",'Data_NSA'!$1:$1,0))/INDEX('Data_NSA'!$A:$OK,MATCH($E77,'Data_NSA'!$A:$A,0),MATCH("CUUR0000SA0",'Data_NSA'!$1:$1,0)))),"") | I77: =IFERROR(100*($D77*(INDEX('Data_NSA'!$A:$OK,MATCH(I$1,'Data_NSA'!$A:$A,0),MATCH($C77,'Data_NSA'!$1:$1,0))/INDEX('Data_NSA'!$A:$OK,MATCH($E77,'Data_NSA'!$A:$A,0),MATCH($C77,'Data_NSA'!$1:$1,0))))/(100*(INDEX('Data_NSA'!$A:$OK,MATCH(I$1,'Data_NSA'!$A:$A,0),MATCH("CUUR0000SA0",'Data_NSA'!$1:$1,0))/INDEX('Data_NSA'!$A:$OK,MATCH($E77,'Data_NSA'!$A:$A,0),MATCH("CUUR0000SA0",'Data_NSA'!$1:$1,0)))),"")
A78: SEFM01 | B78: Canned fruits and vegetables | C78: CUUR0000SEFM01 | D78: 0.096 | E78: 45992 | F78: 2024 | G78: =IFERROR(100*($D78*(INDEX('Data_NSA'!$A:$OK,MATCH(G$1,'Data_NSA'!$A:$A,0),MATCH($C78,'Data_NSA'!$1:$1,0))/INDEX('Data_NSA'!$A:$OK,MATCH($E78,'Data_NSA'!$A:$A,0),MATCH($C78,'Data_NSA'!$1:$1,0))))/(100*(INDEX('Data_NSA'!$A:$OK,MATCH(G$1,'Data_NSA'!$A:$A,0),MATCH("CUUR0000SA0",'Data_NSA'!$1:$1,0))/INDEX('Data_NSA'!$A:$OK,MATCH($E78,'Data_NSA'!$A:$A,0),MATCH("CUUR0000SA0",'Data_NSA'!$1:$1,0)))),"") | H78: =IFERROR(100*($D78*(INDEX('Data_NSA'!$A:$OK,MATCH(H$1,'Data_NSA'!$A:$A,0),MATCH($C78,'Data_NSA'!$1:$1,0))/INDEX('Data_NSA'!$A:$OK,MATCH($E78,'Data_NSA'!$A:$A,0),MATCH($C78,'Data_NSA'!$1:$1,0))))/(100*(INDEX('Data_NSA'!$A:$OK,MATCH(H$1,'Data_NSA'!$A:$A,0),MATCH("CUUR0000SA0",'Data_NSA'!$1:$1,0))/INDEX('Data_NSA'!$A:$OK,MATCH($E78,'Data_NSA'!$A:$A,0),MATCH("CUUR0000SA0",'Data_NSA'!$1:$1,0)))),"") | I78: =IFERROR(100*($D78*(INDEX('Data_NSA'!$A:$OK,MATCH(I$1,'Data_NSA'!$A:$A,0),MATCH($C78,'Data_NSA'!$1:$1,0))/INDEX('Data_NSA'!$A:$OK,MATCH($E78,'Data_NSA'!$A:$A,0),MATCH($C78,'Data_NSA'!$1:$1,0))))/(100*(INDEX('Data_NSA'!$A:$OK,MATCH(I$1,'Data_NSA'!$A:$A,0),MATCH("CUUR0000SA0",'Data_NSA'!$1:$1,0))/INDEX('Data_NSA'!$A:$OK,MATCH($E78,'Data_NSA'!$A:$A,0),MATCH("CUUR0000SA0",'Data_NSA'!$1:$1,0)))),"")
A79: SS13031 | B79: Canned fruits | C79: CUUR0000SS13031 | E79: 45992 | F79: 2024 | G79: =IFERROR(100*($D79*(INDEX('Data_NSA'!$A:$OK,MATCH(G$1,'Data_NSA'!$A:$A,0),MATCH($C79,'Data_NSA'!$1:$1,0))/INDEX('Data_NSA'!$A:$OK,MATCH($E79,'Data_NSA'!$A:$A,0),MATCH($C79,'Data_NSA'!$1:$1,0))))/(100*(INDEX('Data_NSA'!$A:$OK,MATCH(G$1,'Data_NSA'!$A:$A,0),MATCH("CUUR0000SA0",'Data_NSA'!$1:$1,0))/INDEX('Data_NSA'!$A:$OK,MATCH($E79,'Data_NSA'!$A:$A,0),MATCH("CUUR0000SA0",'Data_NSA'!$1:$1,0)))),"") | H79: =IFERROR(100*($D79*(INDEX('Data_NSA'!$A:$OK,MATCH(H$1,'Data_NSA'!$A:$A,0),MATCH($C79,'Data_NSA'!$1:$1,0))/INDEX('Data_NSA'!$A:$OK,MATCH($E79,'Data_NSA'!$A:$A,0),MATCH($C79,'Data_NSA'!$1:$1,0))))/(100*(INDEX('Data_NSA'!$A:$OK,MATCH(H$1,'Data_NSA'!$A:$A,0),MATCH("CUUR0000SA0",'Data_NSA'!$1:$1,0))/INDEX('Data_NSA'!$A:$OK,MATCH($E79,'Data_NSA'!$A:$A,0),MATCH("CUUR0000SA0",'Data_NSA'!$1:$1,0)))),"") | I79: =IFERROR(100*($D79*(INDEX('Data_NSA'!$A:$OK,MATCH(I$1,'Data_NSA'!$A:$A,0),MATCH($C79,'Data_NSA'!$1:$1,0))/INDEX('Data_NSA'!$A:$OK,MATCH($E79,'Data_NSA'!$A:$A,0),MATCH($C79,'Data_NSA'!$1:$1,0))))/(100*(INDEX('Data_NSA'!$A:$OK,MATCH(I$1,'Data_NSA'!$A:$A,0),MATCH("CUUR0000SA0",'Data_NSA'!$1:$1,0))/INDEX('Data_NSA'!$A:$OK,MATCH($E79,'Data_NSA'!$A:$A,0),MATCH("CUUR0000SA0",'Data_NSA'!$1:$1,0)))),"")
A80: SS14021 | B80: Canned vegetables | C80: CUUR0000SS14021 | E80: 45992 | F80: 2024 | G80: =IFERROR(100*($D80*(INDEX('Data_NSA'!$A:$OK,MATCH(G$1,'Data_NSA'!$A:$A,0),MATCH($C80,'Data_NSA'!$1:$1,0))/INDEX('Data_NSA'!$A:$OK,MATCH($E80,'Data_NSA'!$A:$A,0),MATCH($C80,'Data_NSA'!$1:$1,0))))/(100*(INDEX('Data_NSA'!$A:$OK,MATCH(G$1,'Data_NSA'!$A:$A,0),MATCH("CUUR0000SA0",'Data_NSA'!$1:$1,0))/INDEX('Data_NSA'!$A:$OK,MATCH($E80,'Data_NSA'!$A:$A,0),MATCH("CUUR0000SA0",'Data_NSA'!$1:$1,0)))),"") | H80: =IFERROR(100*($D80*(INDEX('Data_NSA'!$A:$OK,MATCH(H$1,'Data_NSA'!$A:$A,0),MATCH($C80,'Data_NSA'!$1:$1,0))/INDEX('Data_NSA'!$A:$OK,MATCH($E80,'Data_NSA'!$A:$A,0),MATCH($C80,'Data_NSA'!$1:$1,0))))/(100*(INDEX('Data_NSA'!$A:$OK,MATCH(H$1,'Data_NSA'!$A:$A,0),MATCH("CUUR0000SA0",'Data_NSA'!$1:$1,0))/INDEX('Data_NSA'!$A:$OK,MATCH($E80,'Data_NSA'!$A:$A,0),MATCH("CUUR0000SA0",'Data_NSA'!$1:$1,0)))),"") | I80: =IFERROR(100*($D80*(INDEX('Data_NSA'!$A:$OK,MATCH(I$1,'Data_NSA'!$A:$A,0),MATCH($C80,'Data_NSA'!$1:$1,0))/INDEX('Data_NSA'!$A:$OK,MATCH($E80,'Data_NSA'!$A:$A,0),MATCH($C80,'Data_NSA'!$1:$1,0))))/(100*(INDEX('Data_NSA'!$A:$OK,MATCH(I$1,'Data_NSA'!$A:$A,0),MATCH("CUUR0000SA0",'Data_NSA'!$1:$1,0))/INDEX('Data_NSA'!$A:$OK,MATCH($E80,'Data_NSA'!$A:$A,0),MATCH("CUUR0000SA0",'Data_NSA'!$1:$1,0)))),"")
A81: SEFM02 | B81: Frozen fruits and vegetables | C81: CUUR0000SEFM02 | D81: 0.084 | E81: 45992 | F81: 2024 | G81: =IFERROR(100*($D81*(INDEX('Data_NSA'!$A:$OK,MATCH(G$1,'Data_NSA'!$A:$A,0),MATCH($C81,'Data_NSA'!$1:$1,0))/INDEX('Data_NSA'!$A:$OK,MATCH($E81,'Data_NSA'!$A:$A,0),MATCH($C81,'Data_NSA'!$1:$1,0))))/(100*(INDEX('Data_NSA'!$A:$OK,MATCH(G$1,'Data_NSA'!$A:$A,0),MATCH("CUUR0000SA0",'Data_NSA'!$1:$1,0))/INDEX('Data_NSA'!$A:$OK,MATCH($E81,'Data_NSA'!$A:$A,0),MATCH("CUUR0000SA0",'Data_NSA'!$1:$1,0)))),"") | H81: =IFERROR(100*($D81*(INDEX('Data_NSA'!$A:$OK,MATCH(H$1,'Data_NSA'!$A:$A,0),MATCH($C81,'Data_NSA'!$1:$1,0))/INDEX('Data_NSA'!$A:$OK,MATCH($E81,'Data_NSA'!$A:$A,0),MATCH($C81,'Data_NSA'!$1:$1,0))))/(100*(INDEX('Data_NSA'!$A:$OK,MATCH(H$1,'Data_NSA'!$A:$A,0),MATCH("CUUR0000SA0",'Data_NSA'!$1:$1,0))/INDEX('Data_NSA'!$A:$OK,MATCH($E81,'Data_NSA'!$A:$A,0),MATCH("CUUR0000SA0",'Data_NSA'!$1:$1,0)))),"") | I81: =IFERROR(100*($D81*(INDEX('Data_NSA'!$A:$OK,MATCH(I$1,'Data_NSA'!$A:$A,0),MATCH($C81,'Data_NSA'!$1:$1,0))/INDEX('Data_NSA'!$A:$OK,MATCH($E81,'Data_NSA'!$A:$A,0),MATCH($C81,'Data_NSA'!$1:$1,0))))/(100*(INDEX('Data_NSA'!$A:$OK,MATCH(I$1,'Data_NSA'!$A:$A,0),MATCH("CUUR0000SA0",'Data_NSA'!$1:$1,0))/INDEX('Data_NSA'!$A:$OK,MATCH($E81,'Data_NSA'!$A:$A,0),MATCH("CUUR0000SA0",'Data_NSA'!$1:$1,0)))),"")
A82: SS14011 | B82: Frozen vegetables | C82: CUUR0000SS14011 | E82: 45992 | F82: 2024 | G82: =IFERROR(100*($D82*(INDEX('Data_NSA'!$A:$OK,MATCH(G$1,'Data_NSA'!$A:$A,0),MATCH($C82,'Data_NSA'!$1:$1,0))/INDEX('Data_NSA'!$A:$OK,MATCH($E82,'Data_NSA'!$A:$A,0),MATCH($C82,'Data_NSA'!$1:$1,0))))/(100*(INDEX('Data_NSA'!$A:$OK,MATCH(G$1,'Data_NSA'!$A:$A,0),MATCH("CUUR0000SA0",'Data_NSA'!$1:$1,0))/INDEX('Data_NSA'!$A:$OK,MATCH($E82,'Data_NSA'!$A:$A,0),MATCH("CUUR0000SA0",'Data_NSA'!$1:$1,0)))),"") | H82: =IFERROR(100*($D82*(INDEX('Data_NSA'!$A:$OK,MATCH(H$1,'Data_NSA'!$A:$A,0),MATCH($C82,'Data_NSA'!$1:$1,0))/INDEX('Data_NSA'!$A:$OK,MATCH($E82,'Data_NSA'!$A:$A,0),MATCH($C82,'Data_NSA'!$1:$1,0))))/(100*(INDEX('Data_NSA'!$A:$OK,MATCH(H$1,'Data_NSA'!$A:$A,0),MATCH("CUUR0000SA0",'Data_NSA'!$1:$1,0))/INDEX('Data_NSA'!$A:$OK,MATCH($E82,'Data_NSA'!$A:$A,0),MATCH("CUUR0000SA0",'Data_NSA'!$1:$1,0)))),"") | I82: =IFERROR(100*($D82*(INDEX('Data_NSA'!$A:$OK,MATCH(I$1,'Data_NSA'!$A:$A,0),MATCH($C82,'Data_NSA'!$1:$1,0))/INDEX('Data_NSA'!$A:$OK,MATCH($E82,'Data_NSA'!$A:$A,0),MATCH($C82,'Data_NSA'!$1:$1,0))))/(100*(INDEX('Data_NSA'!$A:$OK,MATCH(I$1,'Data_NSA'!$A:$A,0),MATCH("CUUR0000SA0",'Data_NSA'!$1:$1,0))/INDEX('Data_NSA'!$A:$OK,MATCH($E82,'Data_NSA'!$A:$A,0),MATCH("CUUR0000SA0",'Data_NSA'!$1:$1,0)))),"")
A83: SEFM03 | B83: Other processed fruits and vegetables including dried | C83: CUUR0000SEFM03 | D83: 0.082 | E83: 45992 | F83: 2024 | G83: =IFERROR(100*($D83*(INDEX('Data_NSA'!$A:$OK,MATCH(G$1,'Data_NSA'!$A:$A,0),MATCH($C83,'Data_NSA'!$1:$1,0))/INDEX('Data_NSA'!$A:$OK,MATCH($E83,'Data_NSA'!$A:$A,0),MATCH($C83,'Data_NSA'!$1:$1,0))))/(100*(INDEX('Data_NSA'!$A:$OK,MATCH(G$1,'Data_NSA'!$A:$A,0),MATCH("CUUR0000SA0",'Data_NSA'!$1:$1,0))/INDEX('Data_NSA'!$A:$OK,MATCH($E83,'Data_NSA'!$A:$A,0),MATCH("CUUR0000SA0",'Data_NSA'!$1:$1,0)))),"") | H83: =IFERROR(100*($D83*(INDEX('Data_NSA'!$A:$OK,MATCH(H$1,'Data_NSA'!$A:$A,0),MATCH($C83,'Data_NSA'!$1:$1,0))/INDEX('Data_NSA'!$A:$OK,MATCH($E83,'Data_NSA'!$A:$A,0),MATCH($C83,'Data_NSA'!$1:$1,0))))/(100*(INDEX('Data_NSA'!$A:$OK,MATCH(H$1,'Data_NSA'!$A:$A,0),MATCH("CUUR0000SA0",'Data_NSA'!$1:$1,0))/INDEX('Data_NSA'!$A:$OK,MATCH($E83,'Data_NSA'!$A:$A,0),MATCH("CUUR0000SA0",'Data_NSA'!$1:$1,0)))),"") | I83: =IFERROR(100*($D83*(INDEX('Data_NSA'!$A:$OK,MATCH(I$1,'Data_NSA'!$A:$A,0),MATCH($C83,'Data_NSA'!$1:$1,0))/INDEX('Data_NSA'!$A:$OK,MATCH($E83,'Data_NSA'!$A:$A,0),MATCH($C83,'Data_NSA'!$1:$1,0))))/(100*(INDEX('Data_NSA'!$A:$OK,MATCH(I$1,'Data_NSA'!$A:$A,0),MATCH("CUUR0000SA0",'Data_NSA'!$1:$1,0))/INDEX('Data_NSA'!$A:$OK,MATCH($E83,'Data_NSA'!$A:$A,0),MATCH("CUUR0000SA0",'Data_NSA'!$1:$1,0)))),"")
A84: SS14022 | B84: Dried beans, peas, and lentils | C84: CUUR0000SS14022 | E84: 45992 | F84: 2024 | G84: =IFERROR(100*($D84*(INDEX('Data_NSA'!$A:$OK,MATCH(G$1,'Data_NSA'!$A:$A,0),MATCH($C84,'Data_NSA'!$1:$1,0))/INDEX('Data_NSA'!$A:$OK,MATCH($E84,'Data_NSA'!$A:$A,0),MATCH($C84,'Data_NSA'!$1:$1,0))))/(100*(INDEX('Data_NSA'!$A:$OK,MATCH(G$1,'Data_NSA'!$A:$A,0),MATCH("CUUR0000SA0",'Data_NSA'!$1:$1,0))/INDEX('Data_NSA'!$A:$OK,MATCH($E84,'Data_NSA'!$A:$A,0),MATCH("CUUR0000SA0",'Data_NSA'!$1:$1,0)))),"") | H84: =IFERROR(100*($D84*(INDEX('Data_NSA'!$A:$OK,MATCH(H$1,'Data_NSA'!$A:$A,0),MATCH($C84,'Data_NSA'!$1:$1,0))/INDEX('Data_NSA'!$A:$OK,MATCH($E84,'Data_NSA'!$A:$A,0),MATCH($C84,'Data_NSA'!$1:$1,0))))/(100*(INDEX('Data_NSA'!$A:$OK,MATCH(H$1,'Data_NSA'!$A:$A,0),MATCH("CUUR0000SA0",'Data_NSA'!$1:$1,0))/INDEX('Data_NSA'!$A:$OK,MATCH($E84,'Data_NSA'!$A:$A,0),MATCH("CUUR0000SA0",'Data_NSA'!$1:$1,0)))),"") | I84: =IFERROR(100*($D84*(INDEX('Data_NSA'!$A:$OK,MATCH(I$1,'Data_NSA'!$A:$A,0),MATCH($C84,'Data_NSA'!$1:$1,0))/INDEX('Data_NSA'!$A:$OK,MATCH($E84,'Data_NSA'!$A:$A,0),MATCH($C84,'Data_NSA'!$1:$1,0))))/(100*(INDEX('Data_NSA'!$A:$OK,MATCH(I$1,'Data_NSA'!$A:$A,0),MATCH("CUUR0000SA0",'Data_NSA'!$1:$1,0))/INDEX('Data_NSA'!$A:$OK,MATCH($E84,'Data_NSA'!$A:$A,0),MATCH("CUUR0000SA0",'Data_NSA'!$1:$1,0)))),"")
A85: SAF114 | B85: Nonalcoholic beverages and beverage materials | C85: CUUR0000SAF114 | D85: 0.995 | E85: 45992 | F85: 2024 | G85: =IFERROR(100*($D85*(INDEX('Data_NSA'!$A:$OK,MATCH(G$1,'Data_NSA'!$A:$A,0),MATCH($C85,'Data_NSA'!$1:$1,0))/INDEX('Data_NSA'!$A:$OK,MATCH($E85,'Data_NSA'!$A:$A,0),MATCH($C85,'Data_NSA'!$1:$1,0))))/(100*(INDEX('Data_NSA'!$A:$OK,MATCH(G$1,'Data_NSA'!$A:$A,0),MATCH("CUUR0000SA0",'Data_NSA'!$1:$1,0))/INDEX('Data_NSA'!$A:$OK,MATCH($E85,'Data_NSA'!$A:$A,0),MATCH("CUUR0000SA0",'Data_NSA'!$1:$1,0)))),"") | H85: =IFERROR(100*($D85*(INDEX('Data_NSA'!$A:$OK,MATCH(H$1,'Data_NSA'!$A:$A,0),MATCH($C85,'Data_NSA'!$1:$1,0))/INDEX('Data_NSA'!$A:$OK,MATCH($E85,'Data_NSA'!$A:$A,0),MATCH($C85,'Data_NSA'!$1:$1,0))))/(100*(INDEX('Data_NSA'!$A:$OK,MATCH(H$1,'Data_NSA'!$A:$A,0),MATCH("CUUR0000SA0",'Data_NSA'!$1:$1,0))/INDEX('Data_NSA'!$A:$OK,MATCH($E85,'Data_NSA'!$A:$A,0),MATCH("CUUR0000SA0",'Data_NSA'!$1:$1,0)))),"") | I85: =IFERROR(100*($D85*(INDEX('Data_NSA'!$A:$OK,MATCH(I$1,'Data_NSA'!$A:$A,0),MATCH($C85,'Data_NSA'!$1:$1,0))/INDEX('Data_NSA'!$A:$OK,MATCH($E85,'Data_NSA'!$A:$A,0),MATCH($C85,'Data_NSA'!$1:$1,0))))/(100*(INDEX('Data_NSA'!$A:$OK,MATCH(I$1,'Data_NSA'!$A:$A,0),MATCH("CUUR0000SA0",'Data_NSA'!$1:$1,0))/INDEX('Data_NSA'!$A:$OK,MATCH($E85,'Data_NSA'!$A:$A,0),MATCH("CUUR0000SA0",'Data_NSA'!$1:$1,0)))),"")
A86: SEFN | B86: Juices and nonalcoholic drinks | C86: CUUR0000SEFN | D86: 0.675 | E86: 45992 | F86: 2024 | G86: =IFERROR(100*($D86*(INDEX('Data_NSA'!$A:$OK,MATCH(G$1,'Data_NSA'!$A:$A,0),MATCH($C86,'Data_NSA'!$1:$1,0))/INDEX('Data_NSA'!$A:$OK,MATCH($E86,'Data_NSA'!$A:$A,0),MATCH($C86,'Data_NSA'!$1:$1,0))))/(100*(INDEX('Data_NSA'!$A:$OK,MATCH(G$1,'Data_NSA'!$A:$A,0),MATCH("CUUR0000SA0",'Data_NSA'!$1:$1,0))/INDEX('Data_NSA'!$A:$OK,MATCH($E86,'Data_NSA'!$A:$A,0),MATCH("CUUR0000SA0",'Data_NSA'!$1:$1,0)))),"") | H86: =IFERROR(100*($D86*(INDEX('Data_NSA'!$A:$OK,MATCH(H$1,'Data_NSA'!$A:$A,0),MATCH($C86,'Data_NSA'!$1:$1,0))/INDEX('Data_NSA'!$A:$OK,MATCH($E86,'Data_NSA'!$A:$A,0),MATCH($C86,'Data_NSA'!$1:$1,0))))/(100*(INDEX('Data_NSA'!$A:$OK,MATCH(H$1,'Data_NSA'!$A:$A,0),MATCH("CUUR0000SA0",'Data_NSA'!$1:$1,0))/INDEX('Data_NSA'!$A:$OK,MATCH($E86,'Data_NSA'!$A:$A,0),MATCH("CUUR0000SA0",'Data_NSA'!$1:$1,0)))),"") | I86: =IFERROR(100*($D86*(INDEX('Data_NSA'!$A:$OK,MATCH(I$1,'Data_NSA'!$A:$A,0),MATCH($C86,'Data_NSA'!$1:$1,0))/INDEX('Data_NSA'!$A:$OK,MATCH($E86,'Data_NSA'!$A:$A,0),MATCH($C86,'Data_NSA'!$1:$1,0))))/(100*(INDEX('Data_NSA'!$A:$OK,MATCH(I$1,'Data_NSA'!$A:$A,0),MATCH("CUUR0000SA0",'Data_NSA'!$1:$1,0))/INDEX('Data_NSA'!$A:$OK,MATCH($E86,'Data_NSA'!$A:$A,0),MATCH("CUUR0000SA0",'Data_NSA'!$1:$1,0)))),"")
A87: SEFN01 | B87: Carbonated drinks | C87: CUUR0000SEFN01 | D87: 0.324 | E87: 45992 | F87: 2024 | G87: =IFERROR(100*($D87*(INDEX('Data_NSA'!$A:$OK,MATCH(G$1,'Data_NSA'!$A:$A,0),MATCH($C87,'Data_NSA'!$1:$1,0))/INDEX('Data_NSA'!$A:$OK,MATCH($E87,'Data_NSA'!$A:$A,0),MATCH($C87,'Data_NSA'!$1:$1,0))))/(100*(INDEX('Data_NSA'!$A:$OK,MATCH(G$1,'Data_NSA'!$A:$A,0),MATCH("CUUR0000SA0",'Data_NSA'!$1:$1,0))/INDEX('Data_NSA'!$A:$OK,MATCH($E87,'Data_NSA'!$A:$A,0),MATCH("CUUR0000SA0",'Data_NSA'!$1:$1,0)))),"") | H87: =IFERROR(100*($D87*(INDEX('Data_NSA'!$A:$OK,MATCH(H$1,'Data_NSA'!$A:$A,0),MATCH($C87,'Data_NSA'!$1:$1,0))/INDEX('Data_NSA'!$A:$OK,MATCH($E87,'Data_NSA'!$A:$A,0),MATCH($C87,'Data_NSA'!$1:$1,0))))/(100*(INDEX('Data_NSA'!$A:$OK,MATCH(H$1,'Data_NSA'!$A:$A,0),MATCH("CUUR0000SA0",'Data_NSA'!$1:$1,0))/INDEX('Data_NSA'!$A:$OK,MATCH($E87,'Data_NSA'!$A:$A,0),MATCH("CUUR0000SA0",'Data_NSA'!$1:$1,0)))),"") | I87: =IFERROR(100*($D87*(INDEX('Data_NSA'!$A:$OK,MATCH(I$1,'Data_NSA'!$A:$A,0),MATCH($C87,'Data_NSA'!$1:$1,0))/INDEX('Data_NSA'!$A:$OK,MATCH($E87,'Data_NSA'!$A:$A,0),MATCH($C87,'Data_NSA'!$1:$1,0))))/(100*(INDEX('Data_NSA'!$A:$OK,MATCH(I$1,'Data_NSA'!$A:$A,0),MATCH("CUUR0000SA0",'Data_NSA'!$1:$1,0))/INDEX('Data_NSA'!$A:$OK,MATCH($E87,'Data_NSA'!$A:$A,0),MATCH("CUUR0000SA0",'Data_NSA'!$1:$1,0)))),"")
A88: SEFN02 | B88: Frozen noncarbonated juices and drinks | C88: CUUR0000SEFN02 | D88: 0.004 | E88: 45992 | F88: 2024 | G88: =IFERROR(100*($D88*(INDEX('Data_NSA'!$A:$OK,MATCH(G$1,'Data_NSA'!$A:$A,0),MATCH($C88,'Data_NSA'!$1:$1,0))/INDEX('Data_NSA'!$A:$OK,MATCH($E88,'Data_NSA'!$A:$A,0),MATCH($C88,'Data_NSA'!$1:$1,0))))/(100*(INDEX('Data_NSA'!$A:$OK,MATCH(G$1,'Data_NSA'!$A:$A,0),MATCH("CUUR0000SA0",'Data_NSA'!$1:$1,0))/INDEX('Data_NSA'!$A:$OK,MATCH($E88,'Data_NSA'!$A:$A,0),MATCH("CUUR0000SA0",'Data_NSA'!$1:$1,0)))),"") | H88: =IFERROR(100*($D88*(INDEX('Data_NSA'!$A:$OK,MATCH(H$1,'Data_NSA'!$A:$A,0),MATCH($C88,'Data_NSA'!$1:$1,0))/INDEX('Data_NSA'!$A:$OK,MATCH($E88,'Data_NSA'!$A:$A,0),MATCH($C88,'Data_NSA'!$1:$1,0))))/(100*(INDEX('Data_NSA'!$A:$OK,MATCH(H$1,'Data_NSA'!$A:$A,0),MATCH("CUUR0000SA0",'Data_NSA'!$1:$1,0))/INDEX('Data_NSA'!$A:$OK,MATCH($E88,'Data_NSA'!$A:$A,0),MATCH("CUUR0000SA0",'Data_NSA'!$1:$1,0)))),"") | I88: =IFERROR(100*($D88*(INDEX('Data_NSA'!$A:$OK,MATCH(I$1,'Data_NSA'!$A:$A,0),MATCH($C88,'Data_NSA'!$1:$1,0))/INDEX('Data_NSA'!$A:$OK,MATCH($E88,'Data_NSA'!$A:$A,0),MATCH($C88,'Data_NSA'!$1:$1,0))))/(100*(INDEX('Data_NSA'!$A:$OK,MATCH(I$1,'Data_NSA'!$A:$A,0),MATCH("CUUR0000SA0",'Data_NSA'!$1:$1,0))/INDEX('Data_NSA'!$A:$OK,MATCH($E88,'Data_NSA'!$A:$A,0),MATCH("CUUR0000SA0",'Data_NSA'!$1:$1,0)))),"")
A89: SEFN03 | B89: Nonfrozen noncarbonated juices and drinks | C89: CUUR0000SEFN03 | D89: 0.346 | E89: 45992 | F89: 2024 | G89: =IFERROR(100*($D89*(INDEX('Data_NSA'!$A:$OK,MATCH(G$1,'Data_NSA'!$A:$A,0),MATCH($C89,'Data_NSA'!$1:$1,0))/INDEX('Data_NSA'!$A:$OK,MATCH($E89,'Data_NSA'!$A:$A,0),MATCH($C89,'Data_NSA'!$1:$1,0))))/(100*(INDEX('Data_NSA'!$A:$OK,MATCH(G$1,'Data_NSA'!$A:$A,0),MATCH("CUUR0000SA0",'Data_NSA'!$1:$1,0))/INDEX('Data_NSA'!$A:$OK,MATCH($E89,'Data_NSA'!$A:$A,0),MATCH("CUUR0000SA0",'Data_NSA'!$1:$1,0)))),"") | H89: =IFERROR(100*($D89*(INDEX('Data_NSA'!$A:$OK,MATCH(H$1,'Data_NSA'!$A:$A,0),MATCH($C89,'Data_NSA'!$1:$1,0))/INDEX('Data_NSA'!$A:$OK,MATCH($E89,'Data_NSA'!$A:$A,0),MATCH($C89,'Data_NSA'!$1:$1,0))))/(100*(INDEX('Data_NSA'!$A:$OK,MATCH(H$1,'Data_NSA'!$A:$A,0),MATCH("CUUR0000SA0",'Data_NSA'!$1:$1,0))/INDEX('Data_NSA'!$A:$OK,MATCH($E89,'Data_NSA'!$A:$A,0),MATCH("CUUR0000SA0",'Data_NSA'!$1:$1,0)))),"") | I89: =IFERROR(100*($D89*(INDEX('Data_NSA'!$A:$OK,MATCH(I$1,'Data_NSA'!$A:$A,0),MATCH($C89,'Data_NSA'!$1:$1,0))/INDEX('Data_NSA'!$A:$OK,MATCH($E89,'Data_NSA'!$A:$A,0),MATCH($C89,'Data_NSA'!$1:$1,0))))/(100*(INDEX('Data_NSA'!$A:$OK,MATCH(I$1,'Data_NSA'!$A:$A,0),MATCH("CUUR0000SA0",'Data_NSA'!$1:$1,0))/INDEX('Data_NSA'!$A:$OK,MATCH($E89,'Data_NSA'!$A:$A,0),MATCH("CUUR0000SA0",'Data_NSA'!$1:$1,0)))),"")
A90: SEFP | B90: Beverage materials including coffee and tea | C90: CUUR0000SEFP | D90: 0.32 | E90: 45992 | F90: 2024 | G90: =IFERROR(100*($D90*(INDEX('Data_NSA'!$A:$OK,MATCH(G$1,'Data_NSA'!$A:$A,0),MATCH($C90,'Data_NSA'!$1:$1,0))/INDEX('Data_NSA'!$A:$OK,MATCH($E90,'Data_NSA'!$A:$A,0),MATCH($C90,'Data_NSA'!$1:$1,0))))/(100*(INDEX('Data_NSA'!$A:$OK,MATCH(G$1,'Data_NSA'!$A:$A,0),MATCH("CUUR0000SA0",'Data_NSA'!$1:$1,0))/INDEX('Data_NSA'!$A:$OK,MATCH($E90,'Data_NSA'!$A:$A,0),MATCH("CUUR0000SA0",'Data_NSA'!$1:$1,0)))),"") | H90: =IFERROR(100*($D90*(INDEX('Data_NSA'!$A:$OK,MATCH(H$1,'Data_NSA'!$A:$A,0),MATCH($C90,'Data_NSA'!$1:$1,0))/INDEX('Data_NSA'!$A:$OK,MATCH($E90,'Data_NSA'!$A:$A,0),MATCH($C90,'Data_NSA'!$1:$1,0))))/(100*(INDEX('Data_NSA'!$A:$OK,MATCH(H$1,'Data_NSA'!$A:$A,0),MATCH("CUUR0000SA0",'Data_NSA'!$1:$1,0))/INDEX('Data_NSA'!$A:$OK,MATCH($E90,'Data_NSA'!$A:$A,0),MATCH("CUUR0000SA0",'Data_NSA'!$1:$1,0)))),"") | I90: =IFERROR(100*($D90*(INDEX('Data_NSA'!$A:$OK,MATCH(I$1,'Data_NSA'!$A:$A,0),MATCH($C90,'Data_NSA'!$1:$1,0))/INDEX('Data_NSA'!$A:$OK,MATCH($E90,'Data_NSA'!$A:$A,0),MATCH($C90,'Data_NSA'!$1:$1,0))))/(100*(INDEX('Data_NSA'!$A:$OK,MATCH(I$1,'Data_NSA'!$A:$A,0),MATCH("CUUR0000SA0",'Data_NSA'!$1:$1,0))/INDEX('Data_NSA'!$A:$OK,MATCH($E90,'Data_NSA'!$A:$A,0),MATCH("CUUR0000SA0",'Data_NSA'!$1:$1,0)))),"")
A91: SEFP01 | B91: Coffee | C91: CUUR0000SEFP01 | D91: 0.221 | E91: 45992 | F91: 2024 | G91: =IFERROR(100*($D91*(INDEX('Data_NSA'!$A:$OK,MATCH(G$1,'Data_NSA'!$A:$A,0),MATCH($C91,'Data_NSA'!$1:$1,0))/INDEX('Data_NSA'!$A:$OK,MATCH($E91,'Data_NSA'!$A:$A,0),MATCH($C91,'Data_NSA'!$1:$1,0))))/(100*(INDEX('Data_NSA'!$A:$OK,MATCH(G$1,'Data_NSA'!$A:$A,0),MATCH("CUUR0000SA0",'Data_NSA'!$1:$1,0))/INDEX('Data_NSA'!$A:$OK,MATCH($E91,'Data_NSA'!$A:$A,0),MATCH("CUUR0000SA0",'Data_NSA'!$1:$1,0)))),"") | H91: =IFERROR(100*($D91*(INDEX('Data_NSA'!$A:$OK,MATCH(H$1,'Data_NSA'!$A:$A,0),MATCH($C91,'Data_NSA'!$1:$1,0))/INDEX('Data_NSA'!$A:$OK,MATCH($E91,'Data_NSA'!$A:$A,0),MATCH($C91,'Data_NSA'!$1:$1,0))))/(100*(INDEX('Data_NSA'!$A:$OK,MATCH(H$1,'Data_NSA'!$A:$A,0),MATCH("CUUR0000SA0",'Data_NSA'!$1:$1,0))/INDEX('Data_NSA'!$A:$OK,MATCH($E91,'Data_NSA'!$A:$A,0),MATCH("CUUR0000SA0",'Data_NSA'!$1:$1,0)))),"") | I91: =IFERROR(100*($D91*(INDEX('Data_NSA'!$A:$OK,MATCH(I$1,'Data_NSA'!$A:$A,0),MATCH($C91,'Data_NSA'!$1:$1,0))/INDEX('Data_NSA'!$A:$OK,MATCH($E91,'Data_NSA'!$A:$A,0),MATCH($C91,'Data_NSA'!$1:$1,0))))/(100*(INDEX('Data_NSA'!$A:$OK,MATCH(I$1,'Data_NSA'!$A:$A,0),MATCH("CUUR0000SA0",'Data_NSA'!$1:$1,0))/INDEX('Data_NSA'!$A:$OK,MATCH($E91,'Data_NSA'!$A:$A,0),MATCH("CUUR0000SA0",'Data_NSA'!$1:$1,0)))),"")
A92: SS17031 | B92: Roasted coffee | C92: CUUR0000SS17031 | E92: 45992 | F92: 2024 | G92: =IFERROR(100*($D92*(INDEX('Data_NSA'!$A:$OK,MATCH(G$1,'Data_NSA'!$A:$A,0),MATCH($C92,'Data_NSA'!$1:$1,0))/INDEX('Data_NSA'!$A:$OK,MATCH($E92,'Data_NSA'!$A:$A,0),MATCH($C92,'Data_NSA'!$1:$1,0))))/(100*(INDEX('Data_NSA'!$A:$OK,MATCH(G$1,'Data_NSA'!$A:$A,0),MATCH("CUUR0000SA0",'Data_NSA'!$1:$1,0))/INDEX('Data_NSA'!$A:$OK,MATCH($E92,'Data_NSA'!$A:$A,0),MATCH("CUUR0000SA0",'Data_NSA'!$1:$1,0)))),"") | H92: =IFERROR(100*($D92*(INDEX('Data_NSA'!$A:$OK,MATCH(H$1,'Data_NSA'!$A:$A,0),MATCH($C92,'Data_NSA'!$1:$1,0))/INDEX('Data_NSA'!$A:$OK,MATCH($E92,'Data_NSA'!$A:$A,0),MATCH($C92,'Data_NSA'!$1:$1,0))))/(100*(INDEX('Data_NSA'!$A:$OK,MATCH(H$1,'Data_NSA'!$A:$A,0),MATCH("CUUR0000SA0",'Data_NSA'!$1:$1,0))/INDEX('Data_NSA'!$A:$OK,MATCH($E92,'Data_NSA'!$A:$A,0),MATCH("CUUR0000SA0",'Data_NSA'!$1:$1,0)))),"") | I92: =IFERROR(100*($D92*(INDEX('Data_NSA'!$A:$OK,MATCH(I$1,'Data_NSA'!$A:$A,0),MATCH($C92,'Data_NSA'!$1:$1,0))/INDEX('Data_NSA'!$A:$OK,MATCH($E92,'Data_NSA'!$A:$A,0),MATCH($C92,'Data_NSA'!$1:$1,0))))/(100*(INDEX('Data_NSA'!$A:$OK,MATCH(I$1,'Data_NSA'!$A:$A,0),MATCH("CUUR0000SA0",'Data_NSA'!$1:$1,0))/INDEX('Data_NSA'!$A:$OK,MATCH($E92,'Data_NSA'!$A:$A,0),MATCH("CUUR0000SA0",'Data_NSA'!$1:$1,0)))),"")
A93: SS17032 | B93: Instant coffee | C93: CUUR0000SS17032 | E93: 45992 | F93: 2024 | G93: =IFERROR(100*($D93*(INDEX('Data_NSA'!$A:$OK,MATCH(G$1,'Data_NSA'!$A:$A,0),MATCH($C93,'Data_NSA'!$1:$1,0))/INDEX('Data_NSA'!$A:$OK,MATCH($E93,'Data_NSA'!$A:$A,0),MATCH($C93,'Data_NSA'!$1:$1,0))))/(100*(INDEX('Data_NSA'!$A:$OK,MATCH(G$1,'Data_NSA'!$A:$A,0),MATCH("CUUR0000SA0",'Data_NSA'!$1:$1,0))/INDEX('Data_NSA'!$A:$OK,MATCH($E93,'Data_NSA'!$A:$A,0),MATCH("CUUR0000SA0",'Data_NSA'!$1:$1,0)))),"") | H93: =IFERROR(100*($D93*(INDEX('Data_NSA'!$A:$OK,MATCH(H$1,'Data_NSA'!$A:$A,0),MATCH($C93,'Data_NSA'!$1:$1,0))/INDEX('Data_NSA'!$A:$OK,MATCH($E93,'Data_NSA'!$A:$A,0),MATCH($C93,'Data_NSA'!$1:$1,0))))/(100*(INDEX('Data_NSA'!$A:$OK,MATCH(H$1,'Data_NSA'!$A:$A,0),MATCH("CUUR0000SA0",'Data_NSA'!$1:$1,0))/INDEX('Data_NSA'!$A:$OK,MATCH($E93,'Data_NSA'!$A:$A,0),MATCH("CUUR0000SA0",'Data_NSA'!$1:$1,0)))),"") | I93: =IFERROR(100*($D93*(INDEX('Data_NSA'!$A:$OK,MATCH(I$1,'Data_NSA'!$A:$A,0),MATCH($C93,'Data_NSA'!$1:$1,0))/INDEX('Data_NSA'!$A:$OK,MATCH($E93,'Data_NSA'!$A:$A,0),MATCH($C93,'Data_NSA'!$1:$1,0))))/(100*(INDEX('Data_NSA'!$A:$OK,MATCH(I$1,'Data_NSA'!$A:$A,0),MATCH("CUUR0000SA0",'Data_NSA'!$1:$1,0))/INDEX('Data_NSA'!$A:$OK,MATCH($E93,'Data_NSA'!$A:$A,0),MATCH("CUUR0000SA0",'Data_NSA'!$1:$1,0)))),"")
A94: SEFP02 | B94: Other beverage materials including tea | C94: CUUR0000SEFP02 | D94: 0.099 | E94: 45992 | F94: 2024 | G94: =IFERROR(100*($D94*(INDEX('Data_NSA'!$A:$OK,MATCH(G$1,'Data_NSA'!$A:$A,0),MATCH($C94,'Data_NSA'!$1:$1,0))/INDEX('Data_NSA'!$A:$OK,MATCH($E94,'Data_NSA'!$A:$A,0),MATCH($C94,'Data_NSA'!$1:$1,0))))/(100*(INDEX('Data_NSA'!$A:$OK,MATCH(G$1,'Data_NSA'!$A:$A,0),MATCH("CUUR0000SA0",'Data_NSA'!$1:$1,0))/INDEX('Data_NSA'!$A:$OK,MATCH($E94,'Data_NSA'!$A:$A,0),MATCH("CUUR0000SA0",'Data_NSA'!$1:$1,0)))),"") | H94: =IFERROR(100*($D94*(INDEX('Data_NSA'!$A:$OK,MATCH(H$1,'Data_NSA'!$A:$A,0),MATCH($C94,'Data_NSA'!$1:$1,0))/INDEX('Data_NSA'!$A:$OK,MATCH($E94,'Data_NSA'!$A:$A,0),MATCH($C94,'Data_NSA'!$1:$1,0))))/(100*(INDEX('Data_NSA'!$A:$OK,MATCH(H$1,'Data_NSA'!$A:$A,0),MATCH("CUUR0000SA0",'Data_NSA'!$1:$1,0))/INDEX('Data_NSA'!$A:$OK,MATCH($E94,'Data_NSA'!$A:$A,0),MATCH("CUUR0000SA0",'Data_NSA'!$1:$1,0)))),"") | I94: =IFERROR(100*($D94*(INDEX('Data_NSA'!$A:$OK,MATCH(I$1,'Data_NSA'!$A:$A,0),MATCH($C94,'Data_NSA'!$1:$1,0))/INDEX('Data_NSA'!$A:$OK,MATCH($E94,'Data_NSA'!$A:$A,0),MATCH($C94,'Data_NSA'!$1:$1,0))))/(100*(INDEX('Data_NSA'!$A:$OK,MATCH(I$1,'Data_NSA'!$A:$A,0),MATCH("CUUR0000SA0",'Data_NSA'!$1:$1,0))/INDEX('Data_NSA'!$A:$OK,MATCH($E94,'Data_NSA'!$A:$A,0),MATCH("CUUR0000SA0",'Data_NSA'!$1:$1,0)))),"")
A95: SAF115 | B95: Other food at home | C95: CUUR0000SAF115 | D95: 2.273 | E95: 45992 | F95: 2024 | G95: =IFERROR(100*($D95*(INDEX('Data_NSA'!$A:$OK,MATCH(G$1,'Data_NSA'!$A:$A,0),MATCH($C95,'Data_NSA'!$1:$1,0))/INDEX('Data_NSA'!$A:$OK,MATCH($E95,'Data_NSA'!$A:$A,0),MATCH($C95,'Data_NSA'!$1:$1,0))))/(100*(INDEX('Data_NSA'!$A:$OK,MATCH(G$1,'Data_NSA'!$A:$A,0),MATCH("CUUR0000SA0",'Data_NSA'!$1:$1,0))/INDEX('Data_NSA'!$A:$OK,MATCH($E95,'Data_NSA'!$A:$A,0),MATCH("CUUR0000SA0",'Data_NSA'!$1:$1,0)))),"") | H95: =IFERROR(100*($D95*(INDEX('Data_NSA'!$A:$OK,MATCH(H$1,'Data_NSA'!$A:$A,0),MATCH($C95,'Data_NSA'!$1:$1,0))/INDEX('Data_NSA'!$A:$OK,MATCH($E95,'Data_NSA'!$A:$A,0),MATCH($C95,'Data_NSA'!$1:$1,0))))/(100*(INDEX('Data_NSA'!$A:$OK,MATCH(H$1,'Data_NSA'!$A:$A,0),MATCH("CUUR0000SA0",'Data_NSA'!$1:$1,0))/INDEX('Data_NSA'!$A:$OK,MATCH($E95,'Data_NSA'!$A:$A,0),MATCH("CUUR0000SA0",'Data_NSA'!$1:$1,0)))),"") | I95: =IFERROR(100*($D95*(INDEX('Data_NSA'!$A:$OK,MATCH(I$1,'Data_NSA'!$A:$A,0),MATCH($C95,'Data_NSA'!$1:$1,0))/INDEX('Data_NSA'!$A:$OK,MATCH($E95,'Data_NSA'!$A:$A,0),MATCH($C95,'Data_NSA'!$1:$1,0))))/(100*(INDEX('Data_NSA'!$A:$OK,MATCH(I$1,'Data_NSA'!$A:$A,0),MATCH("CUUR0000SA0",'Data_NSA'!$1:$1,0))/INDEX('Data_NSA'!$A:$OK,MATCH($E95,'Data_NSA'!$A:$A,0),MATCH("CUUR0000SA0",'Data_NSA'!$1:$1,0)))),"")
A96: SEFR | B96: Sugar and sweets | C96: CUUR0000SEFR | D96: 0.328 | E96: 45992 | F96: 2024 | G96: =IFERROR(100*($D96*(INDEX('Data_NSA'!$A:$OK,MATCH(G$1,'Data_NSA'!$A:$A,0),MATCH($C96,'Data_NSA'!$1:$1,0))/INDEX('Data_NSA'!$A:$OK,MATCH($E96,'Data_NSA'!$A:$A,0),MATCH($C96,'Data_NSA'!$1:$1,0))))/(100*(INDEX('Data_NSA'!$A:$OK,MATCH(G$1,'Data_NSA'!$A:$A,0),MATCH("CUUR0000SA0",'Data_NSA'!$1:$1,0))/INDEX('Data_NSA'!$A:$OK,MATCH($E96,'Data_NSA'!$A:$A,0),MATCH("CUUR0000SA0",'Data_NSA'!$1:$1,0)))),"") | H96: =IFERROR(100*($D96*(INDEX('Data_NSA'!$A:$OK,MATCH(H$1,'Data_NSA'!$A:$A,0),MATCH($C96,'Data_NSA'!$1:$1,0))/INDEX('Data_NSA'!$A:$OK,MATCH($E96,'Data_NSA'!$A:$A,0),MATCH($C96,'Data_NSA'!$1:$1,0))))/(100*(INDEX('Data_NSA'!$A:$OK,MATCH(H$1,'Data_NSA'!$A:$A,0),MATCH("CUUR0000SA0",'Data_NSA'!$1:$1,0))/INDEX('Data_NSA'!$A:$OK,MATCH($E96,'Data_NSA'!$A:$A,0),MATCH("CUUR0000SA0",'Data_NSA'!$1:$1,0)))),"") | I96: =IFERROR(100*($D96*(INDEX('Data_NSA'!$A:$OK,MATCH(I$1,'Data_NSA'!$A:$A,0),MATCH($C96,'Data_NSA'!$1:$1,0))/INDEX('Data_NSA'!$A:$OK,MATCH($E96,'Data_NSA'!$A:$A,0),MATCH($C96,'Data_NSA'!$1:$1,0))))/(100*(INDEX('Data_NSA'!$A:$OK,MATCH(I$1,'Data_NSA'!$A:$A,0),MATCH("CUUR0000SA0",'Data_NSA'!$1:$1,0))/INDEX('Data_NSA'!$A:$OK,MATCH($E96,'Data_NSA'!$A:$A,0),MATCH("CUUR0000SA0",'Data_NSA'!$1:$1,0)))),"")
A97: SEFR01 | B97: Sugar and sugar substitutes | C97: CUUR0000SEFR01 | D97: 0.032 | E97: 45992 | F97: 2024 | G97: =IFERROR(100*($D97*(INDEX('Data_NSA'!$A:$OK,MATCH(G$1,'Data_NSA'!$A:$A,0),MATCH($C97,'Data_NSA'!$1:$1,0))/INDEX('Data_NSA'!$A:$OK,MATCH($E97,'Data_NSA'!$A:$A,0),MATCH($C97,'Data_NSA'!$1:$1,0))))/(100*(INDEX('Data_NSA'!$A:$OK,MATCH(G$1,'Data_NSA'!$A:$A,0),MATCH("CUUR0000SA0",'Data_NSA'!$1:$1,0))/INDEX('Data_NSA'!$A:$OK,MATCH($E97,'Data_NSA'!$A:$A,0),MATCH("CUUR0000SA0",'Data_NSA'!$1:$1,0)))),"") | H97: =IFERROR(100*($D97*(INDEX('Data_NSA'!$A:$OK,MATCH(H$1,'Data_NSA'!$A:$A,0),MATCH($C97,'Data_NSA'!$1:$1,0))/INDEX('Data_NSA'!$A:$OK,MATCH($E97,'Data_NSA'!$A:$A,0),MATCH($C97,'Data_NSA'!$1:$1,0))))/(100*(INDEX('Data_NSA'!$A:$OK,MATCH(H$1,'Data_NSA'!$A:$A,0),MATCH("CUUR0000SA0",'Data_NSA'!$1:$1,0))/INDEX('Data_NSA'!$A:$OK,MATCH($E97,'Data_NSA'!$A:$A,0),MATCH("CUUR0000SA0",'Data_NSA'!$1:$1,0)))),"") | I97: =IFERROR(100*($D97*(INDEX('Data_NSA'!$A:$OK,MATCH(I$1,'Data_NSA'!$A:$A,0),MATCH($C97,'Data_NSA'!$1:$1,0))/INDEX('Data_NSA'!$A:$OK,MATCH($E97,'Data_NSA'!$A:$A,0),MATCH($C97,'Data_NSA'!$1:$1,0))))/(100*(INDEX('Data_NSA'!$A:$OK,MATCH(I$1,'Data_NSA'!$A:$A,0),MATCH("CUUR0000SA0",'Data_NSA'!$1:$1,0))/INDEX('Data_NSA'!$A:$OK,MATCH($E97,'Data_NSA'!$A:$A,0),MATCH("CUUR0000SA0",'Data_NSA'!$1:$1,0)))),"")
A98: SEFR02 | B98: Candy and chewing gum | C98: CUUR0000SEFR02 | D98: 0.241 | E98: 45992 | F98: 2024 | G98: =IFERROR(100*($D98*(INDEX('Data_NSA'!$A:$OK,MATCH(G$1,'Data_NSA'!$A:$A,0),MATCH($C98,'Data_NSA'!$1:$1,0))/INDEX('Data_NSA'!$A:$OK,MATCH($E98,'Data_NSA'!$A:$A,0),MATCH($C98,'Data_NSA'!$1:$1,0))))/(100*(INDEX('Data_NSA'!$A:$OK,MATCH(G$1,'Data_NSA'!$A:$A,0),MATCH("CUUR0000SA0",'Data_NSA'!$1:$1,0))/INDEX('Data_NSA'!$A:$OK,MATCH($E98,'Data_NSA'!$A:$A,0),MATCH("CUUR0000SA0",'Data_NSA'!$1:$1,0)))),"") | H98: =IFERROR(100*($D98*(INDEX('Data_NSA'!$A:$OK,MATCH(H$1,'Data_NSA'!$A:$A,0),MATCH($C98,'Data_NSA'!$1:$1,0))/INDEX('Data_NSA'!$A:$OK,MATCH($E98,'Data_NSA'!$A:$A,0),MATCH($C98,'Data_NSA'!$1:$1,0))))/(100*(INDEX('Data_NSA'!$A:$OK,MATCH(H$1,'Data_NSA'!$A:$A,0),MATCH("CUUR0000SA0",'Data_NSA'!$1:$1,0))/INDEX('Data_NSA'!$A:$OK,MATCH($E98,'Data_NSA'!$A:$A,0),MATCH("CUUR0000SA0",'Data_NSA'!$1:$1,0)))),"") | I98: =IFERROR(100*($D98*(INDEX('Data_NSA'!$A:$OK,MATCH(I$1,'Data_NSA'!$A:$A,0),MATCH($C98,'Data_NSA'!$1:$1,0))/INDEX('Data_NSA'!$A:$OK,MATCH($E98,'Data_NSA'!$A:$A,0),MATCH($C98,'Data_NSA'!$1:$1,0))))/(100*(INDEX('Data_NSA'!$A:$OK,MATCH(I$1,'Data_NSA'!$A:$A,0),MATCH("CUUR0000SA0",'Data_NSA'!$1:$1,0))/INDEX('Data_NSA'!$A:$OK,MATCH($E98,'Data_NSA'!$A:$A,0),MATCH("CUUR0000SA0",'Data_NSA'!$1:$1,0)))),"")
A99: SEFR03 | B99: Other sweets | C99: CUUR0000SEFR03 | D99: 0.055 | E99: 45992 | F99: 2024 | G99: =IFERROR(100*($D99*(INDEX('Data_NSA'!$A:$OK,MATCH(G$1,'Data_NSA'!$A:$A,0),MATCH($C99,'Data_NSA'!$1:$1,0))/INDEX('Data_NSA'!$A:$OK,MATCH($E99,'Data_NSA'!$A:$A,0),MATCH($C99,'Data_NSA'!$1:$1,0))))/(100*(INDEX('Data_NSA'!$A:$OK,MATCH(G$1,'Data_NSA'!$A:$A,0),MATCH("CUUR0000SA0",'Data_NSA'!$1:$1,0))/INDEX('Data_NSA'!$A:$OK,MATCH($E99,'Data_NSA'!$A:$A,0),MATCH("CUUR0000SA0",'Data_NSA'!$1:$1,0)))),"") | H99: =IFERROR(100*($D99*(INDEX('Data_NSA'!$A:$OK,MATCH(H$1,'Data_NSA'!$A:$A,0),MATCH($C99,'Data_NSA'!$1:$1,0))/INDEX('Data_NSA'!$A:$OK,MATCH($E99,'Data_NSA'!$A:$A,0),MATCH($C99,'Data_NSA'!$1:$1,0))))/(100*(INDEX('Data_NSA'!$A:$OK,MATCH(H$1,'Data_NSA'!$A:$A,0),MATCH("CUUR0000SA0",'Data_NSA'!$1:$1,0))/INDEX('Data_NSA'!$A:$OK,MATCH($E99,'Data_NSA'!$A:$A,0),MATCH("CUUR0000SA0",'Data_NSA'!$1:$1,0)))),"") | I99: =IFERROR(100*($D99*(INDEX('Data_NSA'!$A:$OK,MATCH(I$1,'Data_NSA'!$A:$A,0),MATCH($C99,'Data_NSA'!$1:$1,0))/INDEX('Data_NSA'!$A:$OK,MATCH($E99,'Data_NSA'!$A:$A,0),MATCH($C99,'Data_NSA'!$1:$1,0))))/(100*(INDEX('Data_NSA'!$A:$OK,MATCH(I$1,'Data_NSA'!$A:$A,0),MATCH("CUUR0000SA0",'Data_NSA'!$1:$1,0))/INDEX('Data_NSA'!$A:$OK,MATCH($E99,'Data_NSA'!$A:$A,0),MATCH("CUUR0000SA0",'Data_NSA'!$1:$1,0)))),"")
A100: SEFS | B100: Fats and oils | C100: CUUR0000SEFS | D100: 0.231 | E100: 45992 | F100: 2024 | G100: =IFERROR(100*($D100*(INDEX('Data_NSA'!$A:$OK,MATCH(G$1,'Data_NSA'!$A:$A,0),MATCH($C100,'Data_NSA'!$1:$1,0))/INDEX('Data_NSA'!$A:$OK,MATCH($E100,'Data_NSA'!$A:$A,0),MATCH($C100,'Data_NSA'!$1:$1,0))))/(100*(INDEX('Data_NSA'!$A:$OK,MATCH(G$1,'Data_NSA'!$A:$A,0),MATCH("CUUR0000SA0",'Data_NSA'!$1:$1,0))/INDEX('Data_NSA'!$A:$OK,MATCH($E100,'Data_NSA'!$A:$A,0),MATCH("CUUR0000SA0",'Data_NSA'!$1:$1,0)))),"") | H100: =IFERROR(100*($D100*(INDEX('Data_NSA'!$A:$OK,MATCH(H$1,'Data_NSA'!$A:$A,0),MATCH($C100,'Data_NSA'!$1:$1,0))/INDEX('Data_NSA'!$A:$OK,MATCH($E100,'Data_NSA'!$A:$A,0),MATCH($C100,'Data_NSA'!$1:$1,0))))/(100*(INDEX('Data_NSA'!$A:$OK,MATCH(H$1,'Data_NSA'!$A:$A,0),MATCH("CUUR0000SA0",'Data_NSA'!$1:$1,0))/INDEX('Data_NSA'!$A:$OK,MATCH($E100,'Data_NSA'!$A:$A,0),MATCH("CUUR0000SA0",'Data_NSA'!$1:$1,0)))),"") | I100: =IFERROR(100*($D100*(INDEX('Data_NSA'!$A:$OK,MATCH(I$1,'Data_NSA'!$A:$A,0),MATCH($C100,'Data_NSA'!$1:$1,0))/INDEX('Data_NSA'!$A:$OK,MATCH($E100,'Data_NSA'!$A:$A,0),MATCH($C100,'Data_NSA'!$1:$1,0))))/(100*(INDEX('Data_NSA'!$A:$OK,MATCH(I$1,'Data_NSA'!$A:$A,0),MATCH("CUUR0000SA0",'Data_NSA'!$1:$1,0))/INDEX('Data_NSA'!$A:$OK,MATCH($E100,'Data_NSA'!$A:$A,0),MATCH("CUUR0000SA0",'Data_NSA'!$1:$1,0)))),"")
...

Sheet Latest_3M
A1: Latest 3 Published Months
I2: 46204 | O2: 46235 | U2: 46266
A3: item_code | B3: component | C3: parent | D3: series_nsa | E3: series_sa | F3: formula | G3: collection | H3: Dec RI % | I3: NSA index | J3: SA index | K3: SA m/m % | L3: NSA y/y % | M3: RI weight | N3: SA contrib pp | O3: NSA index | P3: SA index | Q3: SA m/m % | R3: NSA y/y % | S3: RI weight | T3: SA contrib pp | U3: NSA index | V3: SA index | W3: SA m/m % | X3: NSA y/y % | Y3: RI weight | Z3: SA contrib pp
A4: SA0 | B4: All items | D4: CUUR0000SA0 | E4: CUSR0000SA0 | F4: aggregate | G4: aggregate | H4: =IFERROR(INDEX(Weights!$D:$D,MATCH($A4,Weights!$A:$A,0)),"") | I4: =IFERROR(INDEX('Data_NSA'!$A:$OK,MATCH(I$2,'Data_NSA'!$A:$A,0),MATCH($D4,'Data_NSA'!$1:$1,0)),"") | J4: =IF($E4="","",IFERROR(INDEX('Data_SA'!$A:$LO,MATCH(I$2,'Data_SA'!$A:$A,0),MATCH($E4,'Data_SA'!$1:$1,0)),"")) | K4: =IF($E4="","",IFERROR(INDEX('Data_SA'!$A:$LO,MATCH(I$2,'Data_SA'!$A:$A,0),MATCH($E4,'Data_SA'!$1:$1,0))/INDEX('Data_SA'!$A:$LO,MATCH(EDATE(I$2,-1),'Data_SA'!$A:$A,0),MATCH($E4,'Data_SA'!$1:$1,0))-1,"")) | L4: =IFERROR(INDEX('Data_NSA'!$A:$OK,MATCH(I$2,'Data_NSA'!$A:$A,0),MATCH($D4,'Data_NSA'!$1:$1,0))/INDEX('Data_NSA'!$A:$OK,MATCH(EDATE(I$2,-12),'Data_NSA'!$A:$A,0),MATCH($D4,'Data_NSA'!$1:$1,0))-1,"") | M4: =IFERROR(INDEX('Weights'!$G:$I,MATCH($A4,'Weights'!$A:$A,0),MATCH(I$2,'Weights'!$G$1:$I$1,0)),"") | N4: =IF($E4="","",IFERROR(100*(INDEX('Weights'!$D:$D,MATCH($A4,'Weights'!$A:$A,0))*(INDEX('Data_NSA'!$A:$OK,MATCH(EDATE(I$2,-1),'Data_NSA'!$A:$A,0),MATCH($D4,'Data_NSA'!$1:$1,0))/INDEX('Data_NSA'!$A:$OK,MATCH(INDEX('Weights'!$E:$E,MATCH($A4,'Weights'!$A:$A,0)),'Data_NSA'!$A:$A,0),MATCH($D4,'Data_NSA'!$1:$1,0))))/(100*(INDEX('Data_NSA'!$A:$OK,MATCH(EDATE(I$2,-1),'Data_NSA'!$A:$A,0),MATCH("CUUR0000SA0",'Data_NSA'!$1:$1,0))/INDEX('Data_NSA'!$A:$OK,MATCH(INDEX('Weights'!$E:$E,MATCH($A4,'Weights'!$A:$A,0)),'Data_NSA'!$A:$A,0),MATCH("CUUR0000SA0",'Data_NSA'!$1:$1,0))))*(INDEX('Data_SA'!$A:$LO,MATCH(I$2,'Data_SA'!$A:$A,0),MATCH($E4,'Data_SA'!$1:$1,0))/INDEX('Data_SA'!$A:$LO,MATCH(EDATE(I$2,-1),'Data_SA'!$A:$A,0),MATCH($E4,'Data_SA'!$1:$1,0))-1),"")) | O4: =IFERROR(INDEX('Data_NSA'!$A:$OK,MATCH(O$2,'Data_NSA'!$A:$A,0),MATCH($D4,'Data_NSA'!$1:$1,0)),"") | P4: =IF($E4="","",IFERROR(INDEX('Data_SA'!$A:$LO,MATCH(O$2,'Data_SA'!$A:$A,0),MATCH($E4,'Data_SA'!$1:$1,0)),"")) | Q4: =IF($E4="","",IFERROR(INDEX('Data_SA'!$A:$LO,MATCH(O$2,'Data_SA'!$A:$A,0),MATCH($E4,'Data_SA'!$1:$1,0))/INDEX('Data_SA'!$A:$LO,MATCH(EDATE(O$2,-1),'Data_SA'!$A:$A,0),MATCH($E4,'Data_SA'!$1:$1,0))-1,"")) | R4: =IFERROR(INDEX('Data_NSA'!$A:$OK,MATCH(O$2,'Data_NSA'!$A:$A,0),MATCH($D4,'Data_NSA'!$1:$1,0))/INDEX('Data_NSA'!$A:$OK,MATCH(EDATE(O$2,-12),'Data_NSA'!$A:$A,0),MATCH($D4,'Data_NSA'!$1:$1,0))-1,"") | S4: =IFERROR(INDEX('Weights'!$G:$I,MATCH($A4,'Weights'!$A:$A,0),MATCH(O$2,'Weights'!$G$1:$I$1,0)),"") | T4: =IF($E4="","",IFERROR(100*(INDEX('Weights'!$D:$D,MATCH($A4,'Weights'!$A:$A,0))*(INDEX('Data_NSA'!$A:$OK,MATCH(EDATE(O$2,-1),'Data_NSA'!$A:$A,0),MATCH($D4,'Data_NSA'!$1:$1,0))/INDEX('Data_NSA'!$A:$OK,MATCH(INDEX('Weights'!$E:$E,MATCH($A4,'Weights'!$A:$A,0)),'Data_NSA'!$A:$A,0),MATCH($D4,'Data_NSA'!$1:$1,0))))/(100*(INDEX('Data_NSA'!$A:$OK,MATCH(EDATE(O$2,-1),'Data_NSA'!$A:$A,0),MATCH("CUUR0000SA0",'Data_NSA'!$1:$1,0))/INDEX('Data_NSA'!$A:$OK,MATCH(INDEX('Weights'!$E:$E,MATCH($A4,'Weights'!$A:$A,0)),'Data_NSA'!$A:$A,0),MATCH("CUUR0000SA0",'Data_NSA'!$1:$1,0))))*(INDEX('Data_SA'!$A:$LO,MATCH(O$2,'Data_SA'!$A:$A,0),MATCH($E4,'Data_SA'!$1:$1,0))/INDEX('Data_SA'!$A:$LO,MATCH(EDATE(O$2,-1),'Data_SA'!$A:$A,0),MATCH($E4,'Data_SA'!$1:$1,0))-1),"")) | U4: =IFERROR(INDEX('Data_NSA'!$A:$OK,MATCH(U$2,'Data_NSA'!$A:$A,0),MATCH($D4,'Data_NSA'!$1:$1,0)),"") | V4: =IF($E4="","",IFERROR(INDEX('Data_SA'!$A:$LO,MATCH(U$2,'Data_SA'!$A:$A,0),MATCH($E4,'Data_SA'!$1:$1,0)),"")) | W4: =IF($E4="","",IFERROR(INDEX('Data_SA'!$A:$LO,MATCH(U$2,'Data_SA'!$A:$A,0),MATCH($E4,'Data_SA'!$1:$1,0))/INDEX('Data_SA'!$A:$LO,MATCH(EDATE(U$2,-1),'Data_SA'!$A:$A,0),MATCH($E4,'Data_SA'!$1:$1,0))-1,"")) | X4: =IFERROR(INDEX('Data_NSA'!$A:$OK,MATCH(U$2,'Data_NSA'!$A:$A,0),MATCH($D4,'Data_NSA'!$1:$1,0))/INDEX('Data_NSA'!$A:$OK,MATCH(EDATE(U$2,-12),'Data_NSA'!$A:$A,0),MATCH($D4,'Data_NSA'!$1:$1,0))-1,"") | Y4: =IFERROR(INDEX('Weights'!$G:$I,MATCH($A4,'Weights'!$A:$A,0),MATCH(U$2,'Weights'!$G$1:$I$1,0)),"") | Z4: =IF($E4="","",IFERROR(100*(INDEX('Weights'!$D:$D,MATCH($A4,'Weights'!$A:$A,0))*(INDEX('Data_NSA'!$A:$OK,MATCH(EDATE(U$2,-1),'Data_NSA'!$A:$A,0),MATCH($D4,'Data_NSA'!$1:$1,0))/INDEX('Data_NSA'!$A:$OK,MATCH(INDEX('Weights'!$E:$E,MATCH($A4,'Weights'!$A:$A,0)),'Data_NSA'!$A:$A,0),MATCH($D4,'Data_NSA'!$1:$1,0))))/(100*(INDEX('Data_NSA'!$A:$OK,MATCH(EDATE(U$2,-1),'Data_NSA'!$A:$A,0),MATCH("CUUR0000SA0",'Data_NSA'!$1:$1,0))/INDEX('Data_NSA'!$A:$OK,MATCH(INDEX('Weights'!$E:$E,MATCH($A4,'Weights'!$A:$A,0)),'Data_NSA'!$A:$A,0),MATCH("CUUR0000SA0",'Data_NSA'!$1:$1,0))))*(INDEX('Data_SA'!$A:$LO,MATCH(U$2,'Data_SA'!$A:$A,0),MATCH($E4,'Data_SA'!$1:$1,0))/INDEX('Data_SA'!$A:$LO,MATCH(EDATE(U$2,-1),'Data_SA'!$A:$A,0),MATCH($E4,'Data_SA'!$1:$1,0))-1),""))
A5: AA0 | B5: All items - old base | C5: SA0 | D5: CUUR0000AA0 | F5: GM | G5: monthly in New York/Los Angeles/Chicago; often bimonthly elsewhere | H5: =IFERROR(INDEX(Weights!$D:$D,MATCH($A5,Weights!$A:$A,0)),"") | I5: =IFERROR(INDEX('Data_NSA'!$A:$OK,MATCH(I$2,'Data_NSA'!$A:$A,0),MATCH($D5,'Data_NSA'!$1:$1,0)),"") | J5: =IF($E5="","",IFERROR(INDEX('Data_SA'!$A:$LO,MATCH(I$2,'Data_SA'!$A:$A,0),MATCH($E5,'Data_SA'!$1:$1,0)),"")) | K5: =IF($E5="","",IFERROR(INDEX('Data_SA'!$A:$LO,MATCH(I$2,'Data_SA'!$A:$A,0),MATCH($E5,'Data_SA'!$1:$1,0))/INDEX('Data_SA'!$A:$LO,MATCH(EDATE(I$2,-1),'Data_SA'!$A:$A,0),MATCH($E5,'Data_SA'!$1:$1,0))-1,"")) | L5: =IFERROR(INDEX('Data_NSA'!$A:$OK,MATCH(I$2,'Data_NSA'!$A:$A,0),MATCH($D5,'Data_NSA'!$1:$1,0))/INDEX('Data_NSA'!$A:$OK,MATCH(EDATE(I$2,-12),'Data_NSA'!$A:$A,0),MATCH($D5,'Data_NSA'!$1:$1,0))-1,"") | M5: =IFERROR(INDEX('Weights'!$G:$I,MATCH($A5,'Weights'!$A:$A,0),MATCH(I$2,'Weights'!$G$1:$I$1,0)),"") | N5: =IF($E5="","",IFERROR(100*(INDEX('Weights'!$D:$D,MATCH($A5,'Weights'!$A:$A,0))*(INDEX('Data_NSA'!$A:$OK,MATCH(EDATE(I$2,-1),'Data_NSA'!$A:$A,0),MATCH($D5,'Data_NSA'!$1:$1,0))/INDEX('Data_NSA'!$A:$OK,MATCH(INDEX('Weights'!$E:$E,MATCH($A5,'Weights'!$A:$A,0)),'Data_NSA'!$A:$A,0),MATCH($D5,'Data_NSA'!$1:$1,0))))/(100*(INDEX('Data_NSA'!$A:$OK,MATCH(EDATE(I$2,-1),'Data_NSA'!$A:$A,0),MATCH("CUUR0000SA0",'Data_NSA'!$1:$1,0))/INDEX('Data_NSA'!$A:$OK,MATCH(INDEX('Weights'!$E:$E,MATCH($A5,'Weights'!$A:$A,0)),'Data_NSA'!$A:$A,0),MATCH("CUUR0000SA0",'Data_NSA'!$1:$1,0))))*(INDEX('Data_SA'!$A:$LO,MATCH(I$2,'Data_SA'!$A:$A,0),MATCH($E5,'Data_SA'!$1:$1,0))/INDEX('Data_SA'!$A:$LO,MATCH(EDATE(I$2,-1),'Data_SA'!$A:$A,0),MATCH($E5,'Data_SA'!$1:$1,0))-1),"")) | O5: =IFERROR(INDEX('Data_NSA'!$A:$OK,MATCH(O$2,'Data_NSA'!$A:$A,0),MATCH($D5,'Data_NSA'!$1:$1,0)),"") | P5: =IF($E5="","",IFERROR(INDEX('Data_SA'!$A:$LO,MATCH(O$2,'Data_SA'!$A:$A,0),MATCH($E5,'Data_SA'!$1:$1,0)),"")) | Q5: =IF($E5="","",IFERROR(INDEX('Data_SA'!$A:$LO,MATCH(O$2,'Data_SA'!$A:$A,0),MATCH($E5,'Data_SA'!$1:$1,0))/INDEX('Data_SA'!$A:$LO,MATCH(EDATE(O$2,-1),'Data_SA'!$A:$A,0),MATCH($E5,'Data_SA'!$1:$1,0))-1,"")) | R5: =IFERROR(INDEX('Data_NSA'!$A:$OK,MATCH(O$2,'Data_NSA'!$A:$A,0),MATCH($D5,'Data_NSA'!$1:$1,0))/INDEX('Data_NSA'!$A:$OK,MATCH(EDATE(O$2,-12),'Data_NSA'!$A:$A,0),MATCH($D5,'Data_NSA'!$1:$1,0))-1,"") | S5: =IFERROR(INDEX('Weights'!$G:$I,MATCH($A5,'Weights'!$A:$A,0),MATCH(O$2,'Weights'!$G$1:$I$1,0)),"") | T5: =IF($E5="","",IFERROR(100*(INDEX('Weights'!$D:$D,MATCH($A5,'Weights'!$A:$A,0))*(INDEX('Data_NSA'!$A:$OK,MATCH(EDATE(O$2,-1),'Data_NSA'!$A:$A,0),MATCH($D5,'Data_NSA'!$1:$1,0))/INDEX('Data_NSA'!$A:$OK,MATCH(INDEX('Weights'!$E:$E,MATCH($A5,'Weights'!$A:$A,0)),'Data_NSA'!$A:$A,0),MATCH($D5,'Data_NSA'!$1:$1,0))))/(100*(INDEX('Data_NSA'!$A:$OK,MATCH(EDATE(O$2,-1),'Data_NSA'!$A:$A,0),MATCH("CUUR0000SA0",'Data_NSA'!$1:$1,0))/INDEX('Data_NSA'!$A:$OK,MATCH(INDEX('Weights'!$E:$E,MATCH($A5,'Weights'!$A:$A,0)),'Data_NSA'!$A:$A,0),MATCH("CUUR0000SA0",'Data_NSA'!$1:$1,0))))*(INDEX('Data_SA'!$A:$LO,MATCH(O$2,'Data_SA'!$A:$A,0),MATCH($E5,'Data_SA'!$1:$1,0))/INDEX('Data_SA'!$A:$LO,MATCH(EDATE(O$2,-1),'Data_SA'!$A:$A,0),MATCH($E5,'Data_SA'!$1:$1,0))-1),"")) | U5: =IFERROR(INDEX('Data_NSA'!$A:$OK,MATCH(U$2,'Data_NSA'!$A:$A,0),MATCH($D5,'Data_NSA'!$1:$1,0)),"") | V5: =IF($E5="","",IFERROR(INDEX('Data_SA'!$A:$LO,MATCH(U$2,'Data_SA'!$A:$A,0),MATCH($E5,'Data_SA'!$1:$1,0)),"")) | W5: =IF($E5="","",IFERROR(INDEX('Data_SA'!$A:$LO,MATCH(U$2,'Data_SA'!$A:$A,0),MATCH($E5,'Data_SA'!$1:$1,0))/INDEX('Data_SA'!$A:$LO,MATCH(EDATE(U$2,-1),'Data_SA'!$A:$A,0),MATCH($E5,'Data_SA'!$1:$1,0))-1,"")) | X5: =IFERROR(INDEX('Data_NSA'!$A:$OK,MATCH(U$2,'Data_NSA'!$A:$A,0),MATCH($D5,'Data_NSA'!$1:$1,0))/INDEX('Data_NSA'!$A:$OK,MATCH(EDATE(U$2,-12),'Data_NSA'!$A:$A,0),MATCH($D5,'Data_NSA'!$1:$1,0))-1,"") | Y5: =IFERROR(INDEX('Weights'!$G:$I,MATCH($A5,'Weights'!$A:$A,0),MATCH(U$2,'Weights'!$G$1:$I$1,0)),"") | Z5: =IF($E5="","",IFERROR(100*(INDEX('Weights'!$D:$D,MATCH($A5,'Weights'!$A:$A,0))*(INDEX('Data_NSA'!$A:$OK,MATCH(EDATE(U$2,-1),'Data_NSA'!$A:$A,0),MATCH($D5,'Data_NSA'!$1:$1,0))/INDEX('Data_NSA'!$A:$OK,MATCH(INDEX('Weights'!$E:$E,MATCH($A5,'Weights'!$A:$A,0)),'Data_NSA'!$A:$A,0),MATCH($D5,'Data_NSA'!$1:$1,0))))/(100*(INDEX('Data_NSA'!$A:$OK,MATCH(EDATE(U$2,-1),'Data_NSA'!$A:$A,0),MATCH("CUUR0000SA0",'Data_NSA'!$1:$1,0))/INDEX('Data_NSA'!$A:$OK,MATCH(INDEX('Weights'!$E:$E,MATCH($A5,'Weights'!$A:$A,0)),'Data_NSA'!$A:$A,0),MATCH("CUUR0000SA0",'Data_NSA'!$1:$1,0))))*(INDEX('Data_SA'!$A:$LO,MATCH(U$2,'Data_SA'!$A:$A,0),MATCH($E5,'Data_SA'!$1:$1,0))/INDEX('Data_SA'!$A:$LO,MATCH(EDATE(U$2,-1),'Data_SA'!$A:$A,0),MATCH($E5,'Data_SA'!$1:$1,0))-1),""))
A6: SAF | B6: Food and beverages | C6: SA0 | D6: CUUR0000SAF | E6: CUSR0000SAF | F6: aggregate | G6: aggregate | H6: =IFERROR(INDEX(Weights!$D:$D,MATCH($A6,Weights!$A:$A,0)),"") | I6: =IFERROR(INDEX('Data_NSA'!$A:$OK,MATCH(I$2,'Data_NSA'!$A:$A,0),MATCH($D6,'Data_NSA'!$1:$1,0)),"") | J6: =IF($E6="","",IFERROR(INDEX('Data_SA'!$A:$LO,MATCH(I$2,'Data_SA'!$A:$A,0),MATCH($E6,'Data_SA'!$1:$1,0)),"")) | K6: =IF($E6="","",IFERROR(INDEX('Data_SA'!$A:$LO,MATCH(I$2,'Data_SA'!$A:$A,0),MATCH($E6,'Data_SA'!$1:$1,0))/INDEX('Data_SA'!$A:$LO,MATCH(EDATE(I$2,-1),'Data_SA'!$A:$A,0),MATCH($E6,'Data_SA'!$1:$1,0))-1,"")) | L6: =IFERROR(INDEX('Data_NSA'!$A:$OK,MATCH(I$2,'Data_NSA'!$A:$A,0),MATCH($D6,'Data_NSA'!$1:$1,0))/INDEX('Data_NSA'!$A:$OK,MATCH(EDATE(I$2,-12),'Data_NSA'!$A:$A,0),MATCH($D6,'Data_NSA'!$1:$1,0))-1,"") | M6: =IFERROR(INDEX('Weights'!$G:$I,MATCH($A6,'Weights'!$A:$A,0),MATCH(I$2,'Weights'!$G$1:$I$1,0)),"") | N6: =IF($E6="","",IFERROR(100*(INDEX('Weights'!$D:$D,MATCH($A6,'Weights'!$A:$A,0))*(INDEX('Data_NSA'!$A:$OK,MATCH(EDATE(I$2,-1),'Data_NSA'!$A:$A,0),MATCH($D6,'Data_NSA'!$1:$1,0))/INDEX('Data_NSA'!$A:$OK,MATCH(INDEX('Weights'!$E:$E,MATCH($A6,'Weights'!$A:$A,0)),'Data_NSA'!$A:$A,0),MATCH($D6,'Data_NSA'!$1:$1,0))))/(100*(INDEX('Data_NSA'!$A:$OK,MATCH(EDATE(I$2,-1),'Data_NSA'!$A:$A,0),MATCH("CUUR0000SA0",'Data_NSA'!$1:$1,0))/INDEX('Data_NSA'!$A:$OK,MATCH(INDEX('Weights'!$E:$E,MATCH($A6,'Weights'!$A:$A,0)),'Data_NSA'!$A:$A,0),MATCH("CUUR0000SA0",'Data_NSA'!$1:$1,0))))*(INDEX('Data_SA'!$A:$LO,MATCH(I$2,'Data_SA'!$A:$A,0),MATCH($E6,'Data_SA'!$1:$1,0))/INDEX('Data_SA'!$A:$LO,MATCH(EDATE(I$2,-1),'Data_SA'!$A:$A,0),MATCH($E6,'Data_SA'!$1:$1,0))-1),"")) | O6: =IFERROR(INDEX('Data_NSA'!$A:$OK,MATCH(O$2,'Data_NSA'!$A:$A,0),MATCH($D6,'Data_NSA'!$1:$1,0)),"") | P6: =IF($E6="","",IFERROR(INDEX('Data_SA'!$A:$LO,MATCH(O$2,'Data_SA'!$A:$A,0),MATCH($E6,'Data_SA'!$1:$1,0)),"")) | Q6: =IF($E6="","",IFERROR(INDEX('Data_SA'!$A:$LO,MATCH(O$2,'Data_SA'!$A:$A,0),MATCH($E6,'Data_SA'!$1:$1,0))/INDEX('Data_SA'!$A:$LO,MATCH(EDATE(O$2,-1),'Data_SA'!$A:$A,0),MATCH($E6,'Data_SA'!$1:$1,0))-1,"")) | R6: =IFERROR(INDEX('Data_NSA'!$A:$OK,MATCH(O$2,'Data_NSA'!$A:$A,0),MATCH($D6,'Data_NSA'!$1:$1,0))/INDEX('Data_NSA'!$A:$OK,MATCH(EDATE(O$2,-12),'Data_NSA'!$A:$A,0),MATCH($D6,'Data_NSA'!$1:$1,0))-1,"") | S6: =IFERROR(INDEX('Weights'!$G:$I,MATCH($A6,'Weights'!$A:$A,0),MATCH(O$2,'Weights'!$G$1:$I$1,0)),"") | T6: =IF($E6="","",IFERROR(100*(INDEX('Weights'!$D:$D,MATCH($A6,'Weights'!$A:$A,0))*(INDEX('Data_NSA'!$A:$OK,MATCH(EDATE(O$2,-1),'Data_NSA'!$A:$A,0),MATCH($D6,'Data_NSA'!$1:$1,0))/INDEX('Data_NSA'!$A:$OK,MATCH(INDEX('Weights'!$E:$E,MATCH($A6,'Weights'!$A:$A,0)),'Data_NSA'!$A:$A,0),MATCH($D6,'Data_NSA'!$1:$1,0))))/(100*(INDEX('Data_NSA'!$A:$OK,MATCH(EDATE(O$2,-1),'Data_NSA'!$A:$A,0),MATCH("CUUR0000SA0",'Data_NSA'!$1:$1,0))/INDEX('Data_NSA'!$A:$OK,MATCH(INDEX('Weights'!$E:$E,MATCH($A6,'Weights'!$A:$A,0)),'Data_NSA'!$A:$A,0),MATCH("CUUR0000SA0",'Data_NSA'!$1:$1,0))))*(INDEX('Data_SA'!$A:$LO,MATCH(O$2,'Data_SA'!$A:$A,0),MATCH($E6,'Data_SA'!$1:$1,0))/INDEX('Data_SA'!$A:$LO,MATCH(EDATE(O$2,-1),'Data_SA'!$A:$A,0),MATCH($E6,'Data_SA'!$1:$1,0))-1),"")) | U6: =IFERROR(INDEX('Data_NSA'!$A:$OK,MATCH(U$2,'Data_NSA'!$A:$A,0),MATCH($D6,'Data_NSA'!$1:$1,0)),"") | V6: =IF($E6="","",IFERROR(INDEX('Data_SA'!$A:$LO,MATCH(U$2,'Data_SA'!$A:$A,0),MATCH($E6,'Data_SA'!$1:$1,0)),"")) | W6: =IF($E6="","",IFERROR(INDEX('Data_SA'!$A:$LO,MATCH(U$2,'Data_SA'!$A:$A,0),MATCH($E6,'Data_SA'!$1:$1,0))/INDEX('Data_SA'!$A:$LO,MATCH(EDATE(U$2,-1),'Data_SA'!$A:$A,0),MATCH($E6,'Data_SA'!$1:$1,0))-1,"")) | X6: =IFERROR(INDEX('Data_NSA'!$A:$OK,MATCH(U$2,'Data_NSA'!$A:$A,0),MATCH($D6,'Data_NSA'!$1:$1,0))/INDEX('Data_NSA'!$A:$OK,MATCH(EDATE(U$2,-12),'Data_NSA'!$A:$A,0),MATCH($D6,'Data_NSA'!$1:$1,0))-1,"") | Y6: =IFERROR(INDEX('Weights'!$G:$I,MATCH($A6,'Weights'!$A:$A,0),MATCH(U$2,'Weights'!$G$1:$I$1,0)),"") | Z6: =IF($E6="","",IFERROR(100*(INDEX('Weights'!$D:$D,MATCH($A6,'Weights'!$A:$A,0))*(INDEX('Data_NSA'!$A:$OK,MATCH(EDATE(U$2,-1),'Data_NSA'!$A:$A,0),MATCH($D6,'Data_NSA'!$1:$1,0))/INDEX('Data_NSA'!$A:$OK,MATCH(INDEX('Weights'!$E:$E,MATCH($A6,'Weights'!$A:$A,0)),'Data_NSA'!$A:$A,0),MATCH($D6,'Data_NSA'!$1:$1,0))))/(100*(INDEX('Data_NSA'!$A:$OK,MATCH(EDATE(U$2,-1),'Data_NSA'!$A:$A,0),MATCH("CUUR0000SA0",'Data_NSA'!$1:$1,0))/INDEX('Data_NSA'!$A:$OK,MATCH(INDEX('Weights'!$E:$E,MATCH($A6,'Weights'!$A:$A,0)),'Data_NSA'!$A:$A,0),MATCH("CUUR0000SA0",'Data_NSA'!$1:$1,0))))*(INDEX('Data_SA'!$A:$LO,MATCH(U$2,'Data_SA'!$A:$A,0),MATCH($E6,'Data_SA'!$1:$1,0))/INDEX('Data_SA'!$A:$LO,MATCH(EDATE(U$2,-1),'Data_SA'!$A:$A,0),MATCH($E6,'Data_SA'!$1:$1,0))-1),""))
A7: SAF1 | B7: Food | C7: SAF | D7: CUUR0000SAF1 | E7: CUSR0000SAF1 | F7: aggregate | G7: aggregate | H7: =IFERROR(INDEX(Weights!$D:$D,MATCH($A7,Weights!$A:$A,0)),"") | I7: =IFERROR(INDEX('Data_NSA'!$A:$OK,MATCH(I$2,'Data_NSA'!$A:$A,0),MATCH($D7,'Data_NSA'!$1:$1,0)),"") | J7: =IF($E7="","",IFERROR(INDEX('Data_SA'!$A:$LO,MATCH(I$2,'Data_SA'!$A:$A,0),MATCH($E7,'Data_SA'!$1:$1,0)),"")) | K7: =IF($E7="","",IFERROR(INDEX('Data_SA'!$A:$LO,MATCH(I$2,'Data_SA'!$A:$A,0),MATCH($E7,'Data_SA'!$1:$1,0))/INDEX('Data_SA'!$A:$LO,MATCH(EDATE(I$2,-1),'Data_SA'!$A:$A,0),MATCH($E7,'Data_SA'!$1:$1,0))-1,"")) | L7: =IFERROR(INDEX('Data_NSA'!$A:$OK,MATCH(I$2,'Data_NSA'!$A:$A,0),MATCH($D7,'Data_NSA'!$1:$1,0))/INDEX('Data_NSA'!$A:$OK,MATCH(EDATE(I$2,-12),'Data_NSA'!$A:$A,0),MATCH($D7,'Data_NSA'!$1:$1,0))-1,"") | M7: =IFERROR(INDEX('Weights'!$G:$I,MATCH($A7,'Weights'!$A:$A,0),MATCH(I$2,'Weights'!$G$1:$I$1,0)),"") | N7: =IF($E7="","",IFERROR(100*(INDEX('Weights'!$D:$D,MATCH($A7,'Weights'!$A:$A,0))*(INDEX('Data_NSA'!$A:$OK,MATCH(EDATE(I$2,-1),'Data_NSA'!$A:$A,0),MATCH($D7,'Data_NSA'!$1:$1,0))/INDEX('Data_NSA'!$A:$OK,MATCH(INDEX('Weights'!$E:$E,MATCH($A7,'Weights'!$A:$A,0)),'Data_NSA'!$A:$A,0),MATCH($D7,'Data_NSA'!$1:$1,0))))/(100*(INDEX('Data_NSA'!$A:$OK,MATCH(EDATE(I$2,-1),'Data_NSA'!$A:$A,0),MATCH("CUUR0000SA0",'Data_NSA'!$1:$1,0))/INDEX('Data_NSA'!$A:$OK,MATCH(INDEX('Weights'!$E:$E,MATCH($A7,'Weights'!$A:$A,0)),'Data_NSA'!$A:$A,0),MATCH("CUUR0000SA0",'Data_NSA'!$1:$1,0))))*(INDEX('Data_SA'!$A:$LO,MATCH(I$2,'Data_SA'!$A:$A,0),MATCH($E7,'Data_SA'!$1:$1,0))/INDEX('Data_SA'!$A:$LO,MATCH(EDATE(I$2,-1),'Data_SA'!$A:$A,0),MATCH($E7,'Data_SA'!$1:$1,0))-1),"")) | O7: =IFERROR(INDEX('Data_NSA'!$A:$OK,MATCH(O$2,'Data_NSA'!$A:$A,0),MATCH($D7,'Data_NSA'!$1:$1,0)),"") | P7: =IF($E7="","",IFERROR(INDEX('Data_SA'!$A:$LO,MATCH(O$2,'Data_SA'!$A:$A,0),MATCH($E7,'Data_SA'!$1:$1,0)),"")) | Q7: =IF($E7="","",IFERROR(INDEX('Data_SA'!$A:$LO,MATCH(O$2,'Data_SA'!$A:$A,0),MATCH($E7,'Data_SA'!$1:$1,0))/INDEX('Data_SA'!$A:$LO,MATCH(EDATE(O$2,-1),'Data_SA'!$A:$A,0),MATCH($E7,'Data_SA'!$1:$1,0))-1,"")) | R7: =IFERROR(INDEX('Data_NSA'!$A:$OK,MATCH(O$2,'Data_NSA'!$A:$A,0),MATCH($D7,'Data_NSA'!$1:$1,0))/INDEX('Data_NSA'!$A:$OK,MATCH(EDATE(O$2,-12),'Data_NSA'!$A:$A,0),MATCH($D7,'Data_NSA'!$1:$1,0))-1,"") | S7: =IFERROR(INDEX('Weights'!$G:$I,MATCH($A7,'Weights'!$A:$A,0),MATCH(O$2,'Weights'!$G$1:$I$1,0)),"") | T7: =IF($E7="","",IFERROR(100*(INDEX('Weights'!$D:$D,MATCH($A7,'Weights'!$A:$A,0))*(INDEX('Data_NSA'!$A:$OK,MATCH(EDATE(O$2,-1),'Data_NSA'!$A:$A,0),MATCH($D7,'Data_NSA'!$1:$1,0))/INDEX('Data_NSA'!$A:$OK,MATCH(INDEX('Weights'!$E:$E,MATCH($A7,'Weights'!$A:$A,0)),'Data_NSA'!$A:$A,0),MATCH($D7,'Data_NSA'!$1:$1,0))))/(100*(INDEX('Data_NSA'!$A:$OK,MATCH(EDATE(O$2,-1),'Data_NSA'!$A:$A,0),MATCH("CUUR0000SA0",'Data_NSA'!$1:$1,0))/INDEX('Data_NSA'!$A:$OK,MATCH(INDEX('Weights'!$E:$E,MATCH($A7,'Weights'!$A:$A,0)),'Data_NSA'!$A:$A,0),MATCH("CUUR0000SA0",'Data_NSA'!$1:$1,0))))*(INDEX('Data_SA'!$A:$LO,MATCH(O$2,'Data_SA'!$A:$A,0),MATCH($E7,'Data_SA'!$1:$1,0))/INDEX('Data_SA'!$A:$LO,MATCH(EDATE(O$2,-1),'Data_SA'!$A:$A,0),MATCH($E7,'Data_SA'!$1:$1,0))-1),"")) | U7: =IFERROR(INDEX('Data_NSA'!$A:$OK,MATCH(U$2,'Data_NSA'!$A:$A,0),MATCH($D7,'Data_NSA'!$1:$1,0)),"") | V7: =IF($E7="","",IFERROR(INDEX('Data_SA'!$A:$LO,MATCH(U$2,'Data_SA'!$A:$A,0),MATCH($E7,'Data_SA'!$1:$1,0)),"")) | W7: =IF($E7="","",IFERROR(INDEX('Data_SA'!$A:$LO,MATCH(U$2,'Data_SA'!$A:$A,0),MATCH($E7,'Data_SA'!$1:$1,0))/INDEX('Data_SA'!$A:$LO,MATCH(EDATE(U$2,-1),'Data_SA'!$A:$A,0),MATCH($E7,'Data_SA'!$1:$1,0))-1,"")) | X7: =IFERROR(INDEX('Data_NSA'!$A:$OK,MATCH(U$2,'Data_NSA'!$A:$A,0),MATCH($D7,'Data_NSA'!$1:$1,0))/INDEX('Data_NSA'!$A:$OK,MATCH(EDATE(U$2,-12),'Data_NSA'!$A:$A,0),MATCH($D7,'Data_NSA'!$1:$1,0))-1,"") | Y7: =IFERROR(INDEX('Weights'!$G:$I,MATCH($A7,'Weights'!$A:$A,0),MATCH(U$2,'Weights'!$G$1:$I$1,0)),"") | Z7: =IF($E7="","",IFERROR(100*(INDEX('Weights'!$D:$D,MATCH($A7,'Weights'!$A:$A,0))*(INDEX('Data_NSA'!$A:$OK,MATCH(EDATE(U$2,-1),'Data_NSA'!$A:$A,0),MATCH($D7,'Data_NSA'!$1:$1,0))/INDEX('Data_NSA'!$A:$OK,MATCH(INDEX('Weights'!$E:$E,MATCH($A7,'Weights'!$A:$A,0)),'Data_NSA'!$A:$A,0),MATCH($D7,'Data_NSA'!$1:$1,0))))/(100*(INDEX('Data_NSA'!$A:$OK,MATCH(EDATE(U$2,-1),'Data_NSA'!$A:$A,0),MATCH("CUUR0000SA0",'Data_NSA'!$1:$1,0))/INDEX('Data_NSA'!$A:$OK,MATCH(INDEX('Weights'!$E:$E,MATCH($A7,'Weights'!$A:$A,0)),'Data_NSA'!$A:$A,0),MATCH("CUUR0000SA0",'Data_NSA'!$1:$1,0))))*(INDEX('Data_SA'!$A:$LO,MATCH(U$2,'Data_SA'!$A:$A,0),MATCH($E7,'Data_SA'!$1:$1,0))/INDEX('Data_SA'!$A:$LO,MATCH(EDATE(U$2,-1),'Data_SA'!$A:$A,0),MATCH($E7,'Data_SA'!$1:$1,0))-1),""))
A8: SAF11 | B8: Food at home | C8: SAF1 | D8: CUUR0000SAF11 | E8: CUSR0000SAF11 | F8: GM | G8: direct collection; monthly in all areas | H8: =IFERROR(INDEX(Weights!$D:$D,MATCH($A8,Weights!$A:$A,0)),"") | I8: =IFERROR(INDEX('Data_NSA'!$A:$OK,MATCH(I$2,'Data_NSA'!$A:$A,0),MATCH($D8,'Data_NSA'!$1:$1,0)),"") | J8: =IF($E8="","",IFERROR(INDEX('Data_SA'!$A:$LO,MATCH(I$2,'Data_SA'!$A:$A,0),MATCH($E8,'Data_SA'!$1:$1,0)),"")) | K8: =IF($E8="","",IFERROR(INDEX('Data_SA'!$A:$LO,MATCH(I$2,'Data_SA'!$A:$A,0),MATCH($E8,'Data_SA'!$1:$1,0))/INDEX('Data_SA'!$A:$LO,MATCH(EDATE(I$2,-1),'Data_SA'!$A:$A,0),MATCH($E8,'Data_SA'!$1:$1,0))-1,"")) | L8: =IFERROR(INDEX('Data_NSA'!$A:$OK,MATCH(I$2,'Data_NSA'!$A:$A,0),MATCH($D8,'Data_NSA'!$1:$1,0))/INDEX('Data_NSA'!$A:$OK,MATCH(EDATE(I$2,-12),'Data_NSA'!$A:$A,0),MATCH($D8,'Data_NSA'!$1:$1,0))-1,"") | M8: =IFERROR(INDEX('Weights'!$G:$I,MATCH($A8,'Weights'!$A:$A,0),MATCH(I$2,'Weights'!$G$1:$I$1,0)),"") | N8: =IF($E8="","",IFERROR(100*(INDEX('Weights'!$D:$D,MATCH($A8,'Weights'!$A:$A,0))*(INDEX('Data_NSA'!$A:$OK,MATCH(EDATE(I$2,-1),'Data_NSA'!$A:$A,0),MATCH($D8,'Data_NSA'!$1:$1,0))/INDEX('Data_NSA'!$A:$OK,MATCH(INDEX('Weights'!$E:$E,MATCH($A8,'Weights'!$A:$A,0)),'Data_NSA'!$A:$A,0),MATCH($D8,'Data_NSA'!$1:$1,0))))/(100*(INDEX('Data_NSA'!$A:$OK,MATCH(EDATE(I$2,-1),'Data_NSA'!$A:$A,0),MATCH("CUUR0000SA0",'Data_NSA'!$1:$1,0))/INDEX('Data_NSA'!$A:$OK,MATCH(INDEX('Weights'!$E:$E,MATCH($A8,'Weights'!$A:$A,0)),'Data_NSA'!$A:$A,0),MATCH("CUUR0000SA0",'Data_NSA'!$1:$1,0))))*(INDEX('Data_SA'!$A:$LO,MATCH(I$2,'Data_SA'!$A:$A,0),MATCH($E8,'Data_SA'!$1:$1,0))/INDEX('Data_SA'!$A:$LO,MATCH(EDATE(I$2,-1),'Data_SA'!$A:$A,0),MATCH($E8,'Data_SA'!$1:$1,0))-1),"")) | O8: =IFERROR(INDEX('Data_NSA'!$A:$OK,MATCH(O$2,'Data_NSA'!$A:$A,0),MATCH($D8,'Data_NSA'!$1:$1,0)),"") | P8: =IF($E8="","",IFERROR(INDEX('Data_SA'!$A:$LO,MATCH(O$2,'Data_SA'!$A:$A,0),MATCH($E8,'Data_SA'!$1:$1,0)),"")) | Q8: =IF($E8="","",IFERROR(INDEX('Data_SA'!$A:$LO,MATCH(O$2,'Data_SA'!$A:$A,0),MATCH($E8,'Data_SA'!$1:$1,0))/INDEX('Data_SA'!$A:$LO,MATCH(EDATE(O$2,-1),'Data_SA'!$A:$A,0),MATCH($E8,'Data_SA'!$1:$1,0))-1,"")) | R8: =IFERROR(INDEX('Data_NSA'!$A:$OK,MATCH(O$2,'Data_NSA'!$A:$A,0),MATCH($D8,'Data_NSA'!$1:$1,0))/INDEX('Data_NSA'!$A:$OK,MATCH(EDATE(O$2,-12),'Data_NSA'!$A:$A,0),MATCH($D8,'Data_NSA'!$1:$1,0))-1,"") | S8: =IFERROR(INDEX('Weights'!$G:$I,MATCH($A8,'Weights'!$A:$A,0),MATCH(O$2,'Weights'!$G$1:$I$1,0)),"") | T8: =IF($E8="","",IFERROR(100*(INDEX('Weights'!$D:$D,MATCH($A8,'Weights'!$A:$A,0))*(INDEX('Data_NSA'!$A:$OK,MATCH(EDATE(O$2,-1),'Data_NSA'!$A:$A,0),MATCH($D8,'Data_NSA'!$1:$1,0))/INDEX('Data_NSA'!$A:$OK,MATCH(INDEX('Weights'!$E:$E,MATCH($A8,'Weights'!$A:$A,0)),'Data_NSA'!$A:$A,0),MATCH($D8,'Data_NSA'!$1:$1,0))))/(100*(INDEX('Data_NSA'!$A:$OK,MATCH(EDATE(O$2,-1),'Data_NSA'!$A:$A,0),MATCH("CUUR0000SA0",'Data_NSA'!$1:$1,0))/INDEX('Data_NSA'!$A:$OK,MATCH(INDEX('Weights'!$E:$E,MATCH($A8,'Weights'!$A:$A,0)),'Data_NSA'!$A:$A,0),MATCH("CUUR0000SA0",'Data_NSA'!$1:$1,0))))*(INDEX('Data_SA'!$A:$LO,MATCH(O$2,'Data_SA'!$A:$A,0),MATCH($E8,'Data_SA'!$1:$1,0))/INDEX('Data_SA'!$A:$LO,MATCH(EDATE(O$2,-1),'Data_SA'!$A:$A,0),MATCH($E8,'Data_SA'!$1:$1,0))-1),"")) | U8: =IFERROR(INDEX('Data_NSA'!$A:$OK,MATCH(U$2,'Data_NSA'!$A:$A,0),MATCH($D8,'Data_NSA'!$1:$1,0)),"") | V8: =IF($E8="","",IFERROR(INDEX('Data_SA'!$A:$LO,MATCH(U$2,'Data_SA'!$A:$A,0),MATCH($E8,'Data_SA'!$1:$1,0)),"")) | W8: =IF($E8="","",IFERROR(INDEX('Data_SA'!$A:$LO,MATCH(U$2,'Data_SA'!$A:$A,0),MATCH($E8,'Data_SA'!$1:$1,0))/INDEX('Data_SA'!$A:$LO,MATCH(EDATE(U$2,-1),'Data_SA'!$A:$A,0),MATCH($E8,'Data_SA'!$1:$1,0))-1,"")) | X8: =IFERROR(INDEX('Data_NSA'!$A:$OK,MATCH(U$2,'Data_NSA'!$A:$A,0),MATCH($D8,'Data_NSA'!$1:$1,0))/INDEX('Data_NSA'!$A:$OK,MATCH(EDATE(U$2,-12),'Data_NSA'!$A:$A,0),MATCH($D8,'Data_NSA'!$1:$1,0))-1,"") | Y8: =IFERROR(INDEX('Weights'!$G:$I,MATCH($A8,'Weights'!$A:$A,0),MATCH(U$2,'Weights'!$G$1:$I$1,0)),"") | Z8: =IF($E8="","",IFERROR(100*(INDEX('Weights'!$D:$D,MATCH($A8,'Weights'!$A:$A,0))*(INDEX('Data_NSA'!$A:$OK,MATCH(EDATE(U$2,-1),'Data_NSA'!$A:$A,0),MATCH($D8,'Data_NSA'!$1:$1,0))/INDEX('Data_NSA'!$A:$OK,MATCH(INDEX('Weights'!$E:$E,MATCH($A8,'Weights'!$A:$A,0)),'Data_NSA'!$A:$A,0),MATCH($D8,'Data_NSA'!$1:$1,0))))/(100*(INDEX('Data_NSA'!$A:$OK,MATCH(EDATE(U$2,-1),'Data_NSA'!$A:$A,0),MATCH("CUUR0000SA0",'Data_NSA'!$1:$1,0))/INDEX('Data_NSA'!$A:$OK,MATCH(INDEX('Weights'!$E:$E,MATCH($A8,'Weights'!$A:$A,0)),'Data_NSA'!$A:$A,0),MATCH("CUUR0000SA0",'Data_NSA'!$1:$1,0))))*(INDEX('Data_SA'!$A:$LO,MATCH(U$2,'Data_SA'!$A:$A,0),MATCH($E8,'Data_SA'!$1:$1,0))/INDEX('Data_SA'!$A:$LO,MATCH(EDATE(U$2,-1),'Data_SA'!$A:$A,0),MATCH($E8,'Data_SA'!$1:$1,0))-1),""))
A9: SAF111 | B9: Cereals and bakery products | C9: SAF11 | D9: CUUR0000SAF111 | E9: CUSR0000SAF111 | F9: GM | G9: monthly | H9: =IFERROR(INDEX(Weights!$D:$D,MATCH($A9,Weights!$A:$A,0)),"") | I9: =IFERROR(INDEX('Data_NSA'!$A:$OK,MATCH(I$2,'Data_NSA'!$A:$A,0),MATCH($D9,'Data_NSA'!$1:$1,0)),"") | J9: =IF($E9="","",IFERROR(INDEX('Data_SA'!$A:$LO,MATCH(I$2,'Data_SA'!$A:$A,0),MATCH($E9,'Data_SA'!$1:$1,0)),"")) | K9: =IF($E9="","",IFERROR(INDEX('Data_SA'!$A:$LO,MATCH(I$2,'Data_SA'!$A:$A,0),MATCH($E9,'Data_SA'!$1:$1,0))/INDEX('Data_SA'!$A:$LO,MATCH(EDATE(I$2,-1),'Data_SA'!$A:$A,0),MATCH($E9,'Data_SA'!$1:$1,0))-1,"")) | L9: =IFERROR(INDEX('Data_NSA'!$A:$OK,MATCH(I$2,'Data_NSA'!$A:$A,0),MATCH($D9,'Data_NSA'!$1:$1,0))/INDEX('Data_NSA'!$A:$OK,MATCH(EDATE(I$2,-12),'Data_NSA'!$A:$A,0),MATCH($D9,'Data_NSA'!$1:$1,0))-1,"") | M9: =IFERROR(INDEX('Weights'!$G:$I,MATCH($A9,'Weights'!$A:$A,0),MATCH(I$2,'Weights'!$G$1:$I$1,0)),"") | N9: =IF($E9="","",IFERROR(100*(INDEX('Weights'!$D:$D,MATCH($A9,'Weights'!$A:$A,0))*(INDEX('Data_NSA'!$A:$OK,MATCH(EDATE(I$2,-1),'Data_NSA'!$A:$A,0),MATCH($D9,'Data_NSA'!$1:$1,0))/INDEX('Data_NSA'!$A:$OK,MATCH(INDEX('Weights'!$E:$E,MATCH($A9,'Weights'!$A:$A,0)),'Data_NSA'!$A:$A,0),MATCH($D9,'Data_NSA'!$1:$1,0))))/(100*(INDEX('Data_NSA'!$A:$OK,MATCH(EDATE(I$2,-1),'Data_NSA'!$A:$A,0),MATCH("CUUR0000SA0",'Data_NSA'!$1:$1,0))/INDEX('Data_NSA'!$A:$OK,MATCH(INDEX('Weights'!$E:$E,MATCH($A9,'Weights'!$A:$A,0)),'Data_NSA'!$A:$A,0),MATCH("CUUR0000SA0",'Data_NSA'!$1:$1,0))))*(INDEX('Data_SA'!$A:$LO,MATCH(I$2,'Data_SA'!$A:$A,0),MATCH($E9,'Data_SA'!$1:$1,0))/INDEX('Data_SA'!$A:$LO,MATCH(EDATE(I$2,-1),'Data_SA'!$A:$A,0),MATCH($E9,'Data_SA'!$1:$1,0))-1),"")) | O9: =IFERROR(INDEX('Data_NSA'!$A:$OK,MATCH(O$2,'Data_NSA'!$A:$A,0),MATCH($D9,'Data_NSA'!$1:$1,0)),"") | P9: =IF($E9="","",IFERROR(INDEX('Data_SA'!$A:$LO,MATCH(O$2,'Data_SA'!$A:$A,0),MATCH($E9,'Data_SA'!$1:$1,0)),"")) | Q9: =IF($E9="","",IFERROR(INDEX('Data_SA'!$A:$LO,MATCH(O$2,'Data_SA'!$A:$A,0),MATCH($E9,'Data_SA'!$1:$1,0))/INDEX('Data_SA'!$A:$LO,MATCH(EDATE(O$2,-1),'Data_SA'!$A:$A,0),MATCH($E9,'Data_SA'!$1:$1,0))-1,"")) | R9: =IFERROR(INDEX('Data_NSA'!$A:$OK,MATCH(O$2,'Data_NSA'!$A:$A,0),MATCH($D9,'Data_NSA'!$1:$1,0))/INDEX('Data_NSA'!$A:$OK,MATCH(EDATE(O$2,-12),'Data_NSA'!$A:$A,0),MATCH($D9,'Data_NSA'!$1:$1,0))-1,"") | S9: =IFERROR(INDEX('Weights'!$G:$I,MATCH($A9,'Weights'!$A:$A,0),MATCH(O$2,'Weights'!$G$1:$I$1,0)),"") | T9: =IF($E9="","",IFERROR(100*(INDEX('Weights'!$D:$D,MATCH($A9,'Weights'!$A:$A,0))*(INDEX('Data_NSA'!$A:$OK,MATCH(EDATE(O$2,-1),'Data_NSA'!$A:$A,0),MATCH($D9,'Data_NSA'!$1:$1,0))/INDEX('Data_NSA'!$A:$OK,MATCH(INDEX('Weights'!$E:$E,MATCH($A9,'Weights'!$A:$A,0)),'Data_NSA'!$A:$A,0),MATCH($D9,'Data_NSA'!$1:$1,0))))/(100*(INDEX('Data_NSA'!$A:$OK,MATCH(EDATE(O$2,-1),'Data_NSA'!$A:$A,0),MATCH("CUUR0000SA0",'Data_NSA'!$1:$1,0))/INDEX('Data_NSA'!$A:$OK,MATCH(INDEX('Weights'!$E:$E,MATCH($A9,'Weights'!$A:$A,0)),'Data_NSA'!$A:$A,0),MATCH("CUUR0000SA0",'Data_NSA'!$1:$1,0))))*(INDEX('Data_SA'!$A:$LO,MATCH(O$2,'Data_SA'!$A:$A,0),MATCH($E9,'Data_SA'!$1:$1,0))/INDEX('Data_SA'!$A:$LO,MATCH(EDATE(O$2,-1),'Data_SA'!$A:$A,0),MATCH($E9,'Data_SA'!$1:$1,0))-1),"")) | U9: =IFERROR(INDEX('Data_NSA'!$A:$OK,MATCH(U$2,'Data_NSA'!$A:$A,0),MATCH($D9,'Data_NSA'!$1:$1,0)),"") | V9: =IF($E9="","",IFERROR(INDEX('Data_SA'!$A:$LO,MATCH(U$2,'Data_SA'!$A:$A,0),MATCH($E9,'Data_SA'!$1:$1,0)),"")) | W9: =IF($E9="","",IFERROR(INDEX('Data_SA'!$A:$LO,MATCH(U$2,'Data_SA'!$A:$A,0),MATCH($E9,'Data_SA'!$1:$1,0))/INDEX('Data_SA'!$A:$LO,MATCH(EDATE(U$2,-1),'Data_SA'!$A:$A,0),MATCH($E9,'Data_SA'!$1:$1,0))-1,"")) | X9: =IFERROR(INDEX('Data_NSA'!$A:$OK,MATCH(U$2,'Data_NSA'!$A:$A,0),MATCH($D9,'Data_NSA'!$1:$1,0))/INDEX('Data_NSA'!$A:$OK,MATCH(EDATE(U$2,-12),'Data_NSA'!$A:$A,0),MATCH($D9,'Data_NSA'!$1:$1,0))-1,"") | Y9: =IFERROR(INDEX('Weights'!$G:$I,MATCH($A9,'Weights'!$A:$A,0),MATCH(U$2,'Weights'!$G$1:$I$1,0)),"") | Z9: =IF($E9="","",IFERROR(100*(INDEX('Weights'!$D:$D,MATCH($A9,'Weights'!$A:$A,0))*(INDEX('Data_NSA'!$A:$OK,MATCH(EDATE(U$2,-1),'Data_NSA'!$A:$A,0),MATCH($D9,'Data_NSA'!$1:$1,0))/INDEX('Data_NSA'!$A:$OK,MATCH(INDEX('Weights'!$E:$E,MATCH($A9,'Weights'!$A:$A,0)),'Data_NSA'!$A:$A,0),MATCH($D9,'Data_NSA'!$1:$1,0))))/(100*(INDEX('Data_NSA'!$A:$OK,MATCH(EDATE(U$2,-1),'Data_NSA'!$A:$A,0),MATCH("CUUR0000SA0",'Data_NSA'!$1:$1,0))/INDEX('Data_NSA'!$A:$OK,MATCH(INDEX('Weights'!$E:$E,MATCH($A9,'Weights'!$A:$A,0)),'Data_NSA'!$A:$A,0),MATCH("CUUR0000SA0",'Data_NSA'!$1:$1,0))))*(INDEX('Data_SA'!$A:$LO,MATCH(U$2,'Data_SA'!$A:$A,0),MATCH($E9,'Data_SA'!$1:$1,0))/INDEX('Data_SA'!$A:$LO,MATCH(EDATE(U$2,-1),'Data_SA'!$A:$A,0),MATCH($E9,'Data_SA'!$1:$1,0))-1),""))
A10: SEFA | B10: Cereals and cereal products | C10: SAF111 | D10: CUUR0000SEFA | E10: CUSR0000SEFA | F10: aggregate | G10: aggregate | H10: =IFERROR(INDEX(Weights!$D:$D,MATCH($A10,Weights!$A:$A,0)),"") | I10: =IFERROR(INDEX('Data_NSA'!$A:$OK,MATCH(I$2,'Data_NSA'!$A:$A,0),MATCH($D10,'Data_NSA'!$1:$1,0)),"") | J10: =IF($E10="","",IFERROR(INDEX('Data_SA'!$A:$LO,MATCH(I$2,'Data_SA'!$A:$A,0),MATCH($E10,'Data_SA'!$1:$1,0)),"")) | K10: =IF($E10="","",IFERROR(INDEX('Data_SA'!$A:$LO,MATCH(I$2,'Data_SA'!$A:$A,0),MATCH($E10,'Data_SA'!$1:$1,0))/INDEX('Data_SA'!$A:$LO,MATCH(EDATE(I$2,-1),'Data_SA'!$A:$A,0),MATCH($E10,'Data_SA'!$1:$1,0))-1,"")) | L10: =IFERROR(INDEX('Data_NSA'!$A:$OK,MATCH(I$2,'Data_NSA'!$A:$A,0),MATCH($D10,'Data_NSA'!$1:$1,0))/INDEX('Data_NSA'!$A:$OK,MATCH(EDATE(I$2,-12),'Data_NSA'!$A:$A,0),MATCH($D10,'Data_NSA'!$1:$1,0))-1,"") | M10: =IFERROR(INDEX('Weights'!$G:$I,MATCH($A10,'Weights'!$A:$A,0),MATCH(I$2,'Weights'!$G$1:$I$1,0)),"") | N10: =IF($E10="","",IFERROR(100*(INDEX('Weights'!$D:$D,MATCH($A10,'Weights'!$A:$A,0))*(INDEX('Data_NSA'!$A:$OK,MATCH(EDATE(I$2,-1),'Data_NSA'!$A:$A,0),MATCH($D10,'Data_NSA'!$1:$1,0))/INDEX('Data_NSA'!$A:$OK,MATCH(INDEX('Weights'!$E:$E,MATCH($A10,'Weights'!$A:$A,0)),'Data_NSA'!$A:$A,0),MATCH($D10,'Data_NSA'!$1:$1,0))))/(100*(INDEX('Data_NSA'!$A:$OK,MATCH(EDATE(I$2,-1),'Data_NSA'!$A:$A,0),MATCH("CUUR0000SA0",'Data_NSA'!$1:$1,0))/INDEX('Data_NSA'!$A:$OK,MATCH(INDEX('Weights'!$E:$E,MATCH($A10,'Weights'!$A:$A,0)),'Data_NSA'!$A:$A,0),MATCH("CUUR0000SA0",'Data_NSA'!$1:$1,0))))*(INDEX('Data_SA'!$A:$LO,MATCH(I$2,'Data_SA'!$A:$A,0),MATCH($E10,'Data_SA'!$1:$1,0))/INDEX('Data_SA'!$A:$LO,MATCH(EDATE(I$2,-1),'Data_SA'!$A:$A,0),MATCH($E10,'Data_SA'!$1:$1,0))-1),"")) | O10: =IFERROR(INDEX('Data_NSA'!$A:$OK,MATCH(O$2,'Data_NSA'!$A:$A,0),MATCH($D10,'Data_NSA'!$1:$1,0)),"") | P10: =IF($E10="","",IFERROR(INDEX('Data_SA'!$A:$LO,MATCH(O$2,'Data_SA'!$A:$A,0),MATCH($E10,'Data_SA'!$1:$1,0)),"")) | Q10: =IF($E10="","",IFERROR(INDEX('Data_SA'!$A:$LO,MATCH(O$2,'Data_SA'!$A:$A,0),MATCH($E10,'Data_SA'!$1:$1,0))/INDEX('Data_SA'!$A:$LO,MATCH(EDATE(O$2,-1),'Data_SA'!$A:$A,0),MATCH($E10,'Data_SA'!$1:$1,0))-1,"")) | R10: =IFERROR(INDEX('Data_NSA'!$A:$OK,MATCH(O$2,'Data_NSA'!$A:$A,0),MATCH($D10,'Data_NSA'!$1:$1,0))/INDEX('Data_NSA'!$A:$OK,MATCH(EDATE(O$2,-12),'Data_NSA'!$A:$A,0),MATCH($D10,'Data_NSA'!$1:$1,0))-1,"") | S10: =IFERROR(INDEX('Weights'!$G:$I,MATCH($A10,'Weights'!$A:$A,0),MATCH(O$2,'Weights'!$G$1:$I$1,0)),"") | T10: =IF($E10="","",IFERROR(100*(INDEX('Weights'!$D:$D,MATCH($A10,'Weights'!$A:$A,0))*(INDEX('Data_NSA'!$A:$OK,MATCH(EDATE(O$2,-1),'Data_NSA'!$A:$A,0),MATCH($D10,'Data_NSA'!$1:$1,0))/INDEX('Data_NSA'!$A:$OK,MATCH(INDEX('Weights'!$E:$E,MATCH($A10,'Weights'!$A:$A,0)),'Data_NSA'!$A:$A,0),MATCH($D10,'Data_NSA'!$1:$1,0))))/(100*(INDEX('Data_NSA'!$A:$OK,MATCH(EDATE(O$2,-1),'Data_NSA'!$A:$A,0),MATCH("CUUR0000SA0",'Data_NSA'!$1:$1,0))/INDEX('Data_NSA'!$A:$OK,MATCH(INDEX('Weights'!$E:$E,MATCH($A10,'Weights'!$A:$A,0)),'Data_NSA'!$A:$A,0),MATCH("CUUR0000SA0",'Data_NSA'!$1:$1,0))))*(INDEX('Data_SA'!$A:$LO,MATCH(O$2,'Data_SA'!$A:$A,0),MATCH($E10,'Data_SA'!$1:$1,0))/INDEX('Data_SA'!$A:$LO,MATCH(EDATE(O$2,-1),'Data_SA'!$A:$A,0),MATCH($E10,'Data_SA'!$1:$1,0))-1),"")) | U10: =IFERROR(INDEX('Data_NSA'!$A:$OK,MATCH(U$2,'Data_NSA'!$A:$A,0),MATCH($D10,'Data_NSA'!$1:$1,0)),"") | V10: =IF($E10="","",IFERROR(INDEX('Data_SA'!$A:$LO,MATCH(U$2,'Data_SA'!$A:$A,0),MATCH($E10,'Data_SA'!$1:$1,0)),"")) | W10: =IF($E10="","",IFERROR(INDEX('Data_SA'!$A:$LO,MATCH(U$2,'Data_SA'!$A:$A,0),MATCH($E10,'Data_SA'!$1:$1,0))/INDEX('Data_SA'!$A:$LO,MATCH(EDATE(U$2,-1),'Data_SA'!$A:$A,0),MATCH($E10,'Data_SA'!$1:$1,0))-1,"")) | X10: =IFERROR(INDEX('Data_NSA'!$A:$OK,MATCH(U$2,'Data_NSA'!$A:$A,0),MATCH($D10,'Data_NSA'!$1:$1,0))/INDEX('Data_NSA'!$A:$OK,MATCH(EDATE(U$2,-12),'Data_NSA'!$A:$A,0),MATCH($D10,'Data_NSA'!$1:$1,0))-1,"") | Y10: =IFERROR(INDEX('Weights'!$G:$I,MATCH($A10,'Weights'!$A:$A,0),MATCH(U$2,'Weights'!$G$1:$I$1,0)),"") | Z10: =IF($E10="","",IFERROR(100*(INDEX('Weights'!$D:$D,MATCH($A10,'Weights'!$A:$A,0))*(INDEX('Data_NSA'!$A:$OK,MATCH(EDATE(U$2,-1),'Data_NSA'!$A:$A,0),MATCH($D10,'Data_NSA'!$1:$1,0))/INDEX('Data_NSA'!$A:$OK,MATCH(INDEX('Weights'!$E:$E,MATCH($A10,'Weights'!$A:$A,0)),'Data_NSA'!$A:$A,0),MATCH($D10,'Data_NSA'!$1:$1,0))))/(100*(INDEX('Data_NSA'!$A:$OK,MATCH(EDATE(U$2,-1),'Data_NSA'!$A:$A,0),MATCH("CUUR0000SA0",'Data_NSA'!$1:$1,0))/INDEX('Data_NSA'!$A:$OK,MATCH(INDEX('Weights'!$E:$E,MATCH($A10,'Weights'!$A:$A,0)),'Data_NSA'!$A:$A,0),MATCH("CUUR0000SA0",'Data_NSA'!$1:$1,0))))*(INDEX('Data_SA'!$A:$LO,MATCH(U$2,'Data_SA'!$A:$A,0),MATCH($E10,'Data_SA'!$1:$1,0))/INDEX('Data_SA'!$A:$LO,MATCH(EDATE(U$2,-1),'Data_SA'!$A:$A,0),MATCH($E10,'Data_SA'!$1:$1,0))-1),""))
